cocotb_Test/action/crc32_comb.v
module crc32_comb
#(parameter crc_len =32, parameter crc =  32'h04C11DB7, parameter GMII = 1, parameter datalen = 8, parameter refin = 1, parameter refout = 1)
(
input updatecrc,                                                    
output reg [crc_len-1:0]result,
input clk,rst,strt,
input  [datalen-1:0] data
);

reg [crc_len-1:0]   crc_poly        = crc;
reg [crc_len-1:0]   crc_acc         = {(crc_len){1'b1}};  //Initiate acc
reg [11:0]          byte_count =0;                                  //Keep track of bytes
reg [4:0]           bit_n = 0;                                      //Keep track of bites
reg [crc_len-1:0]   nresult  ;
reg [datalen-1:0] data_buf;
reg [crc_len-1:0] crc_acc_n;


`ifdef COCOTB_SIM
initial begin
    $dumpfile("sim.vcd");
    $dumpvars(0,crc32_comb);
end    
`endif


generate if (GMII) begin
        
            always @(*) begin

                if(rst) begin
                    crc_acc     <= {(crc_len){1'b1}};
                    result      <=  0;
                    byte_count  <=  0;
                    crc_acc_n   <= {(crc_len){1'b1}};
                    nresult     <=  0;
                    data_buf    <=  0;
                    bit_n       <=  0;
                end

                else begin
                    crc_acc = crc_acc_n;
                end
            end

            always @(posedge clk) begin
                if (updatecrc) begin
                    $display("\n New data %h, \t %b",data,data);

                    data_buf = reflect_byte(data[datalen-1:0]);

                    crc_acc_n =  {data_buf,{(crc_len-datalen){1'b0}}}^ crc_acc_n;
                    $display("1|| \t CRC %h, \t %b", crc_acc_n ,crc_acc_n );
                    
                    for (bit_n = 0; bit_n <datalen ; bit_n =bit_n +1 ) begin // loop count = datalen-crc+1 d = 8, crc = 4 , loop = 7
                        crc_acc_n = crc_bit_updt(crc_acc_n[crc_len-1:0],crc[crc_len-1:0],crc_acc_n[crc_len-1]);
                    $display("2_ %d|| \t CRC %h, \t %b", bit_n,crc_acc_n ,crc_acc_n );
                    end
                    bit_n       <=  0;
                    byte_count <= byte_count + 1;
                    $display("3_ Result : || \t CRC_Reminder: 0x%h, \t %b", result,result);
                end
                    nresult      =   ~crc_acc[crc_len-1:0];
                    result      =     crc_acc[crc_len-1:0];
            end

        initial $display("\t \t -------- \t GMII byte input");

end endgenerate


function [crc_len-1:0]crc_bit_updt (input [crc_len-1:0]crc_acc, input [crc_len-1:0]crc, input bit);
    begin
       
        if (bit) begin
            crc_bit_updt =   (crc_acc << 1);
            crc_bit_updt =   (crc_bit_updt ^ {crc,8'h0}) ;
        end
        else begin
             crc_bit_updt = crc_acc << 1;
        end
    end
endfunction

function [datalen-1:0]reflect_byte (input [datalen-1:0]data);
reg [datalen-1:0]       temp;
reg [4:0]              bit_n;
    begin
       for (bit_n = 0; bit_n <datalen ; bit_n =bit_n +1 ) begin
            temp[bit_n] = data[datalen-1-bit_n];
       end
    reflect_byte = temp;
    end
endfunction

endmodule

cocotb_Test/action/sim.vcd
$date
	Tue Mar 21 09:18:47 2023
$end
$version
	Icarus Verilog
$end
$timescale
	1ps
$end
$scope module crc32_comb $end
$var wire 1 ! clk $end
$var wire 8 " data [7:0] $end
$var wire 1 # rst $end
$var wire 1 $ strt $end
$var wire 1 % updatecrc $end
$var reg 5 & bit_n [4:0] $end
$var reg 12 ' byte_count [11:0] $end
$var reg 32 ( crc_acc [31:0] $end
$var reg 32 ) crc_acc_n [31:0] $end
$var reg 32 * crc_poly [31:0] $end
$var reg 8 + data_buf [7:0] $end
$var reg 32 , nresult [31:0] $end
$var reg 32 - result [31:0] $end
$scope function crc_bit_updt $end
$var reg 1 . bit $end
$var reg 32 / crc [31:0] $end
$var reg 32 0 crc_acc [31:0] $end
$upscope $end
$scope function reflect_byte $end
$var reg 5 1 bit_n [4:0] $end
$var reg 8 2 data [7:0] $end
$var reg 8 3 temp [7:0] $end
$upscope $end
$scope begin genblk1 $end
$upscope $end
$upscope $end
$enddefinitions $end
#0
$dumpvars
bx 3
bx 2
bx 1
bx 0
bx /
x.
b0 -
b0 ,
b0 +
b100110000010001110110110111 *
b11111111111111111111111111111111 )
b11111111111111111111111111111111 (
b0 '
b0 &
z%
z$
1#
bz "
1!
$end
#1000
0!
#2000
b11111111111111111111111111111111 -
1!
#3000
0!
#4000
1!
#5000
0!
#6000
1!
#7000
0!
#8000
1!
#9000
0!
#10000
1!
0#
#11000
0!
#12000
1!
#13000
0!
#14000
1!
#15000
0!
#16000
1!
#17000
0!
#18000
1!
#19000
0!
#20000
1!
b110001 "
#21000
0!
#22000
b1 '
b111010101010010101000100000000 (
b0 &
b11101010101001010100010000000 0
b100110000010001110110110111 /
0.
b111010101010010101000100000000 )
b10001100 +
b10001100 3
b1000 1
b110001 2
1!
1%
#23000
0!
#24000
b111010101010010101000100000000 -
b11000101010101101010111011111111 ,
1!
b110010 "
0%
#25000
0!
#26000
b10 '
b101011010101111010101100000000 (
1.
b0 &
b11110101001001010000111000000000 0
b101011010101111010101100000000 )
b1001100 +
b1001100 3
b1000 1
b110010 2
1!
1%
#27000
0!
#28000
b101011010101111010101100000000 -
b11010100101010000101010011111111 ,
1!
b110011 "
0%
#29000
0!
#30000
b11 '
b11011101000001100101110000000000 (
0.
b0 &
b1101110100000110010111000000000 0
b11011101000001100101110000000000 )
b11001100 +
b11001100 3
b1000 1
b110011 2
1!
1%
#31000
0!
#32000
b11011101000001100101110000000000 -
b100010111110011010001111111111 ,
1!
b110100 "
0%
#33000
0!
#34000
b100 '
b10011100010100010011000000000 (
b0 &
b1001110001010001001100000000 0
0.
b10011100010100010011000000000 )
b101100 +
b101100 3
b1000 1
b110100 2
1!
1%
#35000
0!
#36000
b10011100010100010011000000000 -
b11101100011101011101100111111111 ,
1!
b110101 "
0%
#37000
0!
#38000
b101 '
b111110010000000110110100000000 (
b0 &
b11111111101011101110110100000000 0
1.
b111110010000000110110100000000 )
b10101100 +
b10101100 3
b1000 1
b110101 2
1!
1%
#39000
0!
#40000
b111110010000000110110100000000 -
b11000001101111111001001011111111 ,
1!
b110110 "
0%
#41000
0!
#42000
b110 '
b11110000000001100011101100000000 (
b0 &
b10011000100011011100011000000000 0
1.
b11110000000001100011101100000000 )
b1101100 +
b1101100 3
b1000 1
b110110 2
1!
1%
#43000
0!
#44000
b11110000000001100011101100000000 -
b1111111110011100010011111111 ,
1!
b110111 "
0%
#45000
0!
#46000
b111 '
b10111111000000111000000000000 (
b0 &
b1011111100000011100000000000 0
0.
b10111111000000111000000000000 )
b11101100 +
b11101100 3
b1000 1
b110111 2
1!
1%
