cocotb_Test/coco_trail/test/module.v
`timescale 1ns / 1ps

module clk_divider(
    input internal_clk_fgpa,
    input clk_mode,    // 100Mhz to 0: 1Hz 1: 100Hz
    output reg clk_out=0,
    output reg slow_clk = 0
    );

        `ifdef COCOTB_SIM
        initial begin
            $dumpfile("sim.vcd");
            $dumpvars(0,clk_divider);
        end    
        `endif
        
integer divider = 0;
localparam waitfor = 15;
//           localparam waitfor = 3*10**6;
always @(posedge internal_clk_fgpa) begin
// Clock mode should not be changed frequantly in complex systems


case(clk_mode) 
    1'b0  : begin              
                if(divider >= waitfor) begin
                clk_out <= ~clk_out;
                divider <= 0 ;
                end else  divider <= divider +1;
                slow_clk <= 1;
    end
    1'b1        : begin
                if(divider == 2*waitfor) begin
                clk_out <= ~clk_out;
                divider <= 0 ;
                end else  divider <= divider +1;
                slow_clk <= 0;
    end
    default:    clk_out <= internal_clk_fgpa;
endcase
end
           


endmodule

cocotb_Test/test/sim.vcd
$date
	Sat Mar 18 13:50:40 2023
$end
$version
	Icarus Verilog
$end
$timescale
	1ps
$end
$scope module clk_divider $end
$var wire 1 ! clk_mode $end
$var wire 1 " internal_clk_fgpa $end
$var reg 1 # clk_out $end
$var reg 1 $ slow_clk $end
$var integer 32 % divider [31:0] $end
$upscope $end
$enddefinitions $end
#0
$dumpvars
b1 %
0$
0#
1"
1!
$end
#5000
0"
#10000
b10 %
1"
#15000
0"
#20000
b11 %
1"
#25000
0"
#30000
b100 %
1"
#35000
0"
#40000
b101 %
1"
#45000
0"
#50000
b110 %
1"
#55000
0"
#60000
b111 %
1"
#65000
0"
#70000
b1000 %
1"
#75000
0"
#80000
b1001 %
1"
#85000
0"
#90000
b1010 %
1"
#95000
0"
#100000
b1011 %
1"
#105000
0"
#110000
b1100 %
1"
#115000
0"
#120000
b1101 %
1"
#125000
0"
#130000
b1110 %
1"
#135000
0"
#140000
b1111 %
1"
#145000
0"
#150000
b10000 %
1"
#155000
0"
#160000
b10001 %
1"
#165000
0"
#170000
b10010 %
1"
#175000
0"
#180000
b10011 %
1"
#185000
0"
#190000
b10100 %
1"
#195000
0"
#200000
b10101 %
1"
#205000
0"
#210000
b10110 %
1"
#215000
0"
#220000
b10111 %
1"
#225000
0"
#230000
b11000 %
1"
#235000
0"
#240000
b11001 %
1"
#245000
0"
#250000
b11010 %
1"
#255000
0"
#260000
b11011 %
1"
#265000
0"
#270000
b11100 %
1"
#275000
0"
#280000
b11101 %
1"
#285000
0"
#290000
b11110 %
1"
#295000
0"
#300000
b0 %
1#
1"
#305000
0"
#310000
b1 %
1"
#315000
0"
#320000
b10 %
1"
#325000
0"
#330000
b11 %
1"
#335000
0"
#340000
b100 %
1"
#345000
0"
#350000
b101 %
1"
#355000
0"
#360000
b110 %
1"
#365000
0"
#370000
b111 %
1"
#375000
0"
#380000
b1000 %
1"
#385000
0"
#390000
b1001 %
1"
#395000
0"
#400000
b1010 %
1"
#405000
0"
#410000
b1011 %
1"
#415000
0"
#420000
b1100 %
1"
#425000
0"
#430000
b1101 %
1"
#435000
0"
#440000
b1110 %
1"
#445000
0"
#450000
b1111 %
1"
#455000
0"
#460000
b10000 %
1"
#465000
0"
#470000
b10001 %
1"
#475000
0"
#480000
b10010 %
1"
#485000
0"
#490000
b10011 %
1"
#495000
0"
#500000
b10100 %
1"
#505000
0"
#510000
b10101 %
1"
#515000
0"
#520000
b10110 %
1"
#525000
0"
#530000
b10111 %
1"
#535000
0"
#540000
b11000 %
1"
#545000
0"
#550000
b11001 %
1"
#555000
0"
#560000
b11010 %
1"
#565000
0"
#570000
b11011 %
1"
#575000
0"
#580000
b11100 %
1"
#585000
0"
#590000
b11101 %
1"
#595000
0"
#600000
b11110 %
1"
#605000
0"
#610000
b0 %
0#
1"
#615000
0"
#620000
b1 %
1"
#625000
0"
#630000
b10 %
1"
#635000
0"
#640000
b11 %
1"
#645000
0"
#650000
b100 %
1"
#655000
0"
#660000
b101 %
1"
#665000
0"
#670000
b110 %
1"
#675000
0"
#680000
b111 %
1"
#685000
0"
#690000
b1000 %
1"
#695000
0"
#700000
b1001 %
1"
#705000
0"
#710000
b1010 %
1"
#715000
0"
#720000
b1011 %
1"
#725000
0"
#730000
b1100 %
1"
#735000
0"
#740000
b1101 %
1"
#745000
0"
#750000
b1110 %
1"
#755000
0"
#760000
b1111 %
1"
#765000
0"
#770000
b10000 %
1"
#775000
0"
#780000
b10001 %
1"
#785000
0"
#790000
b10010 %
1"
#795000
0"
#800000
0!
b10011 %
1"
#805000
0"
#810000
1$
b0 %
1#
1"
#815000
0"
#820000
b1 %
1"
#825000
0"
#830000
b10 %
1"
#835000
0"
#840000
b11 %
1"
#845000
0"
#850000
b100 %
1"
#855000
0"
#860000
b101 %
1"
#865000
0"
#870000
b110 %
1"
#875000
0"
#880000
b111 %
1"
#885000
0"
#890000
b1000 %
1"
#895000
0"
#900000
b1001 %
1"
#905000
0"
#910000
b1010 %
1"
#915000
0"
#920000
b1011 %
1"
#925000
0"
#930000
b1100 %
1"
#935000
0"
#940000
b1101 %
1"
#945000
0"
#950000
b1110 %
1"
#955000
0"
#960000
b1111 %
1"
#965000
0"
#970000
b0 %
0#
1"
#975000
0"
#980000
b1 %
1"
#985000
0"
#990000
b10 %
1"
#995000
0"
#1000000
b11 %
1"
#1005000
0"
#1010000
b100 %
1"
#1015000
0"
#1020000
b101 %
1"
#1025000
0"
#1030000
b110 %
1"
#1035000
0"
#1040000
b111 %
1"
#1045000
0"
#1050000
b1000 %
1"
#1055000
0"
#1060000
b1001 %
1"
#1065000
0"
#1070000
b1010 %
1"
#1075000
0"
#1080000
b1011 %
1"
#1085000
0"
#1090000
b1100 %
1"
#1095000
0"
#1100000
b1101 %
1"
#1105000
0"
#1110000
b1110 %
1"
#1115000
0"
#1120000
b1111 %
1"
#1125000
0"
#1130000
b0 %
1#
1"
#1135000
0"
#1140000
b1 %
1"
#1145000
0"
#1150000
b10 %
1"
#1155000
0"
#1160000
b11 %
1"
#1165000
0"
#1170000
b100 %
1"
#1175000
0"
#1180000
b101 %
1"
#1185000
0"
#1190000
b110 %
1"
#1195000
0"
#1200000
b111 %
1"
#1205000
0"
#1210000
b1000 %
1"
#1215000
0"
#1220000
b1001 %
1"
#1225000
0"
#1230000
b1010 %
1"
#1235000
0"
#1240000
b1011 %
1"
#1245000
0"
#1250000
b1100 %
1"
#1255000
0"
#1260000
b1101 %
1"
#1265000
0"
#1270000
b1110 %
1"
#1275000
0"
#1280000
b1111 %
1"
#1285000
0"
#1290000
b0 %
0#
1"
#1295000
0"
#1300000
b1 %
1"
#1305000
0"
#1310000
b10 %
1"
#1315000
0"
#1320000
b11 %
1"
#1325000
0"
#1330000
b100 %
1"
#1335000
0"
#1340000
b101 %
1"
#1345000
0"
#1350000
b110 %
1"
#1355000
0"
#1360000
b111 %
1"
#1365000
0"
#1370000
b1000 %
1"
#1375000
0"
#1380000
b1001 %
1"
#1385000
0"
#1390000
b1010 %
1"
#1395000
0"
#1400000
b1011 %
1"
#1405000
0"
#1410000
b1100 %
1"
#1415000
0"
#1420000
b1101 %
1"
#1425000
0"
#1430000
b1110 %
1"
#1435000
0"
#1440000
b1111 %
1"
#1445000
0"
#1450000
b0 %
1#
1"
#1455000
0"
#1460000
b1 %
1"
#1465000
0"
#1470000
b10 %
1"
#1475000
0"
#1480000
b11 %
1"
#1485000
0"
#1490000
b100 %
1"
#1495000
0"
#1500000
b101 %
1"
#1505000
0"
#1510000
b110 %
1"
#1515000
0"
#1520000
b111 %
1"
#1525000
0"
#1530000
b1000 %
1"
#1535000
0"
#1540000
b1001 %
1"
#1545000
0"
#1550000
b1010 %
1"
#1555000
0"
#1560000
b1011 %
1"
#1565000
0"
#1570000
b1100 %
1"
#1575000
0"
#1580000
b1101 %
1"
#1585000
0"
#1590000
b1110 %
1"
#1595000
0"
#1600000
b1111 %
1"
