Encapsulation/utils.vh
`define min_payload_len                 16'd46
`define len_addr                        13'd6
`define len_len                         13'd2
`define len_crc                         13'd4
`define len_perm                        13'd7
`define len_max_payload                 50

crc32_comb.v
module crc32_comb
#(parameter crc_len =32, parameter crc =  32'h04C11DB7, parameter GMII = 1, parameter datalen = 8, parameter refin = 1, parameter refout = 1,parameter byte_len =64)
(
input updatecrc,                                                    
output reg [crc_len-1:0]result,
input clk,rst,                    
input  [datalen-1:0] data
);

reg [crc_len-1:0]   crc_poly        = crc;
reg [crc_len-1:0]   crc_acc         = {(crc_len){1'b1}};            //Initiate acc
reg [11:0]          byte_count =0;                                  //Keep track of bytes
reg [4:0]           bit_n = 0;                                      //Keep track of bites
reg [crc_len-1:0]   nresult  ;                                      //Final CRC Reminder
reg [datalen-1:0] data_buf;                                         //Databuffer stores reflected databyte
reg [crc_len-1:0] crc_acc_n;                                        //Crc Accumulator



generate if (GMII) begin
            always @(*) begin

                if(rst) begin
                    crc_acc     <= {(crc_len){1'b1}};
                    result      <=  0;
                    byte_count  <=  0;
                    crc_acc_n   <= {(crc_len){1'b1}};
                    nresult     <=  0;
                    data_buf    <=  0;
                    bit_n       <=  0;
                end

                else begin
                    result = nresult;
                end
            end

            always @(posedge clk) begin
                if (updatecrc) begin
                    data_buf = reflect_byte(data[datalen-1:0]);
                    crc_acc_n =  {data_buf,{(crc_len-datalen){1'b0}}}^ crc_acc_n;
                    
                    for (bit_n = 0; bit_n <datalen ; bit_n =bit_n +1 ) begin 
                        // Num of itteration = datalen -- For Single CRC Step
                        crc_acc_n = crc_bit_updt(crc_acc_n[crc_len-1:0],crc[crc_len-1:0],crc_acc_n[crc_len-1]);
                    end
                    bit_n       <=  0;
                    byte_count <= byte_count + 1; //  Keep track of bytes processed

                end
                    if(byte_count == byte_len-1) begin
                        nresult      =  ~reflectcrc(crc_acc_n[crc_len-1:0]);
                    end
            end
end endgenerate


function [crc_len-1:0]crc_bit_updt (input [crc_len-1:0]crc_acc, input [crc_len-1:0]crc, input bit);
//      Basic single CRC step
    begin
        if (bit) begin
            crc_bit_updt =   (crc_acc << 1);
            crc_bit_updt =   (crc_bit_updt ^ crc) ;
        end
        else begin
             crc_bit_updt = crc_acc << 1;
        end
    end
endfunction

function [datalen-1:0]reflect_byte (input [datalen-1:0]data);
//      Reflect 8 bits
reg [datalen-1:0]       temp;
reg [4:0]              bit_n;
    begin
       for (bit_n = 0; bit_n <datalen ; bit_n =bit_n +1 ) begin
            temp[bit_n] = data[datalen-1-bit_n];
       end
    reflect_byte = temp;
    end
endfunction

function [crc_len-1:0]reflectcrc (input [crc_len-1:0]crc_acc);
//      Reflect 32 bits
reg [crc_len-1:0]       temp;
reg [5:0]              bit_n;
    begin
       for (bit_n = 0; bit_n <crc_len ; bit_n =bit_n +1 ) begin
            temp[bit_n] = crc_acc[crc_len-1-bit_n];
       end
    reflectcrc = temp;
    end
endfunction

endmodule

Encapsulation/framing.v
`include "utils.vh"

module ethernet_encapsulation 
#(
    parameter [47:0] destination_mac_addr  = 48'h023528fbdd66,
    parameter [47:0] source_mac_addr       = 48'h072227acdb65
)
(
    // Buffer tx ports
    input [7:0] data_in ,
    input       data_in_clk,read_en,
    input       buffer_ready, buffer_empt,
    output  reg    data_recive,

    // Transmission ports
    output [7:0]    gmii_data_out,
    output          gmii_clk_o, en_tx,
    input           gmii_clk_i,clk,rst,
    output          gmii_er, gmii_en
);

// Dump waveforms with makefile
`ifdef COCOTB_SIM
initial begin
    $dumpfile("sim.vcd");
    $dumpvars(0,ethernet_encapsulation);
end    
`endif

    crc32_comb crc_mod(
        .clk(clk),.rst(rst_crc),
        .updatecrc(updatecrc),
        .data(crc_data_in),
        .result(crc_check)
    );

    //  Define Registers
    reg                         buffer_data_valid = 0;                               // Payload read correct or not
    reg         [3:0]                   state_reg = 0;                               // FSN State register, keep track of frame section 
    reg         [7:0]                   data_out;                                    // GMII output buffer
    reg         [8*`len_max_payload-1:0]              data_buf;                                    // Register that holds data
    wire                                data_out_en;                                 // Data_out can be transmitted
    reg         [13:0]                  byte_count = 0;                              // Track bytes in each state
    reg         [15:0]                 len_payload = 0;                              // Keep track of every payloads Byte Length
    reg         [31:0]                 crc_res     = {(`len_crc){1'b1}};             // Initate CRC, update with every processed byte
    reg                                save_payload_buf = 0;                         // Save Payload Stages 
    wire        [7:0]                   crc_data_in;
    reg    updatecrc = 0;
    reg    rst_crc = 1;
    assign crc_data_in = data_out;
    wire        [31:0]                  crc_check;

    //  Ethernet Frame Encapsulation Stages
    localparam  IDLE                = 4'd0,
                PERMABLE            = 4'd1,
                SDF                 = 4'd2,  
                LEN                 = 4'd3,
                PAYLOAD             = 4'd4,  
                FCS                 = 4'd5,
                EXT                 = 4'd6,
                Dest_MAC            = 4'd7,
                Source_Mac          = 4'd8;

    localparam Permable_val = 8'b101010,                            
               Start_Del_val= 8'b101011;                                            // IEEE defined Permable and Delimeter bytes


    assign data_out_en = (state_reg != IDLE)? 1'b1:1'b0;
    // Data out should not be transmitted when IDLE

    // Select the right output according to stages
    always @(*) begin
        case (state_reg)
            IDLE        :   begin
                                data_out    =   0;
                            end

            PERMABLE    : data_out    =     Permable_val;
                            
            SDF         : data_out    =     Start_Del_val;

            Dest_MAC    :   begin
                            data_out    =     destination_mac_addr[(8*(`len_addr-byte_count)-1)-:8]; 
                            end 
                         
            Source_Mac  :   begin
                            data_out    =     source_mac_addr[(8*(`len_addr-byte_count)-1)-:8]; 
                            end 

            LEN         :   begin
                            data_out    =     len_payload[(8*(`len_len-byte_count)-1)-:8];
                            end 

            PAYLOAD     :   begin
                            data_out     =     data_buf[(8*(len_payload-byte_count)-1)-:8];
                            end 

            EXT         : begin
                            data_out    =     0;
                            end
            
            FCS         : begin
                            data_out    =    crc_check[(8*(`len_crc-byte_count)-1)-:8];
                        end
        endcase
    end

    // Ethernet Frame Stages
    always @(posedge clk) begin
        if (!rst) begin
            if (en_tx) begin
                    case (state_reg)
                        IDLE:       begin
                                    rst_crc    =   1;
                                        if (buffer_data_valid) begin
                                            state_reg = PERMABLE;
                                            rst_crc    =   0;
                                        end
                                    end 
                        PERMABLE:   begin
                                        if(byte_count < `len_perm-1 ) begin
                                            byte_count  = byte_count +1;
                                        end 
                                        else begin
                                            state_reg = SDF;
                                            byte_count = 0;
                                        end
                                    end
                        SDF:        begin
                                        state_reg   = Dest_MAC;
                                        updatecrc   =   1;
                                    end
                        Dest_MAC:   begin
                                        if (byte_count < `len_addr-1) begin
                                            byte_count = byte_count + 1;
                                        end 
                                        else begin
                                            byte_count= 0;
                                            state_reg = Source_Mac;
                                        end
                                    end
                        Source_Mac: begin
                                        if (byte_count < `len_addr-1) begin
                                            byte_count = byte_count + 1;
                                        end 
                                        else begin
                                            byte_count= 0;
                                            state_reg = LEN;
                                        end  
                                    end
                        LEN:        begin
                                        if (byte_count < `len_len-1) begin
                                            byte_count = byte_count + 1;
                                        end 
                                        else begin
                                            byte_count= 0;
                                            state_reg = PAYLOAD;
                                        end  
                                    end
                        PAYLOAD:    begin
                                        if (byte_count < len_payload-1) begin
                                            byte_count = byte_count + 1;
                                            state_reg = PAYLOAD;
                                        end 
                                        else begin
                                            byte_count= 0;
                                            if (len_payload <= `min_payload_len)
                                                state_reg = EXT;
                                            else
                                                state_reg = FCS;
                                        end  
                                    end

                        EXT:        begin
                                        if (byte_count < `min_payload_len-len_payload-1) begin
                                            byte_count = byte_count + 1;
                                        end 
                                        else begin
                                            state_reg = FCS;
                                            byte_count = 0;
                                            updatecrc   =   0;
                                        end
                                    end

                        FCS:        begin
                                        if (byte_count < `len_crc-1) begin
                                            byte_count = byte_count + 1;
                                        end 
                                        else begin
                                            byte_count= 0;
                                            state_reg = IDLE;
                                        end 
                                    end

                        default: state_reg = IDLE;
                    endcase
            end
        end 
    end

    // Fill the payload buffer
    always @(posedge clk) begin
        if (!rst) begin
            case (save_payload_buf)
            1'b0   :    
                        begin
                                if (buffer_ready) begin
                                    if(state_reg == IDLE) begin
                                        data_recive         = 1;
                                        save_payload_buf    = 1'b1; 
                                        buffer_data_valid   = 0;
                                        len_payload         = 0; 
                                    end
                                end
                        end 
            1'b1: 
                        begin
                                if(read_en) begin
                                    data_buf        =   data_buf <<8;
                                    data_buf[7:0]   =   data_in;
                                    len_payload     =   len_payload +1;
                                end
                                else
                                    if (buffer_empt) begin
                                        buffer_data_valid <= 1;
                                        save_payload_buf   <=1'b0;
                                    end
                        end
            default: save_payload_buf   <=1'b0;
            endcase
        end
    end

    //  Global Synchronous Reset
    always @(posedge clk ) begin
        if (rst) begin
            len_payload                     = 0;
            state_reg                       =IDLE;
            save_payload_buf                =1'b0;
            data_buf                        = 0;
            crc_res                         = {(`len_crc){1'b1}};
            data_out                        = 0;
            buffer_data_valid               = 0;
            byte_count                      = 0;
        end
    end

endmodule


// Issues
// The fifo?, clock ? 
// Make Recive stage asynch

Encapsulation/sim.vcd
$date
	Wed Apr  5 15:07:17 2023
$end
$version
	Icarus Verilog
$end
$timescale
	1ps
$end
$scope module ethernet_encapsulation $end
$var wire 1 ! buffer_empt $end
$var wire 1 " buffer_ready $end
$var wire 1 # clk $end
$var wire 8 $ crc_data_in [7:0] $end
$var wire 8 % data_in [7:0] $end
$var wire 1 & data_in_clk $end
$var wire 1 ' en_tx $end
$var wire 1 ( gmii_clk_i $end
$var wire 1 ) gmii_clk_o $end
$var wire 8 * gmii_data_out [7:0] $end
$var wire 1 + gmii_en $end
$var wire 1 , gmii_er $end
$var wire 1 - read_en $end
$var wire 1 . rst $end
$var wire 1 / data_out_en $end
$var wire 32 0 crc_check [31:0] $end
$var reg 1 1 buffer_data_valid $end
$var reg 14 2 byte_count [13:0] $end
$var reg 32 3 crc_res [31:0] $end
$var reg 400 4 data_buf [399:0] $end
$var reg 8 5 data_out [7:0] $end
$var reg 1 6 data_recive $end
$var reg 16 7 len_payload [15:0] $end
$var reg 1 8 rst_crc $end
$var reg 1 9 save_payload_buf $end
$var reg 4 : state_reg [3:0] $end
$var reg 1 ; updatecrc $end
$scope module crc_mod $end
$var wire 1 # clk $end
$var wire 8 < data [7:0] $end
$var wire 1 8 rst $end
$var wire 1 ; updatecrc $end
$var reg 5 = bit_n [4:0] $end
$var reg 12 > byte_count [11:0] $end
$var reg 32 ? crc_acc [31:0] $end
$var reg 32 @ crc_acc_n [31:0] $end
$var reg 32 A crc_poly [31:0] $end
$var reg 8 B data_buf [7:0] $end
$var reg 32 C nresult [31:0] $end
$var reg 32 D result [31:0] $end
$scope function crc_bit_updt $end
$var reg 1 E bit $end
$var reg 32 F crc [31:0] $end
$var reg 32 G crc_acc [31:0] $end
$upscope $end
$scope function reflect_byte $end
$var reg 5 H bit_n [4:0] $end
$var reg 8 I data [7:0] $end
$var reg 8 J temp [7:0] $end
$upscope $end
$scope function reflectcrc $end
$var reg 6 K bit_n [5:0] $end
$var reg 32 L crc_acc [31:0] $end
$var reg 32 M temp [31:0] $end
$upscope $end
$scope begin genblk1 $end
$upscope $end
$upscope $end
$upscope $end
$enddefinitions $end
#0
$dumpvars
bx M
bx L
bx K
bx J
bx I
bx H
bx G
bx F
xE
b0 D
b0 C
b0 B
b100110000010001110110110111 A
b11111111111111111111111111111111 @
b11111111111111111111111111111111 ?
b0 >
b0 =
b0 <
0;
b0 :
09
18
b0 7
x6
b0 5
bx 4
b1111 3
b0 2
01
b0 0
0/
z.
z-
z,
z+
bz *
z)
z(
z'
z&
bz %
b0 $
z#
z"
z!
$end
#1
1#
#1001
0#
#2001
1#
#3001
0#
#4001
1#
#5001
0#
#6001
1#
#7001
0#
#8001
1#
#9001
0#
#10001
b0 4
1#
1.
#11001
0#
#12001
1#
#13001
0#
#14001
1#
#15001
0#
#16001
1#
#17001
0#
#18001
1#
#19001
0#
#20001
1#
#21001
0#
#22001
1#
0.
#23001
0#
#24001
1#
#25001
0#
#26001
1#
#27001
0#
#28001
1#
#29001
0#
#30001
1#
#31001
0#
#32001
1#
#33001
0#
#34001
1#
#35001
0#
#36001
1#
#37001
0#
#38001
1#
#39001
0#
#40001
1#
#41001
0#
#42001
1#
#43001
0#
#44001
1#
#45001
0#
#46001
1#
#47001
0#
#48001
1#
#49001
0#
#50001
1#
#51001
0#
#52001
1#
#53001
0#
#54001
1#
#55001
0#
#56001
1#
#57001
0#
1"
0!
#58001
1-
b11 %
19
16
1#
#59001
0#
#60001
b10000 %
b1 7
b11 4
1#
#61001
0#
#62001
b1 %
b10 7
b1100010000 4
1#
#63001
0#
#64001
b1010 %
b11 7
b110001000000000001 4
1#
#65001
0#
#66001
b1001 %
b100 7
b11000100000000000100001010 4
1#
#67001
0#
#68001
b1101 %
b101 7
b1100010000000000010000101000001001 4
1#
#69001
0#
#70001
b11 %
b110 7
b110001000000000001000010100000100100001101 4
1#
#71001
0#
#72001
b1111 %
b111 7
b11000100000000000100001010000010010000110100000011 4
1#
#73001
0#
#74001
b111 %
b1000 7
b1100010000000000010000101000001001000011010000001100001111 4
1#
#75001
0#
#76001
b1101 %
b1001 7
b110001000000000001000010100000100100001101000000110000111100000111 4
1#
#77001
0#
#78001
b1010 %
b1010 7
b11000100000000000100001010000010010000110100000011000011110000011100001101 4
1#
#79001
0#
#80001
b1111 %
b1011 7
b1100010000000000010000101000001001000011010000001100001111000001110000110100001010 4
1#
#81001
0#
#82001
b1011 %
b1100 7
b110001000000000001000010100000100100001101000000110000111100000111000011010000101000001111 4
1#
#83001
0#
#84001
b10000 %
b1101 7
b11000100000000000100001010000010010000110100000011000011110000011100001101000010100000111100001011 4
1#
#85001
0#
#86001
b11 %
b1110 7
b1100010000000000010000101000001001000011010000001100001111000001110000110100001010000011110000101100010000 4
1#
#87001
0#
#88001
b100 %
b1111 7
b110001000000000001000010100000100100001101000000110000111100000111000011010000101000001111000010110001000000000011 4
1#
#89001
0#
#90001
b1010 %
b10000 7
b11000100000000000100001010000010010000110100000011000011110000011100001101000010100000111100001011000100000000001100000100 4
1#
#91001
0#
#92001
b10 %
b10001 7
b1100010000000000010000101000001001000011010000001100001111000001110000110100001010000011110000101100010000000000110000010000001010 4
1#
#93001
0#
#94001
b1001 %
b10010 7
b110001000000000001000010100000100100001101000000110000111100000111000011010000101000001111000010110001000000000011000001000000101000000010 4
1#
#95001
0#
#96001
b1011 %
b10011 7
b11000100000000000100001010000010010000110100000011000011110000011100001101000010100000111100001011000100000000001100000100000010100000001000001001 4
1#
#97001
0#
#98001
b111 %
b10100 7
b1100010000000000010000101000001001000011010000001100001111000001110000110100001010000011110000101100010000000000110000010000001010000000100000100100001011 4
1#
#99001
0#
#100001
b11 %
b10101 7
b110001000000000001000010100000100100001101000000110000111100000111000011010000101000001111000010110001000000000011000001000000101000000010000010010000101100000111 4
1#
#101001
0#
#102001
b10110 7
b11000100000000000100001010000010010000110100000011000011110000011100001101000010100000111100001011000100000000001100000100000010100000001000001001000010110000011100000011 4
1#
#103001
0#
#104001
b1100 %
b10111 7
b1100010000000000010000101000001001000011010000001100001111000001110000110100001010000011110000101100010000000000110000010000001010000000100000100100001011000001110000001100000011 4
1#
#105001
0#
#106001
b1 %
b11000 7
b110001000000000001000010100000100100001101000000110000111100000111000011010000101000001111000010110001000000000011000001000000101000000010000010010000101100000111000000110000001100001100 4
1#
#107001
0#
#108001
b111 %
b11001 7
b11000100000000000100001010000010010000110100000011000011110000011100001101000010100000111100001011000100000000001100000100000010100000001000001001000010110000011100000011000000110000110000000001 4
1#
#109001
0#
#110001
b11010 7
b1100010000000000010000101000001001000011010000001100001111000001110000110100001010000011110000101100010000000000110000010000001010000000100000100100001011000001110000001100000011000011000000000100000111 4
1#
#111001
0#
#112001
b1 %
b11011 7
b110001000000000001000010100000100100001101000000110000111100000111000011010000101000001111000010110001000000000011000001000000101000000010000010010000101100000111000000110000001100001100000000010000011100000111 4
1#
#113001
0#
#114001
b100 %
b11100 7
b11000100000000000100001010000010010000110100000011000011110000011100001101000010100000111100001011000100000000001100000100000010100000001000001001000010110000011100000011000000110000110000000001000001110000011100000001 4
1#
#115001
0#
#116001
b101 %
b11101 7
b1100010000000000010000101000001001000011010000001100001111000001110000110100001010000011110000101100010000000000110000010000001010000000100000100100001011000001110000001100000011000011000000000100000111000001110000000100000100 4
1#
#117001
0#
#118001
b1001 %
b11110 7
b110001000000000001000010100000100100001101000000110000111100000111000011010000101000001111000010110001000000000011000001000000101000000010000010010000101100000111000000110000001100001100000000010000011100000111000000010000010000000101 4
1#
#119001
0#
#120001
b1000 %
b11111 7
b11000100000000000100001010000010010000110100000011000011110000011100001101000010100000111100001011000100000000001100000100000010100000001000001001000010110000011100000011000000110000110000000001000001110000011100000001000001000000010100001001 4
1#
#121001
0#
#122001
b1111 %
b100000 7
b1100010000000000010000101000001001000011010000001100001111000001110000110100001010000011110000101100010000000000110000010000001010000000100000100100001011000001110000001100000011000011000000000100000111000001110000000100000100000001010000100100001000 4
1#
#123001
0#
#124001
b100001 7
b110001000000000001000010100000100100001101000000110000111100000111000011010000101000001111000010110001000000000011000001000000101000000010000010010000101100000111000000110000001100001100000000010000011100000111000000010000010000000101000010010000100000001111 4
1#
#125001
0#
#126001
b10 %
b100010 7
b11000100000000000100001010000010010000110100000011000011110000011100001101000010100000111100001011000100000000001100000100000010100000001000001001000010110000011100000011000000110000110000000001000001110000011100000001000001000000010100001001000010000000111100001111 4
1#
#127001
0#
#128001
b1001 %
b100011 7
b1100010000000000010000101000001001000011010000001100001111000001110000110100001010000011110000101100010000000000110000010000001010000000100000100100001011000001110000001100000011000011000000000100000111000001110000000100000100000001010000100100001000000011110000111100000010 4
1#
#129001
0#
#130001
b1101 %
b100100 7
b110001000000000001000010100000100100001101000000110000111100000111000011010000101000001111000010110001000000000011000001000000101000000010000010010000101100000111000000110000001100001100000000010000011100000111000000010000010000000101000010010000100000001111000011110000001000001001 4
1#
#131001
0#
#132001
b1000 %
b100101 7
b11000100000000000100001010000010010000110100000011000011110000011100001101000010100000111100001011000100000000001100000100000010100000001000001001000010110000011100000011000000110000110000000001000001110000011100000001000001000000010100001001000010000000111100001111000000100000100100001101 4
1#
#133001
0#
#134001
b1011 %
b100110 7
b1100010000000000010000101000001001000011010000001100001111000001110000110100001010000011110000101100010000000000110000010000001010000000100000100100001011000001110000001100000011000011000000000100000111000001110000000100000100000001010000100100001000000011110000111100000010000010010000110100001000 4
1#
#135001
0#
#136001
b110 %
b100111 7
b110001000000000001000010100000100100001101000000110000111100000111000011010000101000001111000010110001000000000011000001000000101000000010000010010000101100000111000000110000001100001100000000010000011100000111000000010000010000000101000010010000100000001111000011110000001000001001000011010000100000001011 4
1#
#137001
0#
#138001
b1001 %
b101000 7
b11000100000000000100001010000010010000110100000011000011110000011100001101000010100000111100001011000100000000001100000100000010100000001000001001000010110000011100000011000000110000110000000001000001110000011100000001000001000000010100001001000010000000111100001111000000100000100100001101000010000000101100000110 4
1#
#139001
0#
#140001
b101 %
b101001 7
b1100010000000000010000101000001001000011010000001100001111000001110000110100001010000011110000101100010000000000110000010000001010000000100000100100001011000001110000001100000011000011000000000100000111000001110000000100000100000001010000100100001000000011110000111100000010000010010000110100001000000010110000011000001001 4
1#
#141001
0#
#142001
b1 %
b101010 7
b110001000000000001000010100000100100001101000000110000111100000111000011010000101000001111000010110001000000000011000001000000101000000010000010010000101100000111000000110000001100001100000000010000011100000111000000010000010000000101000010010000100000001111000011110000001000001001000011010000100000001011000001100000100100000101 4
1#
#143001
0#
#144001
b1011 %
b101011 7
b11000100000000000100001010000010010000110100000011000011110000011100001101000010100000111100001011000100000000001100000100000010100000001000001001000010110000011100000011000000110000110000000001000001110000011100000001000001000000010100001001000010000000111100001111000000100000100100001101000010000000101100000110000010010000010100000001 4
1#
#145001
0#
#146001
b101 %
b101100 7
b1100010000000000010000101000001001000011010000001100001111000001110000110100001010000011110000101100010000000000110000010000001010000000100000100100001011000001110000001100000011000011000000000100000111000001110000000100000100000001010000100100001000000011110000111100000010000010010000110100001000000010110000011000001001000001010000000100001011 4
1#
#147001
0#
#148001
b1001 %
b101101 7
b110001000000000001000010100000100100001101000000110000111100000111000011010000101000001111000010110001000000000011000001000000101000000010000010010000101100000111000000110000001100001100000000010000011100000111000000010000010000000101000010010000100000001111000011110000001000001001000011010000100000001011000001100000100100000101000000010000101100000101 4
1#
#149001
0#
#150001
b10 %
b101110 7
b11000100000000000100001010000010010000110100000011000011110000011100001101000010100000111100001011000100000000001100000100000010100000001000001001000010110000011100000011000000110000110000000001000001110000011100000001000001000000010100001001000010000000111100001111000000100000100100001101000010000000101100000110000010010000010100000001000010110000010100001001 4
1#
#151001
0#
#152001
b1011 %
b101111 7
b1100010000000000010000101000001001000011010000001100001111000001110000110100001010000011110000101100010000000000110000010000001010000000100000100100001011000001110000001100000011000011000000000100000111000001110000000100000100000001010000100100001000000011110000111100000010000010010000110100001000000010110000011000001001000001010000000100001011000001010000100100000010 4
1#
#153001
0#
#154001
b10 %
b110000 7
b110001000000000001000010100000100100001101000000110000111100000111000011010000101000001111000010110001000000000011000001000000101000000010000010010000101100000111000000110000001100001100000000010000011100000111000000010000010000000101000010010000100000001111000011110000001000001001000011010000100000001011000001100000100100000101000000010000101100000101000010010000001000001011 4
1#
#155001
0#
#156001
b101 %
b110001 7
b11000100000000000100001010000010010000110100000011000011110000011100001101000010100000111100001011000100000000001100000100000010100000001000001001000010110000011100000011000000110000110000000001000001110000011100000001000001000000010100001001000010000000111100001111000000100000100100001101000010000000101100000110000010010000010100000001000010110000010100001001000000100000101100000010 4
1#
#157001
0#
#158001
0-
b110010 7
b1100010000000000010000101000001001000011010000001100001111000001110000110100001010000011110000101100010000000000110000010000001010000000100000100100001011000001110000001100000011000011000000000100000111000001110000000100000100000001010000100100001000000011110000111100000010000010010000110100001000000010110000011000001001000001010000000100001011000001010000100100000010000010110000001000000101 4
1#
#159001
0#
#160001
1!
0"
1#
#161001
0#
#162001
09
11
1#
