Encapsulation/utils.vh
`define min_payload_len                 16'd46
`define len_addr                        13'd6
`define len_len                         13'd2
`define len_crc                         13'd4
`define len_perm                        13'd7
`define len_max_payload                 50

crc32_comb.sv

module crc32_comb 
import global::*; // Global Ethernet Module Parameters
(
  input                           clk,
  input                           rst,
  input                           strt,

  input                           updatecrc,

  input   [global::datalen-1:0]   data,
  output  [global::crc_len-1:0]   result
);

// Dump waveforms with makefile
`ifdef COCOTB_SIM
initial begin
    $dumpfile("sim.vcd");
    $dumpvars(0,crc32_comb);
end    
`endif

localparam crc_len = global::crc_len,
           datalen = global::datalen;

logic [11:0] payload_len;
int makefile_param ;

// Determine a payload length for testing purposes
`ifdef testing
initial begin
  payload_len = global::payload_len;
  $display("Payload len %d",`payload);
  makefile_param = `payload;
  $display("***** Make file param into reg %d \n", makefile_param);
end
`endif 

logic [crc_len-1:0] crc_acc     = {(crc_len){1'b1}}; 
logic [11:0]        byte_count  = 0;
logic [crc_len-1:0] crc_acc_n   = {(crc_len){1'b1}};
logic [crc_len-1:0] nresult     = 0;
logic [11:0]        bit_n       = 0;
logic [datalen-1:0] data_buf;
logic [crc_len-1:0] crc         = global::crc_poly;

assign result = nresult;

  always_comb begin  
    if(rst) begin
      crc_acc = {(crc_len){1'b1}};
      byte_count = 0;
      crc_acc_n  = {(crc_len){1'b1}};
      nresult = 0;
      data_buf = 0;
      bit_n = 0;
    end
  end

  always_ff @(posedge clk) begin 
    if (updatecrc) begin
      data_buf = reflect_byte(data[datalen-1:0]); // Ref_in --> CRC parementer reflect incoming data byte
      crc_acc_n = {data_buf, {(crc_len-datalen){1'b0}}} ^ crc_acc_n; // Pad the data and xor with first byte of the crc accumulator

      // Itterrate over every bit of data size  
      for (bit_n = 0; bit_n <datalen ; bit_n =bit_n +1 ) begin           
        crc_acc_n = crc_bit_updt(crc_acc_n[crc_len-1:0], crc[crc_len-1:0], crc_acc_n[crc_len-1]);
      end
      
      bit_n <= 0;
      byte_count <= byte_count + 1; // Keep track of bytes processed
    
    end
        if(byte_count == payload_len-1) begin
          nresult = ~reflectcrc(crc_acc_n[crc_len-1:0]); //Ref_out --> CRC parameter reflect output crc result at the end
        end
  end


//////////////////////////
/////// FUNCTIONS ///////
/////////////////////////

//      Basic single CRC step for one bit
function automatic [crc_len-1:0] crc_bit_updt  (input logic [crc_len-1:0]crc_acc, input logic [crc_len-1:0]crc, input logic bit_l);
  begin
    if (bit_l) begin
      crc_bit_updt = (crc_acc << 1);
      crc_bit_updt = (crc_bit_updt ^ crc);
    end else begin
      crc_bit_updt = crc_acc << 1;
    end
  end
  return crc_bit_updt;
endfunction

//      Reflect 8 bits
function automatic [datalen-1:0]reflect_byte (input logic [datalen-1:0]data);
  logic [datalen-1:0] result;
  logic [4:0] bit_n;

  begin
    for (bit_n = 0; bit_n <datalen ; bit_n =bit_n +1 ) begin
      result[bit_n] = data[datalen-1-bit_n];
    end
    return result;
  end
endfunction

//      Reflect 32 bits
function automatic [crc_len-1:0]reflectcrc (input logic [crc_len-1:0]crc_acc);
  logic [crc_len-1:0]       temp;
  logic [5:0]              bit_n;
  
  begin
    for (bit_n = 0; bit_n <crc_len ; bit_n =bit_n +1 ) begin
      temp[bit_n] = crc_acc[crc_len-1-bit_n];
    end
    return temp;
  end
endfunction


endmodule

Encapsulation/encapsulation.sv
`include "utils.vh"

module encapsulation 
#(
    parameter [47:0] destination_mac_addr  = 48'h023528fbdd66,
    parameter [47:0] source_mac_addr       = 48'h072227acdb65
)
(
    // Payload Buffer Ports
    input  [7:0]     data_in ,
    input            data_in_clk,
    input            read_en,
    input            buffer_ready, 
    input            buffer_empt,
    output  logic    data_recived,

    // Control Signals
    input           en_tx,
    input           clk,        // Ethernet controller clock not gmii clock
    input           rst,

    // TX to GMII Buffer
    output  logic   buf_dv
);

// Dump waveforms with makefile
`ifdef COCOTB_SIM
initial begin
    $dumpfile("sim.vcd");
    $dumpvars(0,encapsulation);
end    
`endif

    crc32_comb crc_mod(
        .clk(clk),.rst(rst_crc),

        .updatecrc(updatecrc),
        
        .data(crc_data_in),
        .result(crc_check)
    );

    //  Define Registers
    logic                         buffer_data_valid = 0;                               // Payload read correct or not
    logic         [3:0]                   state_reg = 0;                               // FSN State logicister, keep track of frame section 

    logic         [7:0]                   data_out;                                    // GMII output buffer
    logic         [8*`len_max_payload-1:0]data_buf;                      // logicister that holds data
    wire                                data_out_en;                                 // Data_out can be transmitted
    logic         [13:0]                  byte_count = 0;                              // Track bytes in each state
    logic         [15:0]                 len_payload = 0;                              // Keep track of every payloads Byte Length
    logic         [31:0]                 crc_res     = {(`len_crc){1'b1}};             // Initate CRC, update with every processed byte
    logic                                save_payload_buf = 0;                         // Save Payload Stages 
    wire        [7:0]                   crc_data_in;
    logic    updatecrc = 0;
    logic    rst_crc = 1;
    assign crc_data_in = data_out;
    wire        [31:0]                  crc_check;

    //  Ethernet Frame Encapsulation Stages
    localparam  IDLE                = 4'd0,
                PERMABLE            = 4'd1,
                SDF                 = 4'd2,  
                LEN                 = 4'd3,
                PAYLOAD             = 4'd4,  
                FCS                 = 4'd5,
                EXT                 = 4'd6,
                Dest_MAC            = 4'd7,
                Source_Mac          = 4'd8;

    localparam Permable_val = 8'b101010,                            
               Start_Del_val= 8'b101011;                                            // IEEE defined Permable and Delimeter bytes


    assign data_out_en = (state_reg != IDLE)? 1'b1:1'b0;
    // Data out should not be transmitted when IDLE

    // Select the right output according to stages
    always @(*) begin
        case (state_reg)
            IDLE        :   begin
                                data_out    =   0;
                            end

            PERMABLE    : data_out    =     Permable_val;
                            
            SDF         : data_out    =     Start_Del_val;

            Dest_MAC    :   begin
                            data_out    =     destination_mac_addr[(8*(`len_addr-byte_count)-1)-:8]; 
                            end 
                         
            Source_Mac  :   begin
                            data_out    =     source_mac_addr[(8*(`len_addr-byte_count)-1)-:8]; 
                            end 

            LEN         :   begin
                            data_out    =     len_payload[(8*(`len_len-byte_count)-1)-:8];
                            end 

            PAYLOAD     :   begin
                            data_out     =     data_buf[(8*(len_payload-byte_count)-1)-:8];
                            end 

            EXT         : begin
                            data_out    =     0;
                            end
            
            FCS         : begin
                            data_out    =    crc_check[(8*(`len_crc-byte_count)-1)-:8];
                        end
        endcase
    end

    // Ethernet Frame Stages
    always @(posedge clk) begin
        if (!rst) begin
            if (en_tx) begin
                    case (state_reg)
                        IDLE:       begin
                                    rst_crc    =   1;
                                    buf_dv  = 0;
                                        if (buffer_data_valid) begin
                                            state_reg = PERMABLE;
                                            buf_dv  = 1;
                                            rst_crc    =   0;
                                        end
                                    end 
                        PERMABLE:   begin
                                        if(byte_count < `len_perm-1 ) begin
                                            byte_count  = byte_count +1;
                                        end 
                                        else begin
                                            state_reg = SDF;
                                            byte_count = 0;
                                        end
                                    end
                        SDF:        begin
                                        state_reg   = Dest_MAC;
                                        updatecrc   =   1;
                                    end
                        Dest_MAC:   begin
                                        if (byte_count < `len_addr-1) begin
                                            byte_count = byte_count + 1;
                                        end 
                                        else begin
                                            byte_count= 0;
                                            state_reg = Source_Mac;
                                        end
                                    end
                        Source_Mac: begin
                                        if (byte_count < `len_addr-1) begin
                                            byte_count = byte_count + 1;
                                        end 
                                        else begin
                                            byte_count= 0;
                                            state_reg = LEN;
                                        end  
                                    end
                        LEN:        begin
                                        if (byte_count < `len_len-1) begin
                                            byte_count = byte_count + 1;
                                        end 
                                        else begin
                                            byte_count= 0;
                                            state_reg = PAYLOAD;
                                        end  
                                    end
                        PAYLOAD:    begin
                                        if (byte_count < len_payload-1) begin
                                            byte_count = byte_count + 1;
                                            state_reg = PAYLOAD;
                                        end 
                                        else begin
                                            byte_count= 0;
                                            if (len_payload <= `min_payload_len)
                                                state_reg = EXT;
                                            else
                                                state_reg = FCS;
                                        end  
                                    end

                        EXT:        begin
                                        if (byte_count < `min_payload_len-len_payload-1) begin
                                            byte_count = byte_count + 1;
                                        end 
                                        else begin
                                            state_reg = FCS;
                                            byte_count = 0;
                                            updatecrc   =   0;
                                        end
                                    end

                        FCS:        begin
                                        if (byte_count < `len_crc-1) begin
                                            byte_count = byte_count + 1;
                                        end 
                                        else begin
                                            byte_count= 0;
                                            state_reg = IDLE;
                                        end 
                                    end

                        default: state_reg = IDLE;
                    endcase
            end
        end 
    end

    // Fill the payload buffer
    always @(posedge clk) begin
        if (!rst) begin
            case (save_payload_buf)
            1'b0   :    
                        begin
                                if (buffer_ready) begin
                                    if(state_reg == IDLE) begin
                                        data_recived         = 1;
                                        save_payload_buf    = 1'b1; 
                                        buffer_data_valid   = 0;
                                        len_payload         = 0; 
                                    end
                                end
                        end 
            1'b1: 
                        begin
                                if(read_en) begin
                                    data_buf        =   data_buf <<8;
                                    data_buf[7:0]   =   data_in;
                                    len_payload     =   len_payload +1;
                                end
                                else
                                    if (buffer_empt) begin
                                        buffer_data_valid <= 1;
                                        save_payload_buf   <=1'b0;
                                    end
                        end
            default: save_payload_buf   <=1'b0;
            endcase
        end
    end

    //  Global Synchronous Reset
    always @(posedge clk ) begin
        if (rst) begin
            len_payload                     = 0;
            state_reg                       =IDLE;
            save_payload_buf                =1'b0;
            data_buf                        = 0;
            crc_res                         = {(`len_crc){1'b1}};
            data_out                        = 0;
            buffer_data_valid               = 0;
            byte_count                      = 0;
            buf_dv  = 0;
        end
    end

endmodule


// Issues
// The fifo?, clock ? 
// Make Recive stage asynch

Encapsulation/sim.vcd
$date
	Fri Apr 28 15:10:43 2023
$end
$version
	Icarus Verilog
$end
$timescale
	1ps
$end
$scope module encapsulation $end
$scope module crc_mod $end
$var wire 1 ! clk $end
$var wire 8 " data [7:0] $end
$var wire 32 # result [31:0] $end
$var wire 1 $ rst $end
$var wire 1 % strt $end
$var wire 1 & updatecrc $end
$var reg 12 ' bit_n [11:0] $end
$var reg 12 ( byte_count [11:0] $end
$var reg 32 ) crc [31:0] $end
$var reg 32 * crc_acc [31:0] $end
$var reg 32 + crc_acc_n [31:0] $end
$var reg 8 , data_buf [7:0] $end
$var reg 32 - nresult [31:0] $end
$var reg 12 . payload_len [11:0] $end
$scope function crc_bit_updt $end
$upscope $end
$scope function reflect_byte $end
$upscope $end
$scope function reflectcrc $end
$upscope $end
$upscope $end
$upscope $end
$scope module encapsulation $end
$var wire 1 / buffer_empt $end
$var wire 1 0 buffer_ready $end
$var wire 1 ! clk $end
$var wire 8 1 crc_data_in [7:0] $end
$var wire 8 2 data_in [7:0] $end
$var wire 1 3 data_in_clk $end
$var wire 1 4 en_tx $end
$var wire 1 5 read_en $end
$var wire 1 6 rst $end
$var wire 1 7 data_out_en $end
$var wire 32 8 crc_check [31:0] $end
$var reg 1 9 buf_dv $end
$var reg 1 : buffer_data_valid $end
$var reg 14 ; byte_count [13:0] $end
$var reg 32 < crc_res [31:0] $end
$var reg 400 = data_buf [399:0] $end
$var reg 8 > data_out [7:0] $end
$var reg 1 ? data_recived $end
$var reg 16 @ len_payload [15:0] $end
$var reg 1 $ rst_crc $end
$var reg 1 A save_payload_buf $end
$var reg 4 B state_reg [3:0] $end
$var reg 1 & updatecrc $end
$scope module crc_mod $end
$scope function crc_bit_updt $end
$upscope $end
$scope function reflect_byte $end
$upscope $end
$scope function reflectcrc $end
$upscope $end
$upscope $end
$upscope $end
$enddefinitions $end
#0
$dumpvars
b0 B
0A
b0 @
x?
b0 >
bx =
b1111 <
b0 ;
0:
x9
b0 8
07
z6
z5
z4
z3
bz 2
b0 1
z0
z/
bx .
b0 -
b0 ,
b11111111111111111111111111111111 +
b11111111111111111111111111111111 *
b100110000010001110110110111 )
b0 (
b0 '
0&
z%
1$
b0 #
b0 "
z!
$end
#1
1!
#1001
0!
#2001
1!
#3001
0!
#4001
1!
#5001
0!
#6001
1!
#7001
0!
#8001
1!
#9001
0!
#10001
09
b0 =
1!
16
#11001
0!
#12001
1!
#13001
0!
#14001
1!
#15001
0!
#16001
1!
#17001
0!
#18001
1!
#19001
0!
#20001
1!
#21001
0!
#22001
1!
06
#23001
0!
#24001
1!
#25001
0!
#26001
1!
#27001
0!
#28001
1!
#29001
0!
#30001
1!
#31001
0!
#32001
1!
#33001
0!
#34001
1!
#35001
0!
#36001
1!
#37001
0!
#38001
1!
#39001
0!
#40001
1!
#41001
0!
#42001
1!
#43001
0!
#44001
1!
#45001
0!
#46001
1!
#47001
0!
#48001
1!
#49001
0!
#50001
1!
#51001
0!
#52001
1!
#53001
0!
#54001
1!
#55001
0!
#56001
1!
#57001
0!
10
0/
#58001
15
b1111 2
1A
1?
1!
#59001
0!
#60001
b101 2
b1 @
b1111 =
1!
#61001
0!
#62001
b1101 2
b10 @
b111100000101 =
1!
#63001
0!
#64001
b1100 2
b11 @
b11110000010100001101 =
1!
#65001
0!
#66001
b10000 2
b100 @
b1111000001010000110100001100 =
1!
#67001
0!
#68001
b1010 2
b101 @
b111100000101000011010000110000010000 =
1!
#69001
0!
#70001
b10 2
b110 @
b11110000010100001101000011000001000000001010 =
1!
#71001
0!
#72001
b1110 2
b111 @
b1111000001010000110100001100000100000000101000000010 =
1!
#73001
0!
#74001
b110 2
b1000 @
b111100000101000011010000110000010000000010100000001000001110 =
1!
#75001
0!
#76001
b1000 2
b1001 @
b11110000010100001101000011000001000000001010000000100000111000000110 =
1!
#77001
0!
#78001
b1111 2
b1010 @
b1111000001010000110100001100000100000000101000000010000011100000011000001000 =
1!
#79001
0!
#80001
b11 2
b1011 @
b111100000101000011010000110000010000000010100000001000001110000001100000100000001111 =
1!
#81001
0!
#82001
b1011 2
b1100 @
b11110000010100001101000011000001000000001010000000100000111000000110000010000000111100000011 =
1!
#83001
0!
#84001
b10 2
b1101 @
b1111000001010000110100001100000100000000101000000010000011100000011000001000000011110000001100001011 =
1!
#85001
0!
#86001
b1011 2
b1110 @
b111100000101000011010000110000010000000010100000001000001110000001100000100000001111000000110000101100000010 =
1!
#87001
0!
#88001
b1001 2
b1111 @
b11110000010100001101000011000001000000001010000000100000111000000110000010000000111100000011000010110000001000001011 =
1!
#89001
0!
#90001
b100 2
b10000 @
b1111000001010000110100001100000100000000101000000010000011100000011000001000000011110000001100001011000000100000101100001001 =
1!
#91001
0!
#92001
b10 2
b10001 @
b111100000101000011010000110000010000000010100000001000001110000001100000100000001111000000110000101100000010000010110000100100000100 =
1!
#93001
0!
#94001
b10010 @
b11110000010100001101000011000001000000001010000000100000111000000110000010000000111100000011000010110000001000001011000010010000010000000010 =
1!
#95001
0!
#96001
b110 2
b10011 @
b1111000001010000110100001100000100000000101000000010000011100000011000001000000011110000001100001011000000100000101100001001000001000000001000000010 =
1!
#97001
0!
#98001
b100 2
b10100 @
b111100000101000011010000110000010000000010100000001000001110000001100000100000001111000000110000101100000010000010110000100100000100000000100000001000000110 =
1!
#99001
0!
#100001
b10101 @
b11110000010100001101000011000001000000001010000000100000111000000110000010000000111100000011000010110000001000001011000010010000010000000010000000100000011000000100 =
1!
#101001
0!
#102001
b1 2
b10110 @
b1111000001010000110100001100000100000000101000000010000011100000011000001000000011110000001100001011000000100000101100001001000001000000001000000010000001100000010000000100 =
1!
#103001
0!
#104001
b10000 2
b10111 @
b111100000101000011010000110000010000000010100000001000001110000001100000100000001111000000110000101100000010000010110000100100000100000000100000001000000110000001000000010000000001 =
1!
#105001
0!
#106001
b10 2
b11000 @
b11110000010100001101000011000001000000001010000000100000111000000110000010000000111100000011000010110000001000001011000010010000010000000010000000100000011000000100000001000000000100010000 =
1!
#107001
0!
#108001
b1000 2
b11001 @
b1111000001010000110100001100000100000000101000000010000011100000011000001000000011110000001100001011000000100000101100001001000001000000001000000010000001100000010000000100000000010001000000000010 =
1!
#109001
0!
#110001
b1111 2
b11010 @
b111100000101000011010000110000010000000010100000001000001110000001100000100000001111000000110000101100000010000010110000100100000100000000100000001000000110000001000000010000000001000100000000001000001000 =
1!
#111001
0!
#112001
b1011 2
b11011 @
b11110000010100001101000011000001000000001010000000100000111000000110000010000000111100000011000010110000001000001011000010010000010000000010000000100000011000000100000001000000000100010000000000100000100000001111 =
1!
#113001
0!
#114001
b1010 2
b11100 @
b1111000001010000110100001100000100000000101000000010000011100000011000001000000011110000001100001011000000100000101100001001000001000000001000000010000001100000010000000100000000010001000000000010000010000000111100001011 =
1!
#115001
0!
#116001
b1 2
b11101 @
b111100000101000011010000110000010000000010100000001000001110000001100000100000001111000000110000101100000010000010110000100100000100000000100000001000000110000001000000010000000001000100000000001000001000000011110000101100001010 =
1!
#117001
0!
#118001
b101 2
b11110 @
b11110000010100001101000011000001000000001010000000100000111000000110000010000000111100000011000010110000001000001011000010010000010000000010000000100000011000000100000001000000000100010000000000100000100000001111000010110000101000000001 =
1!
#119001
0!
#120001
b1011 2
b11111 @
b1111000001010000110100001100000100000000101000000010000011100000011000001000000011110000001100001011000000100000101100001001000001000000001000000010000001100000010000000100000000010001000000000010000010000000111100001011000010100000000100000101 =
1!
#121001
0!
#122001
b1 2
b100000 @
b111100000101000011010000110000010000000010100000001000001110000001100000100000001111000000110000101100000010000010110000100100000100000000100000001000000110000001000000010000000001000100000000001000001000000011110000101100001010000000010000010100001011 =
1!
#123001
0!
#124001
b1011 2
b100001 @
b11110000010100001101000011000001000000001010000000100000111000000110000010000000111100000011000010110000001000001011000010010000010000000010000000100000011000000100000001000000000100010000000000100000100000001111000010110000101000000001000001010000101100000001 =
1!
#125001
0!
#126001
b10000 2
b100010 @
b1111000001010000110100001100000100000000101000000010000011100000011000001000000011110000001100001011000000100000101100001001000001000000001000000010000001100000010000000100000000010001000000000010000010000000111100001011000010100000000100000101000010110000000100001011 =
1!
#127001
0!
#128001
b10 2
b100011 @
b111100000101000011010000110000010000000010100000001000001110000001100000100000001111000000110000101100000010000010110000100100000100000000100000001000000110000001000000010000000001000100000000001000001000000011110000101100001010000000010000010100001011000000010000101100010000 =
1!
#129001
0!
#130001
b110 2
b100100 @
b11110000010100001101000011000001000000001010000000100000111000000110000010000000111100000011000010110000001000001011000010010000010000000010000000100000011000000100000001000000000100010000000000100000100000001111000010110000101000000001000001010000101100000001000010110001000000000010 =
1!
#131001
0!
#132001
b10000 2
b100101 @
b1111000001010000110100001100000100000000101000000010000011100000011000001000000011110000001100001011000000100000101100001001000001000000001000000010000001100000010000000100000000010001000000000010000010000000111100001011000010100000000100000101000010110000000100001011000100000000001000000110 =
1!
#133001
0!
#134001
b1110 2
b100110 @
b111100000101000011010000110000010000000010100000001000001110000001100000100000001111000000110000101100000010000010110000100100000100000000100000001000000110000001000000010000000001000100000000001000001000000011110000101100001010000000010000010100001011000000010000101100010000000000100000011000010000 =
1!
#135001
0!
#136001
b1101 2
b100111 @
b11110000010100001101000011000001000000001010000000100000111000000110000010000000111100000011000010110000001000001011000010010000010000000010000000100000011000000100000001000000000100010000000000100000100000001111000010110000101000000001000001010000101100000001000010110001000000000010000001100001000000001110 =
1!
#137001
0!
#138001
b1001 2
b101000 @
b1111000001010000110100001100000100000000101000000010000011100000011000001000000011110000001100001011000000100000101100001001000001000000001000000010000001100000010000000100000000010001000000000010000010000000111100001011000010100000000100000101000010110000000100001011000100000000001000000110000100000000111000001101 =
1!
#139001
0!
#140001
b1011 2
b101001 @
b111100000101000011010000110000010000000010100000001000001110000001100000100000001111000000110000101100000010000010110000100100000100000000100000001000000110000001000000010000000001000100000000001000001000000011110000101100001010000000010000010100001011000000010000101100010000000000100000011000010000000011100000110100001001 =
1!
#141001
0!
#142001
b1101 2
b101010 @
b11110000010100001101000011000001000000001010000000100000111000000110000010000000111100000011000010110000001000001011000010010000010000000010000000100000011000000100000001000000000100010000000000100000100000001111000010110000101000000001000001010000101100000001000010110001000000000010000001100001000000001110000011010000100100001011 =
1!
#143001
0!
#144001
b101 2
b101011 @
b1111000001010000110100001100000100000000101000000010000011100000011000001000000011110000001100001011000000100000101100001001000001000000001000000010000001100000010000000100000000010001000000000010000010000000111100001011000010100000000100000101000010110000000100001011000100000000001000000110000100000000111000001101000010010000101100001101 =
1!
#145001
0!
#146001
b10000 2
b101100 @
b111100000101000011010000110000010000000010100000001000001110000001100000100000001111000000110000101100000010000010110000100100000100000000100000001000000110000001000000010000000001000100000000001000001000000011110000101100001010000000010000010100001011000000010000101100010000000000100000011000010000000011100000110100001001000010110000110100000101 =
1!
#147001
0!
#148001
b11 2
b101101 @
b11110000010100001101000011000001000000001010000000100000111000000110000010000000111100000011000010110000001000001011000010010000010000000010000000100000011000000100000001000000000100010000000000100000100000001111000010110000101000000001000001010000101100000001000010110001000000000010000001100001000000001110000011010000100100001011000011010000010100010000 =
1!
#149001
0!
#150001
b1010 2
b101110 @
b1111000001010000110100001100000100000000101000000010000011100000011000001000000011110000001100001011000000100000101100001001000001000000001000000010000001100000010000000100000000010001000000000010000010000000111100001011000010100000000100000101000010110000000100001011000100000000001000000110000100000000111000001101000010010000101100001101000001010001000000000011 =
1!
#151001
0!
#152001
b1111 2
b101111 @
b111100000101000011010000110000010000000010100000001000001110000001100000100000001111000000110000101100000010000010110000100100000100000000100000001000000110000001000000010000000001000100000000001000001000000011110000101100001010000000010000010100001011000000010000101100010000000000100000011000010000000011100000110100001001000010110000110100000101000100000000001100001010 =
1!
#153001
0!
#154001
b110000 @
b11110000010100001101000011000001000000001010000000100000111000000110000010000000111100000011000010110000001000001011000010010000010000000010000000100000011000000100000001000000000100010000000000100000100000001111000010110000101000000001000001010000101100000001000010110001000000000010000001100001000000001110000011010000100100001011000011010000010100010000000000110000101000001111 =
1!
#155001
0!
#156001
b1101 2
b110001 @
b1111000001010000110100001100000100000000101000000010000011100000011000001000000011110000001100001011000000100000101100001001000001000000001000000010000001100000010000000100000000010001000000000010000010000000111100001011000010100000000100000101000010110000000100001011000100000000001000000110000100000000111000001101000010010000101100001101000001010001000000000011000010100000111100001111 =
1!
#157001
0!
#158001
05
b110010 @
b111100000101000011010000110000010000000010100000001000001110000001100000100000001111000000110000101100000010000010110000100100000100000000100000001000000110000001000000010000000001000100000000001000001000000011110000101100001010000000010000010100001011000000010000101100010000000000100000011000010000000011100000110100001001000010110000110100000101000100000000001100001010000011110000111100001101 =
1!
#159001
0!
#160001
1/
00
1!
#161001
0!
#162001
0A
1:
1!
