CRC_Algorithms/CRC_32/crc32_comb.sv
module crc32_comb 
import global::*; // Global Ethernet Module Parameters
(
  input                           clk,
  input                           rst,
  input                           strt,
  input                           crc_lsb,
  input                           updatecrc,
  input   [15:0]                  length,
  input   [global::datalen-1:0]   data,
  output  [global::crc_len-1:0]   result
);


`ifdef COCOTB_SIM
initial begin
    $dumpfile("sim.vcd");
    $dumpvars(0,crc32_comb);
end    
`endif


localparam crc_len = global::crc_len,
           datalen = global::datalen;

logic [15:0] payload_len = length;
int makefile_param ;

// Determine a payload length for testing purposes
`ifdef testing
initial begin
  payload_len = global::payload_len;
  $display("Payload len %d",`payload);
  makefile_param = `payload;
  $display("***** Make file param into reg %d \n", makefile_param);
end
`endif 

logic [crc_len-1:0] crc_acc     = {(crc_len){1'b1}}; 
logic [11:0]        byte_count  = 0;
logic [crc_len-1:0] crc_acc_n   = {(crc_len){1'b1}};
logic [crc_len-1:0] nresult     = 0;
logic [11:0]        bit_n       = 0;
logic [datalen-1:0] data_buf;
logic [crc_len-1:0] crc         = global::crc_poly;
wire [crc_len-1:0] mytest;


assign mytest = ~reflectcrc(crc_acc_n[crc_len-1:0]);

assign result = nresult;

  always_comb begin  
    if(rst) begin
      crc_acc = {(crc_len){1'b1}};
      byte_count = 0;
      crc_acc_n  = {(crc_len){1'b1}};
      nresult = 0;
      data_buf = 0;
      bit_n = 0;
    end
  end

  always_ff @(posedge clk) begin 
    if (updatecrc) begin
      data_buf = reflect_byte(data[datalen-1:0]); // Ref_in --> CRC parementer reflect incoming data byte
      crc_acc_n = {data_buf, {(crc_len-datalen){1'b0}}} ^ crc_acc_n; // Pad the data and xor with first byte of the crc accumulator

      // Itterrate over every bit of data size  
      for (bit_n = 0; bit_n <datalen ; bit_n =bit_n +1 ) begin           
        crc_acc_n = crc_bit_updt(crc_acc_n[crc_len-1:0], crc[crc_len-1:0], crc_acc_n[crc_len-1]);
      end
      
      bit_n <= 0;
      byte_count <= byte_count + 1; // Keep track of bytes processed
    
    end
        if(byte_count == payload_len-1) begin
          nresult = ~reflectcrc(crc_acc_n[crc_len-1:0]); //Ref_out --> CRC parameter reflect output crc result at the end
        end
  end


//////////////////////////
/////// FUNCTIONS ///////
/////////////////////////

//      Basic single CRC step for one bit
function automatic [crc_len-1:0] crc_bit_updt  (input logic [crc_len-1:0]crc_acc, input logic [crc_len-1:0]crc, input logic bit_l);
  begin
    if (bit_l) begin
      crc_bit_updt = (crc_acc << 1);
      crc_bit_updt = (crc_bit_updt ^ crc);
    end else begin
      crc_bit_updt = crc_acc << 1;
    end
  end
  return crc_bit_updt;
endfunction

//      Reflect 8 bits
function automatic [datalen-1:0]reflect_byte (input logic [datalen-1:0]data);
  logic [datalen-1:0] result;
  logic [4:0] bit_n;

  begin
    for (bit_n = 0; bit_n <datalen ; bit_n =bit_n +1 ) begin
      result[bit_n] = data[datalen-1-bit_n];
    end
    return result;
  end
endfunction

//      Reflect 32 bits
function automatic [crc_len-1:0]reflectcrc (input logic [crc_len-1:0]crc_acc);
  logic [crc_len-1:0]       temp;
  logic [5:0]              bit_n;
  
  begin
    for (bit_n = 0; bit_n <crc_len ; bit_n =bit_n +1 ) begin
      temp[bit_n] = crc_acc[crc_len-1-bit_n];
    end
    return temp;
  end
endfunction


endmodule

CRC_Algorithms/CRC_32/sim.vcd
$date
	Fri Jun 16 14:39:10 2023
$end
$version
	Icarus Verilog
$end
$timescale
	1ps
$end
$scope module crc32_comb $end
$var wire 1 ! clk $end
$var wire 1 " crc_lsb $end
$var wire 8 # data [7:0] $end
$var wire 16 $ length [15:0] $end
$var wire 32 % mytest [31:0] $end
$var wire 32 & result [31:0] $end
$var wire 1 ' rst $end
$var wire 1 ( strt $end
$var wire 1 ) updatecrc $end
$var reg 12 * bit_n [11:0] $end
$var reg 12 + byte_count [11:0] $end
$var reg 32 , crc [31:0] $end
$var reg 32 - crc_acc [31:0] $end
$var reg 32 . crc_acc_n [31:0] $end
$var reg 8 / data_buf [7:0] $end
$var reg 32 0 nresult [31:0] $end
$var reg 16 1 payload_len [15:0] $end
$var integer 32 2 makefile_param [31:0] $end
$scope function crc_bit_updt $end
$upscope $end
$scope function reflect_byte $end
$upscope $end
$scope function reflectcrc $end
$upscope $end
$upscope $end
$enddefinitions $end
#0
$dumpvars
b111100 2
b1001 1
b0 0
b0 /
b11111111111111111111111111111111 .
b11111111111111111111111111111111 -
b100110000010001110110110111 ,
b0 +
b0 *
z)
1(
1'
b0 &
b0 %
bz $
bz #
z"
1!
$end
#1000
0!
#2000
1!
#3000
0!
#4000
1!
#5000
0!
#6000
1!
#7000
0!
#8000
1!
#9000
0!
#10000
1!
0'
#11000
0!
#12000
1!
#13000
0!
#14000
1!
#15000
0!
#16000
1!
#17000
0!
#18000
1!
#19000
0!
#20000
1!
b10 #
#21000
0!
#22000
b1 +
b111100000011001000111010100001 %
b0 *
b1111010100011101100111111000011 .
b1000000 /
1!
1)
#23000
0!
#24000
1!
b110101 #
0)
#25000
0!
#26000
b10 +
b100101010111001011010001011110 %
b0 *
b10000101110100101100010101011011 .
b10101100 /
1!
1)
#27000
0!
#28000
1!
b101000 #
0)
#29000
0!
#30000
b11 +
b1101011010000010110011100110000 %
b0 *
b11110011000110010111110100101001 .
b10100 /
1!
1)
#31000
0!
#32000
1!
b11111011 #
0)
#33000
0!
#34000
b100 +
b11011110110111111011010111010010 %
b0 *
b10110100010100100000010010000100 .
b11011111 /
1!
1)
#35000
0!
#36000
1!
b11011101 #
0)
#37000
0!
#38000
b101 +
b1000010011000110010110110101001 %
b0 *
b1101010010010110011100110111101 .
b10111011 /
1!
1)
#39000
0!
#40000
1!
b1100110 #
0)
#41000
0!
#42000
b110 +
b11011001100110110101001110000001 %
b0 *
b1111110001101010010011001100100 .
b1100110 /
1!
1)
#43000
0!
#44000
1!
b111 #
0)
#45000
0!
#46000
b111 +
b11010110000000000101001011001011 %
b0 *
b101100101101011111111110010100 .
b11100000 /
1!
1)
#47000
0!
#48000
1!
b100010 #
0)
#49000
0!
#50000
b1000 +
b1011000000101011010100000011 %
b0 *
b111111010100101011111100101111 .
b1000100 /
1!
1)
#51000
0!
#52000
b1011000000101011010100000011 &
b1011000000101011010100000011 0
1!
b100111 #
0)
#53000
0!
#54000
b1001 +
b11101110000010100000100111101001 %
b11101110000010100000100111101001 &
b11101110000010100000100111101001 0
b0 *
b1101000011011111010111110001000 .
b11100100 /
1!
1)
#55000
0!
#56000
1!
b10101100 #
0)
#57000
0!
#58000
b1010 +
b11010100010110100101000010011011 %
b0 *
b100110111101011010010111010100 .
b110101 /
1!
1)
#59000
0!
#60000
1!
b11011011 #
0)
#61000
0!
#62000
b1011 +
b10100100000010101111010001001101 %
b0 *
b1001101110100001010111111011010 .
b11011011 /
1!
1)
#63000
0!
#64000
1!
b1100101 #
0)
#65000
0!
#66000
b1100 +
b11100111000100110100110110000011 %
b0 *
b111110010011010011011100011000 .
b10100110 /
1!
1)
#67000
0!
#68000
1!
b0 #
0)
#69000
0!
#70000
b1101 +
b10100110010101000010111001011010 %
b0 *
b10100101100010111101010110011010 .
b0 /
1!
1)
#71000
0!
#72000
1!
b11000111 #
0)
#73000
0!
#74000
b1110 +
b1011100000110100101010001011010 %
b0 *
b10100101110101011010011111000101 .
b11100011 /
1!
1)
#75000
0!
#76000
1!
b1000010 #
0)
#77000
0!
#78000
b1111 +
b11000001001100100110110110001111 %
b0 *
b1110010010011011001101111100 .
b1000010 /
1!
1)
#79000
0!
#80000
1!
b1100101 #
0)
#81000
0!
#82000
b10000 +
b10010010000111001101011010000110 %
b0 *
b10011110100101001100011110110110 .
b10100110 /
1!
1)
#83000
0!
#84000
1!
b1101110 #
0)
#85000
0!
#86000
b10001 +
b1111100010000011001100100010001 %
b0 *
b1110111011001100111110111000001 .
b1110110 /
1!
1)
#87000
0!
#88000
1!
b1101001 #
0)
#89000
0!
#90000
b10010 +
b10001100101000000101011100011010 %
b0 *
b10100111000101011111101011001110 .
b10010110 /
1!
1)
#91000
0!
#92000
1!
b1101101 #
0)
#93000
0!
#94000
b10011 +
b11100111011111010101101000101 %
b0 *
b1011101001010100000100011000111 .
b10110110 /
1!
1)
#95000
0!
#96000
1!
b1000001 #
0)
#97000
0!
#98000
b10100 +
b11010101011100111100010000111111 %
b0 *
b11110111000011000101010100 .
b10000010 /
1!
1)
#99000
0!
#100000
1!
b1100100 #
0)
#101000
0!
#102000
b10101 +
b101110011011100001010000110101 %
b0 *
b1010011110101111000100110001011 .
b100110 /
1!
1)
#103000
0!
#104000
1!
b11000100 #
0)
#105000
0!
#106000
b10110 +
b11000100101100100001100010011 %
b0 *
b110111001111011001011011100111 .
b100011 /
1!
1)
#107000
0!
#108000
1!
b10110001 #
0)
#109000
0!
#110000
b10111 +
b11101010110000101011101100001010 %
b0 *
b10101111001000101011110010101000 .
b10001101 /
1!
1)
#111000
0!
#112000
1!
b1101101 #
0)
#113000
0!
#114000
b11000 +
b1001111101101100111001101 %
b0 *
b1001100011001001000001101111111 .
b10110110 /
1!
1)
#115000
0!
#116000
1!
b1000101 #
0)
#117000
0!
#118000
b11001 +
b110001011000001101101001000110 %
b0 *
b10011101101001001111100101110011 .
b10100010 /
1!
1)
#119000
0!
#120000
1!
b1101110 #
0)
#121000
0!
#122000
b11010 +
b11100111100001100010011110101101 %
b0 *
b1001010000110111001111000011000 .
b1110110 /
1!
1)
#123000
0!
#124000
1!
b1100101 #
0)
#125000
0!
#126000
b11011 +
b1000111010110100010001100101000 %
b0 *
b11101011001110111010010100011101 .
b10100110 /
1!
1)
#127000
0!
#128000
1!
b1110011 #
0)
#129000
0!
#130000
b11100 +
b101110111111000011110111010010 %
b0 *
b10110100010000111100000010001011 .
b11001110 /
1!
1)
#131000
0!
#132000
1!
b1110110 #
0)
#133000
0!
#134000
b11101 +
b11100101110111010001000001 %
b0 *
b1111101110100010001011000111111 .
b1101110 /
1!
1)
#135000
0!
#136000
1!
b1100101 #
0)
#137000
0!
#138000
b11110 +
b11101110000000101001110000101000 %
b0 *
b11101011110001101011111110001000 .
b10100110 /
1!
1)
#139000
0!
#140000
1!
b1000010 #
0)
#141000
0!
#142000
b11111 +
b1111111100010110110010101010111 %
b0 *
b10101010110010010111000000001 .
b1000010 /
1!
1)
#143000
0!
#144000
1!
b1110101 #
0)
#145000
0!
#146000
b100000 +
b111000111010010010100001100 %
b0 *
b11001111010110110100011100011111 .
b10101110 /
1!
1)
#147000
0!
#148000
1!
b1000101 #
0)
#149000
0!
#150000
b100001 +
b11011101000001010000101110011100 %
b0 *
b11000110001011110101111101000100 .
b10100010 /
1!
1)
#151000
0!
#152000
1!
b1110100 #
0)
#153000
0!
#154000
b100010 +
b1111100000011101000000011001100 %
b0 *
b11001100111111101000111111000001 .
b101110 /
1!
1)
#155000
0!
#156000
1!
b1101000 #
0)
#157000
0!
#158000
b100011 +
b11110001011000011011111100 %
b0 *
b11000000100111100101110000111111 .
b10110 /
1!
1)
#159000
0!
#160000
1!
b1100101 #
0)
#161000
0!
#162000
b100100 +
b1011011110100100000000111101011 %
b0 *
b101000011111111011010000100101 .
b10100110 /
1!
1)
#163000
0!
#164000
1!
b1110010 #
0)
#165000
0!
#166000
b100101 +
b1011011100010100001011001101100 %
b0 *
b11001001100101111010111000100101 .
b1001110 /
1!
1)
#167000
0!
#168000
1!
b1101110 #
0)
#169000
0!
#170000
b100110 +
b111100010101110000010010110111 %
b0 *
b10010110111110001010111000011 .
b1110110 /
1!
1)
#171000
0!
#172000
1!
b1100101 #
0)
#173000
0!
#174000
b100111 +
b10111010111000110000101101110001 %
b0 *
b1110001001011110011100010100010 .
b10100110 /
1!
1)
#175000
0!
#176000
1!
b1110100 #
0)
#177000
0!
#178000
b101000 +
b10100010110100101111100000001001 %
b0 *
b1101111111000001011010010111010 .
b101110 /
1!
1)
#179000
0!
#180000
1!
b1010000 #
0)
#181000
0!
#182000
b101001 +
b11000000000101111101010000100101 %
b0 *
b1011011110101000001011111111100 .
b1010 /
1!
1)
#183000
0!
#184000
1!
b1100001 #
0)
#185000
0!
#186000
b101010 +
b10100011011100110111110111010000 %
b0 *
b11110100010000010011000100111010 .
b10000110 /
1!
1)
#187000
0!
#188000
1!
b1100011 #
0)
#189000
0!
#190000
b101011 +
b10000000110010010111111011000110 %
b0 *
b10011100100000010110110011111110 .
b11000110 /
1!
1)
#191000
0!
#192000
1!
b1101011 #
0)
#193000
0!
#194000
b101100 +
b1111010111001011111100110100110 %
b0 *
b10011010011000000101100010100001 .
b11010110 /
1!
1)
#195000
0!
#196000
1!
b1100101 #
0)
#197000
0!
#198000
b101101 +
b11010000000101011001100101111110 %
b0 *
b10000001011001100101011111110100 .
b10100110 /
1!
1)
#199000
0!
#200000
1!
b1110100 #
0)
#201000
0!
#202000
b101110 +
b110010000001110001001100001010 %
b0 *
b10101111001101110001111110110011 .
b101110 /
1!
1)
#203000
0!
#204000
1!
b1101001 #
0)
#205000
0!
#206000
b101111 +
b110100010111101100001111100 %
b0 *
b11000001111001000010111010011111 .
b10010110 /
1!
1)
#207000
0!
#208000
1!
b1010000 #
0)
#209000
0!
#210000
b110000 +
b11100000110111000000100010110110 %
b0 *
b10010010111011111100010011111000 .
b1010 /
1!
1)
#211000
0!
#212000
1!
b1100001 #
0)
#213000
0!
#214000
b110001 +
b11001010010101010111010011110010 %
b0 *
b10110000110100010101010110101100 .
b10000110 /
1!
1)
#215000
0!
#216000
1!
b1111001 #
0)
#217000
0!
#218000
b110010 +
b10101000101000101110000001010001 %
b0 *
b1110101111110001011101011101010 .
b10011110 /
1!
1)
#219000
0!
#220000
1!
b1101100 #
0)
#221000
0!
#222000
b110011 +
b10001010110000100000000101111100 %
b0 *
b11000001011111111011110010101110 .
b110110 /
1!
1)
#223000
0!
#224000
1!
b1101111 #
0)
#225000
0!
#226000
b110100 +
b1010110001101100110110001010010 %
b0 *
b10110101110010011001001110010101 .
b11110110 /
1!
1)
#227000
0!
#228000
1!
b1100001 #
0)
#229000
0!
#230000
b110101 +
b1101101100001001011100011110111 %
b0 *
b10000111000101101111001001001 .
b10000110 /
1!
1)
#231000
0!
#232000
1!
b1100100 #
0)
#233000
0!
#234000
b110110 +
b10111011011010011010100111001011 %
b0 *
b101100011010100110100100100010 .
b100110 /
1!
1)
#235000
0!
#236000
1!
b1110101 #
0)
#237000
0!
#238000
b110111 +
b11111110011000000001100010101111 %
b0 *
b1010111001111111100110000000 .
b10101110 /
1!
1)
#239000
0!
#240000
1!
b1000111 #
0)
#241000
0!
#242000
b111000 +
b1111100001011011110010111011111 %
b0 *
b100010110000100101111000001 .
b11100010 /
1!
1)
#243000
0!
#244000
1!
b11000011 #
0)
#245000
0!
#246000
b111001 +
b11000110011111111001111000100111 %
b0 *
b11011100001100000000110011100 .
b11000011 /
1!
1)
#247000
0!
#248000
1!
b10110110 #
0)
#249000
0!
#250000
b111010 +
b1010101110011000011001111000001 %
b0 *
b1111100001100111100110001010101 .
b1101101 /
1!
1)
#251000
0!
#252000
1!
b1101110 #
0)
#253000
0!
#254000
b111011 +
b10010100001111101001110111000111 %
b0 *
b11100010001101000001111010110 .
b1110110 /
1!
1)
#255000
0!
#256000
1!
b1100100 #
0)
#257000
0!
#258000
b111100 +
b10011101010010010010001101000010 %
b0 *
b10111101001110110110110101000110 .
b100110 /
1!
1)
#259000
0!
#260000
1!
b1100101 #
0)
#261000
0!
#262000
b111101 +
b1110111100101010001001111000101 %
b0 *
b1011100001101110101011000010001 .
b10100110 /
1!
1)
#263000
0!
#264000
1!
b1110010 #
0)
#265000
0!
#266000
b111110 +
b10000111011100000101110010110001 %
b0 *
b1110010110001011111000100011110 .
b1001110 /
1!
1)
#267000
0!
#268000
1!
b1101001 #
0)
#269000
0!
#270000
b111111 +
b1011010100011011100010100110111 %
b0 *
b10011010111000100111010100101 .
b10010110 /
1!
1)
#271000
0!
#272000
1!
b1101100 #
0)
#273000
0!
#274000
b1000000 +
b101110111000011110101000110100 %
b0 *
b11010011101010000111100010001011 .
b110110 /
1!
1)
#275000
0!
#276000
1!
b1101001 #
0)
#277000
0!
#278000
b1000001 +
b11000111111101100010001100101110 %
b0 *
b10001011001110111001000000011100 .
b10010110 /
1!
1)
#279000
0!
#280000
1!
b1111001 #
0)
#281000
0!
#282000
b1000010 +
b100111110010101101110111111001 %
b0 *
b1100000010001001010110000011011 .
b10011110 /
1!
1)
#283000
0!
#284000
1!
b1101111 #
0)
#285000
0!
#286000
b1000011 +
b11001011010010010001001100100001 %
b0 *
b1111011001101110110110100101100 .
b11110110 /
1!
1)
#287000
0!
#288000
1!
b1110010 #
0)
#289000
0!
#290000
b1000100 +
b100000101010111010011011010000 %
b0 *
b11110100100110100010101011111011 .
b1001110 /
1!
1)
#291000
0!
#292000
1!
0)
