CRC_Algorithms/CRC_32/crc32_comb.sv
module crc32_comb 
import global::*; // Global Ethernet Module Parameters
(
  input                           clk,
  input                           rst,
  input                           strt,
  input                           crc_lsb,
  input                           updatecrc,

  input   [global::datalen-1:0]   data,
  output  [global::crc_len-1:0]   result
);

`ifdef COCOTB_SIM
initial begin
    $dumpfile("sim.vcd");
    $dumpvars(0,crc32_comb);
end    
`endif

localparam crc_len = global::crc_len,
           datalen = global::datalen;

logic [11:0] payload_len = 1515;
int makefile_param ;

// Determine a payload length for testing purposes
`ifdef testing
initial begin
  payload_len = global::payload_len;
  $display("Payload len %d",`payload);
  makefile_param = `payload;
  $display("***** Make file param into reg %d \n", makefile_param);
end
`endif 

logic [crc_len-1:0] crc_acc     = {(crc_len){1'b1}}; 
logic [11:0]        byte_count  = 0;
logic [crc_len-1:0] crc_acc_n   = {(crc_len){1'b1}};
logic [crc_len-1:0] nresult     = 0;
logic [11:0]        bit_n       = 0;
logic [datalen-1:0] data_buf;
logic [crc_len-1:0] crc         = global::crc_poly;
wire [crc_len-1:0] mytest;


assign mytest = ~reflectcrc(crc_acc_n[crc_len-1:0]);

assign result = nresult;

  always_comb begin  
    if(rst) begin
      crc_acc = {(crc_len){1'b1}};
      byte_count = 0;
      crc_acc_n  = {(crc_len){1'b1}};
      nresult = 0;
      data_buf = 0;
      bit_n = 0;
    end
  end

  always_ff @(posedge clk) begin 
    if (updatecrc) begin
      data_buf = reflect_byte(data[datalen-1:0]); // Ref_in --> CRC parementer reflect incoming data byte
      crc_acc_n = {data_buf, {(crc_len-datalen){1'b0}}} ^ crc_acc_n; // Pad the data and xor with first byte of the crc accumulator

      // Itterrate over every bit of data size  
      for (bit_n = 0; bit_n <datalen ; bit_n =bit_n +1 ) begin           
        crc_acc_n = crc_bit_updt(crc_acc_n[crc_len-1:0], crc[crc_len-1:0], crc_acc_n[crc_len-1]);
      end
      
      bit_n <= 0;
      byte_count <= byte_count + 1; // Keep track of bytes processed
    
    end
        if(byte_count == payload_len-1) begin
          nresult = ~reflectcrc(crc_acc_n[crc_len-1:0]); //Ref_out --> CRC parameter reflect output crc result at the end
        end
  end


//////////////////////////
/////// FUNCTIONS ///////
/////////////////////////

//      Basic single CRC step for one bit
function automatic [crc_len-1:0] crc_bit_updt  (input logic [crc_len-1:0]crc_acc, input logic [crc_len-1:0]crc, input logic bit_l);
  begin
    if (bit_l) begin
      crc_bit_updt = (crc_acc << 1);
      crc_bit_updt = (crc_bit_updt ^ crc);
    end else begin
      crc_bit_updt = crc_acc << 1;
    end
  end
  return crc_bit_updt;
endfunction

//      Reflect 8 bits
function automatic [datalen-1:0]reflect_byte (input logic [datalen-1:0]data);
  logic [datalen-1:0] result;
  logic [4:0] bit_n;

  begin
    for (bit_n = 0; bit_n <datalen ; bit_n =bit_n +1 ) begin
      result[bit_n] = data[datalen-1-bit_n];
    end
    return result;
  end
endfunction

//      Reflect 32 bits
function automatic [crc_len-1:0]reflectcrc (input logic [crc_len-1:0]crc_acc);
  logic [crc_len-1:0]       temp;
  logic [5:0]              bit_n;
  
  begin
    for (bit_n = 0; bit_n <crc_len ; bit_n =bit_n +1 ) begin
      temp[bit_n] = crc_acc[crc_len-1-bit_n];
    end
    return temp;
  end
endfunction


endmodule

CRC_Algorithms/CRC_32/sim.vcd
$date
	Fri May  5 15:12:01 2023
$end
$version
	Icarus Verilog
$end
$timescale
	1ps
$end
$scope module crc32_comb $end
$var wire 1 ! clk $end
$var wire 1 " crc_lsb $end
$var wire 8 # data [7:0] $end
$var wire 32 $ mytest [31:0] $end
$var wire 32 % result [31:0] $end
$var wire 1 & rst $end
$var wire 1 ' strt $end
$var wire 1 ( updatecrc $end
$var reg 12 ) bit_n [11:0] $end
$var reg 12 * byte_count [11:0] $end
$var reg 32 + crc [31:0] $end
$var reg 32 , crc_acc [31:0] $end
$var reg 32 - crc_acc_n [31:0] $end
$var reg 8 . data_buf [7:0] $end
$var reg 32 / nresult [31:0] $end
$var reg 12 0 payload_len [11:0] $end
$var integer 32 1 makefile_param [31:0] $end
$scope function crc_bit_updt $end
$upscope $end
$scope function reflect_byte $end
$upscope $end
$scope function reflectcrc $end
$upscope $end
$upscope $end
$enddefinitions $end
#0
$dumpvars
b1010 1
b1001 0
b0 /
b0 .
b11111111111111111111111111111111 -
b11111111111111111111111111111111 ,
b100110000010001110110110111 +
b0 *
b0 )
z(
1'
1&
b0 %
b0 $
bz #
z"
1!
$end
#1000
0!
#2000
1!
#3000
0!
#4000
1!
#5000
0!
#6000
1!
#7000
0!
#8000
1!
#9000
0!
#10000
1!
0&
#11000
0!
#12000
1!
#13000
0!
#14000
1!
#15000
0!
#16000
1!
#17000
0!
#18000
1!
#19000
0!
#20000
1!
b110001 #
#21000
0!
#22000
b1 *
b10000011110111001110111110110111 $
b0 )
b10010000010001100010000111110 -
b10001100 .
1!
1(
#23000
0!
#24000
1!
b110010 #
0(
#25000
0!
#26000
b10 *
b1001111010100110100010011001101 $
b0 )
b1001100110111010011010100001101 -
b1001100 .
1!
1(
#27000
0!
#28000
1!
b110011 #
0(
#29000
0!
#30000
b11 *
b10001000010010000110001111010010 $
b0 )
b10110100001110011110110111101110 -
b11001100 .
1!
1(
#31000
0!
#32000
1!
b110100 #
0(
#33000
0!
#34000
b100 *
b10011011111000111110000010100011 $
b0 )
b111010111110000011100000100110 -
b101100 .
1!
1(
#35000
0!
#36000
1!
b110101 #
0(
#37000
0!
#38000
b101 *
b11001011111101010011101000011100 $
b0 )
b11000111101000110101000000101100 -
b10101100 .
1!
1(
#39000
0!
#40000
1!
b110110 #
0(
#41000
0!
#42000
b110 *
b1001011100101101001101100001 $
b0 )
b1111001001101001011000101101111 -
b1101100 .
1!
1(
#43000
0!
#44000
1!
b110111 #
0(
#45000
0!
#46000
b111 *
b1010000000000110110100110011111 $
b0 )
b110011010010011111111110101 -
b11101100 .
1!
1(
#47000
0!
#48000
1!
b111000 #
0(
#49000
0!
#50000
b1000 *
b10011010111000001101101010101111 $
b0 )
b1010101001001111100010100110 -
b11100 .
1!
1(
#51000
0!
#52000
b10011010111000001101101010101111 %
b10011010111000001101101010101111 /
1!
b111001 #
0(
#53000
0!
#54000
b1001 *
b11001011111101000011100100100110 $
b11001011111101000011100100100110 %
b11001011111101000011100100100110 /
b0 )
b10011011011000111101000000101100 -
b10011100 .
1!
1(
#55000
0!
#56000
1!
0(
