CRC_Algorithms/CRC_32_Table/crc_32_table.v

module crc_32_table #(
parameter crc_len =32, parameter crc =  32'h04C11DB7, 
parameter GMII = 1, parameter datalen = 8, 
parameter refin = 1, parameter refout = 1,parameter byte_len =9
) (
input updatecrc,                                                    
output reg [crc_len-1:0]result,
input clk,rst,strt,                    
input  [datalen-1:0] data
);

reg [crc_len-1:0]   crc_poly        = crc;
reg [crc_len-1:0]   crc_acc         = {(crc_len){1'b1}};            //Initiate acc
reg [11:0]          byte_count =0;                                  //Keep track of bytes
reg [crc_len-1:0]   nresult  ;                                      //Final CRC Reminder
reg [datalen-1:0] data_buf;                                         //Databuffer stores reflected databyte
reg [crc_len-1:0] crc_acc_n;                                        //Crc Accumulator

reg [crc_len-1:0] lookup [2**datalen-1:0];

initial begin
    //Init lookuptable for crc
    $readmemh("look.mem", lookup);
end


// Dump waveforms with makefile
`ifdef COCOTB_SIM
initial begin
    $dumpfile("sim.vcd");
    $dumpvars(0,crc_32_table);
end    
`endif


generate if(GMII) begin
        always @(*) begin
            if (rst) begin
                crc_acc         <=  {(crc_len){1'b1}};
                crc_acc_n       <=  {(crc_len){1'b1}};  
                data_buf        <=   0;
                nresult         <=   0;  
                byte_count      <=  0;
            end
            else begin
                result          <=  nresult;
            end
            
        end

        always @(posedge clk) begin
            if (updatecrc) begin
                data_buf    =   reflect_byte(data);  // 0-IF Crc refin then reverse the incoming data bits
                    if (byte_count<=byte_len) begin
                        // 1-MS byte of Crc_acc is xored with new data
                        // 2-Derived the Crc result from table for the MSB
                        // 3-Left shift accumlator byte length and xor with new Crc
                       crc_acc_n    =  crc_acc_n<<(datalen) ^ lookup[((crc_acc_n[crc_len-1:(crc_len-datalen)])^data_buf)];
                       byte_count   =  byte_count + 1;

                       if (byte_count == byte_len) begin    //  4- IF Crc refout then reverse the outcome
                            nresult =   ~reflectcrc(crc_acc_n);
                       end

                    end 
                    
            end
        end
    
    
    end
endgenerate


function [datalen-1:0]reflect_byte (input [datalen-1:0]data);
//      Reflect 8 bits
reg [datalen-1:0]       temp;
reg [4:0]              bit_n;
    begin
       for (bit_n = 0; bit_n <datalen ; bit_n =bit_n +1 ) begin
            temp[bit_n] = data[datalen-1-bit_n];
       end
    reflect_byte = temp;
    end
endfunction

function [crc_len-1:0]reflectcrc (input [crc_len-1:0]crc_acc);
//      Reflect 32 bits
reg [crc_len-1:0]       temp;
reg [5:0]              bit_n;
    begin
       for (bit_n = 0; bit_n <crc_len ; bit_n =bit_n +1 ) begin
            temp[bit_n] = crc_acc[crc_len-1-bit_n];
       end
    reflectcrc = temp;
    end
endfunction



endmodule

cocotb_Test/CRC_32_Table/sim.vcd
$date
	Tue Mar 28 13:46:17 2023
$end
$version
	Icarus Verilog
$end
$timescale
	1ps
$end
$scope module crc_32_table $end
$var wire 1 ! clk $end
$var wire 8 " data [7:0] $end
$var wire 1 # rst $end
$var wire 1 $ strt $end
$var wire 1 % updatecrc $end
$var reg 12 & byte_count [11:0] $end
$var reg 32 ' crc_acc [31:0] $end
$var reg 32 ( crc_acc_n [31:0] $end
$var reg 32 ) crc_poly [31:0] $end
$var reg 8 * data_buf [7:0] $end
$var reg 32 + nresult [31:0] $end
$var reg 32 , result [31:0] $end
$scope function reflect_byte $end
$var reg 5 - bit_n [4:0] $end
$var reg 8 . data [7:0] $end
$var reg 8 / temp [7:0] $end
$upscope $end
$scope function reflectcrc $end
$var reg 6 0 bit_n [5:0] $end
$var reg 32 1 crc_acc [31:0] $end
$var reg 32 2 temp [31:0] $end
$upscope $end
$scope begin genblk1 $end
$upscope $end
$upscope $end
$enddefinitions $end
#0
$dumpvars
bx 2
bx 1
bx 0
bx /
bx .
bx -
bx ,
bx +
bx *
b100110000010001110110110111 )
bx (
b11111111111111111111111111111111 '
b0 &
z%
z$
z#
bz "
z!
$end
#2000001
b0 +
b0 *
b11111111111111111111111111111111 (
1!
1$
1#
#2001001
0!
#2002001
1!
#2003001
0!
#2004001
1!
#2005001
0!
#2006001
1!
#2007001
0!
#2008001
1!
#2009001
0!
#2010001
b0 ,
1!
0#
#2011001
0!
#2012001
1!
#2013001
0!
#2014001
1!
#2015001
0!
#2016001
1!
#2017001
0!
#2018001
1!
#2019001
0!
#2020001
1!
b110001 "
#2021001
0!
#2022001
b1 &
b10010000010001100010000111110 (
b10001100 *
b10001100 /
b1000 -
b110001 .
1!
1%
#2023001
0!
#2024001
1!
b110010 "
0%
#2025001
0!
#2026001
b10 &
b1001100110111010011010100001101 (
b1001100 *
b1001100 /
b1000 -
b110010 .
1!
1%
#2027001
0!
#2028001
1!
b110011 "
0%
#2029001
0!
#2030001
b11 &
b10110100001110011110110111101110 (
b11001100 *
b11001100 /
b1000 -
b110011 .
1!
1%
#2031001
0!
#2032001
1!
b110100 "
0%
#2033001
0!
#2034001
b100 &
b111010111110000011100000100110 (
b101100 *
b101100 /
b1000 -
b110100 .
1!
1%
#2035001
0!
#2036001
1!
b110101 "
0%
#2037001
0!
#2038001
b101 &
b11000111101000110101000000101100 (
b10101100 *
b10101100 /
b1000 -
b110101 .
1!
1%
#2039001
0!
#2040001
1!
b110110 "
0%
#2041001
0!
#2042001
b110 &
b1111001001101001011000101101111 (
b1101100 *
b1101100 /
b1000 -
b110110 .
1!
1%
#2043001
0!
#2044001
1!
b110111 "
0%
#2045001
0!
#2046001
b111 &
b110011010010011111111110101 (
b11101100 *
b11101100 /
b1000 -
b110111 .
1!
1%
#2047001
0!
#2048001
1!
b111000 "
0%
#2049001
0!
#2050001
b1000 &
b1010101001001111100010100110 (
b11100 *
b11100 /
b1000 -
b111000 .
1!
1%
#2051001
0!
#2052001
1!
b111001 "
0%
#2053001
0!
#2054001
b11001011111101000011100100100110 ,
b11001011111101000011100100100110 +
b110100000010111100011011011001 2
b100000 0
b10011011011000111101000000101100 1
b1001 &
b10011011011000111101000000101100 (
b10011100 *
b10011100 /
b1000 -
b111001 .
1!
1%
#2055001
0!
#2056001
1!
0%
