Framing/framing.v

module ethernet_encapsulation 
#(
    parameter [47:0] destination_mac_addr  = 48'h023528fbdd66,
    parameter [47:0] source_mac_addr       = 48'h072227acdb65
)
(
    // Buffer tx ports
    input [7:0] data_in ,
    input       data_in_clk,read_en,
    input       buffer_ready, buffer_empt,
    output  reg    data_recive,

    // Transmission ports
    output [7:0]    gmii_data_out,
    output          gmii_clk_o, en_tx,
    input           gmii_clk_i,clk,rst,
    output          gmii_er, gmii_en
);

// Dump waveforms with makefile
`ifdef COCOTB_SIM
initial begin
    $dumpfile("sim.vcd");
    $dumpvars(0,ethernet_encapsulation);
end    
`endif

    reg buffer_data_valid= 0;

    reg     [3:0]               state_reg = 0;
    reg     [7:0]               data_out;
    reg                         gmii_o_en = 0;
    reg    [8*10-1:0]         data_buf;
    wire                        update_state;

    localparam  IDLE                = 4'd0,
                PERMABLE            = 4'd1,
                SDF                 = 4'd2,  
                LEN                 = 4'd3,
                PAYLOAD             = 4'd4,  
                FCS                 = 4'd5,
                EXT                 = 4'd6,
                Dest_MAC            = 4'd7,
                Source_Mac          = 4'd8;

    reg  fill_buf = 0;           
    localparam  REC                 = 2'd0,
                Init_rec            = 2'd1;

    integer j;
   
    reg [47:0] mac_addr_des ;
    reg [47:0] mac_addr_src ;
    
    localparam Permable_val = 8'b101010,
               Start_Del_val= 8'b101011;
    localparam min_payload_len = 16'd46;
    localparam      len_addr    = 6,
                    len_len     = 2,
                    len_crc     = 4,
                    len_perm    = 7;
    integer i = 0;

    reg [13:0] len_payload = 0;
    reg [31:0] crc_res;
    
    // Ethernet Frame Stages
    always @(posedge clk) begin
        if (rst) begin
            i = 0;
            state_reg = IDLE;
            mac_addr_des = destination_mac_addr;
            mac_addr_src = source_mac_addr;
        end 
        else begin
            if (en_tx) begin
                    case (state_reg)
                        IDLE:       begin
                                        if (buffer_data_valid) begin
                                            state_reg = PERMABLE;
                                        end
                                    end 
                        PERMABLE:   begin
                                        if(i < len_perm ) begin
                                            data_out = Permable_val;
                                            i  = i +1;
                                        end 
                                        else begin
                                            state_reg = SDF;
                                            i = 0;
                                        end
                                    end
                        SDF:        begin
                                        data_out    = Start_Del_val;
                                        state_reg   = Dest_MAC;
                                    end
                        Dest_MAC:   begin
                                        if (i < len_addr) begin
                                            data_out = destination_mac_addr[(8*(len_addr-i)-1)-:8]; 
                                            i = i + 1;
                                        end 
                                        else begin
                                            i= 0;
                                            state_reg = Source_Mac;
                                        end
                                    end
                        Source_Mac: begin
                                        if (i < len_addr) begin
                                            data_out = source_mac_addr[(8*(len_addr-i)-1)-:8]; 
                                            i = i + 1;
                                        end 
                                        else begin
                                            i= 0;
                                            state_reg = LEN;
                                        end  
                                    end
                        LEN:        begin
                                        if (i < len_len) begin
                                            data_out = len_payload[((8*(len_len-i)-1)-1)-:8];
                                            i = i + 1;
                                        end 
                                        else begin
                                            i= 0;
                                            state_reg = PAYLOAD;
                                        end  
                                    end
                        PAYLOAD:    begin
                                        if (i < len_payload) begin
                                            data_out = data_buf[(8*(len_payload-i)-1)-:8];
                                            i = i + 1;
                                            state_reg = PAYLOAD;
                                        end 
                                        else begin
                                            i= 0;
                                            if (len_payload <= min_payload_len)
                                                state_reg = EXT;
                                            else
                                                state_reg = FCS;
                                        end  
                                    end

                        EXT:        begin
                                        if (i < min_payload_len-len_payload) begin
                                            data_out = 0;
                                            i = i + 1;
                                        end 
                                        else begin
                                            state_reg = FCS;
                                            i = 0;
                                        end
                                    end

                        FCS:        begin
                                        if (i < 4) begin
                                            data_out = crc_res[(8*(len_crc-i)-1)-:8];
                                            i = i + 1;
                                        end 
                                        else begin
                                            i= 0;
                                            state_reg = IDLE;
                                        end 
                                    end

                        default: state_reg = IDLE;
                    endcase
            end
        end 
    end

    // Fill the payload buffer
    always @(posedge clk) begin
        case (fill_buf)
        REC    :    
                    begin
                            if (buffer_ready) begin
                                data_recive         = 1;
                                fill_buf            = Init_rec; 
                                buffer_data_valid   = 0;
                                len_payload         = 0; //Problematic
                            end
                    end 
        Init_rec: 
                    begin
                            if(read_en) begin
                                data_buf        =   data_buf <<8;
                                data_buf[7:0]   =   data_in;
                                len_payload     =   len_payload +1;
                            end
                            else
                                if (buffer_empt) begin
                                    buffer_data_valid <= 1;
                                    fill_buf   <=REC;
                                end
                    end
        default: fill_buf   <=REC;
        endcase
    end




endmodule


// Issues
// The fifo clock ? 
// Make Recive stage ascnh
// len_payload calc

Framing/sim.vcd
$date
	Wed Mar 29 11:05:44 2023
$end
$version
	Icarus Verilog
$end
$timescale
	1ps
$end
$scope module ethernet_encapsulation $end
$var wire 1 ! buffer_empt $end
$var wire 1 " buffer_ready $end
$var wire 1 # clk $end
$var wire 8 $ data_in [7:0] $end
$var wire 1 % data_in_clk $end
$var wire 1 & en_tx $end
$var wire 1 ' gmii_clk_i $end
$var wire 1 ( gmii_clk_o $end
$var wire 8 ) gmii_data_out [7:0] $end
$var wire 1 * gmii_en $end
$var wire 1 + gmii_er $end
$var wire 1 , read_en $end
$var wire 1 - rst $end
$var reg 1 . buffer_data_valid $end
$var reg 32 / crc_res [31:0] $end
$var reg 80 0 data_buf [79:0] $end
$var reg 8 1 data_out [7:0] $end
$var reg 1 2 data_recive $end
$var reg 1 3 fill_buf $end
$var reg 1 4 gmii_o_en $end
$var reg 14 5 len_payload [13:0] $end
$var reg 48 6 mac_addr_des [47:0] $end
$var reg 48 7 mac_addr_src [47:0] $end
$var reg 4 8 state_reg [3:0] $end
$var integer 32 9 i [31:0] $end
$upscope $end
$enddefinitions $end
#0
$dumpvars
b0 9
b0 8
bx 7
bx 6
b0 5
04
03
x2
bx 1
bx 0
bx /
0.
z-
z,
z+
z*
bz )
z(
z'
z&
z%
bz $
1#
z"
z!
$end
#1000
0#
#2000
1#
#3000
0#
#4000
1#
#5000
0#
#6000
1#
#7000
0#
#8000
1#
#9000
0#
#10000
b1110010001000100111101011001101101101100101 7
b100011010100101000111110111101110101100110 6
1#
1-
#11000
0#
#12000
1#
#13000
0#
#14000
1#
#15000
0#
#16000
1#
#17000
0#
#18000
1#
#19000
0#
#20000
1#
#21000
0#
#22000
1#
0-
#23000
0#
#24000
1#
#25000
0#
#26000
1#
#27000
0#
#28000
1#
#29000
0#
#30000
1#
#31000
0#
#32000
1#
#33000
0#
#34000
1#
#35000
0#
#36000
1#
#37000
0#
#38000
1#
#39000
0#
#40000
1#
#41000
0#
#42000
1#
#43000
0#
#44000
1#
#45000
0#
#46000
1#
#47000
0#
#48000
1#
#49000
0#
#50000
1#
#51000
0#
#52000
1#
#53000
0#
#54000
1#
#55000
0#
#56000
1#
#57000
0#
1"
0!
#58000
1,
b1100001 $
13
12
1#
#59000
0#
#60000
b1010111 $
b1 5
bx01100001 0
1#
#61000
0#
#62000
b1011101 $
b10 5
bx0110000101010111 0
1#
#63000
0#
#64000
b1000101 $
b11 5
bx011000010101011101011101 0
1#
#65000
0#
#66000
b11010110 $
b100 5
bx01100001010101110101110101000101 0
1#
#67000
0#
#68000
b101 $
b101 5
bx0110000101010111010111010100010111010110 0
1#
#69000
0#
#70000
b10101110 $
b110 5
bx011000010101011101011101010001011101011000000101 0
1#
#71000
0#
#72000
b11011 $
b111 5
bx01100001010101110101110101000101110101100000010110101110 0
1#
#73000
0#
#74000
b11000111 $
b1000 5
bx0110000101010111010111010100010111010110000001011010111000011011 0
1#
#75000
0#
#76000
b1000101 $
b1001 5
bx011000010101011101011101010001011101011000000101101011100001101111000111 0
1#
#77000
0#
#78000
b10110100 $
b1010 5
b1100001010101110101110101000101110101100000010110101110000110111100011101000101 0
1#
#79000
0#
#80000
b10000 $
b1011 5
b1010111010111010100010111010110000001011010111000011011110001110100010110110100 0
1#
#81000
0#
#82000
b11000000 $
b1100 5
b1011101010001011101011000000101101011100001101111000111010001011011010000010000 0
1#
#83000
0#
#84000
b10011000 $
b1101 5
b1000101110101100000010110101110000110111100011101000101101101000001000011000000 0
1#
#85000
0#
#86000
b100001 $
b1110 5
b11010110000001011010111000011011110001110100010110110100000100001100000010011000 0
1#
#87000
0#
#88000
b1110110 $
b1111 5
b101101011100001101111000111010001011011010000010000110000001001100000100001 0
1#
#89000
0#
#90000
0,
b10000 5
b10101110000110111100011101000101101101000001000011000000100110000010000101110110 0
1#
#91000
0#
#92000
1!
0"
1#
#93000
0#
#94000
03
1.
1#
#95000
0#
#96000
1#
#97001
0#
#98001
1#
#99001
0#
#100001
1#
#101001
0#
#102001
1#
#103001
0#
#104001
1#
#105001
0#
#106001
1#
1-
#107001
0#
#108001
1#
#109001
0#
#110001
1#
#111001
0#
#112001
1#
#113001
0#
#114001
1#
#115001
0#
#116001
1#
#117001
0#
#118001
1#
0-
#119001
0#
#120001
1#
#121001
0#
#122001
1#
#123001
0#
#124001
1#
#125001
0#
#126001
1#
#127001
0#
#128001
1#
#129001
0#
#130001
1#
#131001
0#
#132001
1#
#133001
0#
#134001
1#
#135001
0#
#136001
1#
#137001
0#
#138001
1#
#139001
0#
#140001
1#
#141001
0#
#142001
1#
#143001
0#
#144001
1#
#145001
0#
#146001
1#
#147001
0#
#148001
1#
#149001
0#
#150001
1#
#151001
0#
#152001
1#
#153001
0#
1"
0!
#154001
1,
b1111110 $
b0 5
0.
13
1#
#155001
0#
#156001
b111001 $
b1 5
b11011110001110100010110110100000100001100000010011000001000010111011001111110 0
1#
#157001
0#
#158001
b10101110 $
b10 5
b11000111010001011011010000010000110000001001100000100001011101100111111000111001 0
1#
#159001
0#
#160001
b1001001 $
b11 5
b1000101101101000001000011000000100110000010000101110110011111100011100110101110 0
1#
#161001
0#
#162001
b11100 $
b100 5
b10110100000100001100000010011000001000010111011001111110001110011010111001001001 0
1#
#163001
0#
#164001
b11010001 $
b101 5
b10000110000001001100000100001011101100111111000111001101011100100100100011100 0
1#
#165001
0#
#166001
b10010000 $
b110 5
b11000000100110000010000101110110011111100011100110101110010010010001110011010001 0
1#
#167001
0#
#168001
b10110000 $
b111 5
b10011000001000010111011001111110001110011010111001001001000111001101000110010000 0
1#
#169001
0#
#170001
b111 $
b1000 5
b100001011101100111111000111001101011100100100100011100110100011001000010110000 0
1#
#171001
0#
#172001
b11010000 $
b1001 5
b1110110011111100011100110101110010010010001110011010001100100001011000000000111 0
1#
#173001
0#
#174001
b1001001 $
b1010 5
b1111110001110011010111001001001000111001101000110010000101100000000011111010000 0
1#
#175001
0#
#176001
b11110101 $
b1011 5
b111001101011100100100100011100110100011001000010110000000001111101000001001001 0
1#
#177001
0#
#178001
b100011 $
b1100 5
b10101110010010010001110011010001100100001011000000000111110100000100100111110101 0
1#
#179001
0#
#180001
b10001100 $
b1101 5
b1001001000111001101000110010000101100000000011111010000010010011111010100100011 0
1#
#181001
0#
#182001
b11010011 $
b1110 5
b11100110100011001000010110000000001111101000001001001111101010010001110001100 0
1#
#183001
0#
#184001
b1010101 $
b1111 5
b11010001100100001011000000000111110100000100100111110101001000111000110011010011 0
1#
#185001
0#
#186001
b11001000 $
b10000 5
b10010000101100000000011111010000010010011111010100100011100011001101001101010101 0
1#
#187001
0#
#188001
b10100001 $
b10001 5
b10110000000001111101000001001001111101010010001110001100110100110101010111001000 0
1#
#189001
0#
#190001
b11110100 $
b10010 5
b111110100000100100111110101001000111000110011010011010101011100100010100001 0
1#
#191001
0#
#192001
b11000001 $
b10011 5
b11010000010010011111010100100011100011001101001101010101110010001010000111110100 0
1#
#193001
0#
#194001
b10001100 $
b10100 5
b1001001111101010010001110001100110100110101010111001000101000011111010011000001 0
1#
#195001
0#
#196001
b1011011 $
b10101 5
b11110101001000111000110011010011010101011100100010100001111101001100000110001100 0
1#
#197001
0#
#198001
b10100101 $
b10110 5
b100011100011001101001101010101110010001010000111110100110000011000110001011011 0
1#
#199001
0#
#200001
b11001101 $
b10111 5
b10001100110100110101010111001000101000011111010011000001100011000101101110100101 0
1#
#201001
0#
#202001
b11111000 $
b11000 5
b11010011010101011100100010100001111101001100000110001100010110111010010111001101 0
1#
#203001
0#
#204001
b111 $
b11001 5
b1010101110010001010000111110100110000011000110001011011101001011100110111111000 0
1#
#205001
0#
#206001
b11001110 $
b11010 5
b11001000101000011111010011000001100011000101101110100101110011011111100000000111 0
1#
#207001
0#
#208001
b111101 $
b11011 5
b10100001111101001100000110001100010110111010010111001101111110000000011111001110 0
1#
#209001
0#
#210001
b1001101 $
b11100 5
b11110100110000011000110001011011101001011100110111111000000001111100111000111101 0
1#
#211001
0#
#212001
b11001 $
b11101 5
b11000001100011000101101110100101110011011111100000000111110011100011110101001101 0
1#
#213001
0#
#214001
b1010011 $
b11110 5
b10001100010110111010010111001101111110000000011111001110001111010100110100011001 0
1#
#215001
0#
#216001
b1101011 $
b11111 5
b1011011101001011100110111111000000001111100111000111101010011010001100101010011 0
1#
#217001
0#
#218001
b1000000 $
b100000 5
b10100101110011011111100000000111110011100011110101001101000110010101001101101011 0
1#
#219001
0#
#220001
b111101 $
b100001 5
b11001101111110000000011111001110001111010100110100011001010100110110101101000000 0
1#
#221001
0#
#222001
b10011110 $
b100010 5
b11111000000001111100111000111101010011010001100101010011011010110100000000111101 0
1#
#223001
0#
#224001
b11011000 $
b100011 5
b111110011100011110101001101000110010101001101101011010000000011110110011110 0
1#
#225001
0#
#226001
b1010011 $
b100100 5
b11001110001111010100110100011001010100110110101101000000001111011001111011011000 0
1#
#227001
0#
#228001
b1000001 $
b100101 5
b111101010011010001100101010011011010110100000000111101100111101101100001010011 0
1#
#229001
0#
#230001
b10101110 $
b100110 5
b1001101000110010101001101101011010000000011110110011110110110000101001101000001 0
1#
#231001
0#
#232001
b11001111 $
b100111 5
b11001010100110110101101000000001111011001111011011000010100110100000110101110 0
1#
#233001
0#
#234001
b1011000 $
b101000 5
b1010011011010110100000000111101100111101101100001010011010000011010111011001111 0
1#
#235001
0#
#236001
b1011100 $
b101001 5
b1101011010000000011110110011110110110000101001101000001101011101100111101011000 0
1#
#237001
0#
#238001
b1100111 $
b101010 5
b1000000001111011001111011011000010100110100000110101110110011110101100001011100 0
1#
#239001
0#
#240001
b11010110 $
b101011 5
b111101100111101101100001010011010000011010111011001111010110000101110001100111 0
1#
#241001
0#
#242001
b1110 $
b101100 5
b10011110110110000101001101000001101011101100111101011000010111000110011111010110 0
1#
#243001
0#
#244001
b11101011 $
b101101 5
b11011000010100110100000110101110110011110101100001011100011001111101011000001110 0
1#
#245001
0#
#246001
b111001 $
b101110 5
b1010011010000011010111011001111010110000101110001100111110101100000111011101011 0
1#
#247001
0#
#248001
b1011001 $
b101111 5
b1000001101011101100111101011000010111000110011111010110000011101110101100111001 0
1#
#249001
0#
#250001
b11100001 $
b110000 5
b10101110110011110101100001011100011001111101011000001110111010110011100101011001 0
1#
#251001
0#
#252001
b10111011 $
b110001 5
b11001111010110000101110001100111110101100000111011101011001110010101100111100001 0
1#
#253001
0#
#254001
0,
b110010 5
b1011000010111000110011111010110000011101110101100111001010110011110000110111011 0
1#
#255001
0#
#256001
1!
0"
1#
#257001
0#
#258001
03
1.
1#
