Framing/utils.vh
`define min_payload_len 16'd46
`define len_addr    13'd6
`define len_len     13'd2
`define len_crc     13'd4
`define len_perm    13'd7

Framing/framing.v
`include "utils.vh"

module ethernet_encapsulation 
#(
    parameter [47:0] destination_mac_addr  = 48'h023528fbdd66,
    parameter [47:0] source_mac_addr       = 48'h072227acdb65
)
(
    // Buffer tx ports
    input [7:0] data_in ,
    input       data_in_clk,read_en,
    input       buffer_ready, buffer_empt,
    output  reg    data_recive,

    // Transmission ports
    output [7:0]    gmii_data_out,
    output          gmii_clk_o, en_tx,
    input           gmii_clk_i,clk,rst,
    output          gmii_er, gmii_en
);

// Dump waveforms with makefile
`ifdef COCOTB_SIM
initial begin
    $dumpfile("sim.vcd");
    $dumpvars(0,ethernet_encapsulation);
end    
`endif

    //  Define Registers
    reg                         buffer_data_valid = 0;                               // Payload read correct or not
    reg         [3:0]                   state_reg = 0;                               // FSN State register, keep track of frame section 
    reg         [7:0]                   data_out;                                    // GMII output buffer
    reg         [8*10-1:0]              data_buf;                                    // Register that holds data
    wire                                data_out_en;                                 // Data_out can be transmitted
    reg         [13:0]                  byte_count = 0;                              // Track bytes in each state
    reg         [13:0]                 len_payload = 0;                              // Keep track of every payloads Byte Length
    reg         [31:0]                 crc_res     = {(`len_crc){1'b1}};             // Initate CRC, update with every processed byte
    reg                                save_payload_buf = 0;                         // Save Payload Stages 


    //  Ethernet Frame Encapsulation Stages
    localparam  IDLE                = 4'd0,
                PERMABLE            = 4'd1,
                SDF                 = 4'd2,  
                LEN                 = 4'd3,
                PAYLOAD             = 4'd4,  
                FCS                 = 4'd5,
                EXT                 = 4'd6,
                Dest_MAC            = 4'd7,
                Source_Mac          = 4'd8;

    localparam Permable_val = 8'b101010,                            
               Start_Del_val= 8'b101011;                                            // IEEE defined Permable and Delimeter bytes


    assign data_out_en = (state_reg != IDLE)? 1'b1:1'b0;
    // Data out should not be transmitted when IDLE

    // Select the right output according to stages
    always @(*) begin
        case (state_reg)
            IDLE        : data_out    =   0;

            PERMABLE    : data_out    =     Permable_val;
                            
            SDF         : data_out    =     Start_Del_val;

            Dest_MAC    : data_out    =     destination_mac_addr[(8*(`len_addr-byte_count)-1)-:8]; 
                         
            Source_Mac  : data_out    =     source_mac_addr[(8*(`len_addr-byte_count)-1)-:8]; 

            LEN         : data_out    =     len_payload[((8*(`len_len-byte_count)-1)-1)-:8];

            PAYLOAD     : data_out    =     len_payload[((8*(`len_len-byte_count)-1)-1)-:8];

            EXT         : data_out    =     0;

            FCS         : data_out    =     crc_res[(8*(`len_crc-byte_count)-1)-:8];
        endcase
    end

    // Ethernet Frame Stages
    always @(posedge clk) begin
        if (!rst) begin
            if (en_tx) begin
                    case (state_reg)
                        IDLE:       begin
                                        if (buffer_data_valid) begin
                                            state_reg = PERMABLE;
                                        end
                                    end 
                        PERMABLE:   begin
                                        if(byte_count < `len_perm-1 ) begin
                                            byte_count  = byte_count +1;
                                        end 
                                        else begin
                                            state_reg = SDF;
                                            byte_count = 0;
                                        end
                                    end
                        SDF:        begin
                                        state_reg   = Dest_MAC;
                                    end
                        Dest_MAC:   begin
                                        if (byte_count < `len_addr-1) begin
                                            byte_count = byte_count + 1;
                                        end 
                                        else begin
                                            byte_count= 0;
                                            state_reg = Source_Mac;
                                        end
                                    end
                        Source_Mac: begin
                                        if (byte_count < `len_addr-1) begin
                                            byte_count = byte_count + 1;
                                        end 
                                        else begin
                                            byte_count= 0;
                                            state_reg = LEN;
                                        end  
                                    end
                        LEN:        begin
                                        if (byte_count < `len_len-1) begin
                                            byte_count = byte_count + 1;
                                        end 
                                        else begin
                                            byte_count= 0;
                                            state_reg = PAYLOAD;
                                        end  
                                    end
                        PAYLOAD:    begin
                                        if (byte_count < len_payload-1) begin
                                            byte_count = byte_count + 1;
                                            state_reg = PAYLOAD;
                                        end 
                                        else begin
                                            byte_count= 0;
                                            if (len_payload <= `min_payload_len)
                                                state_reg = EXT;
                                            else
                                                state_reg = FCS;
                                        end  
                                    end

                        EXT:        begin
                                        if (byte_count < `min_payload_len-len_payload-1) begin
                                            byte_count = byte_count + 1;
                                        end 
                                        else begin
                                            state_reg = FCS;
                                            byte_count = 0;
                                        end
                                    end

                        FCS:        begin
                                        if (byte_count < `len_crc-1) begin
                                            byte_count = byte_count + 1;
                                        end 
                                        else begin
                                            byte_count= 0;
                                            state_reg = IDLE;
                                        end 
                                    end

                        default: state_reg = IDLE;
                    endcase
            end
        end 
    end

    // Fill the payload buffer
    always @(posedge clk) begin
        if (!rst) begin
            case (save_payload_buf)
            1'b0   :    
                        begin
                                if (buffer_ready) begin
                                    if(state_reg == IDLE) begin
                                        data_recive         = 1;
                                        save_payload_buf    = 1'b1; 
                                        buffer_data_valid   = 0;
                                        len_payload         = 0; //Problematic
                                    end
                                end
                        end 
            1'b1: 
                        begin
                                if(read_en) begin
                                    data_buf        =   data_buf <<8;
                                    data_buf[7:0]   =   data_in;
                                    len_payload     =   len_payload +1;
                                end
                                else
                                    if (buffer_empt) begin
                                        buffer_data_valid <= 1;
                                        save_payload_buf   <=1'b0;
                                    end
                        end
            default: save_payload_buf   <=1'b0;
            endcase
        end
    end

    //  Global Synchronous Reset
    always @(posedge clk ) begin
        if (rst) begin
            len_payload                     = 0;
            state_reg                       =IDLE;
            save_payload_buf                =1'b0;
            data_buf                        = 0;
            crc_res                         = {(`len_crc){1'b1}};
            data_out                        = 0;
            buffer_data_valid               = 0;
            byte_count                      = 0;
        end
    end

endmodule


// Issues
// The fifo clock ? 
// Make Recive stage ascnh
// len_payload calc

Framing/sim.vcd
$date
	Wed Mar 29 14:25:58 2023
$end
$version
	Icarus Verilog
$end
$timescale
	1ps
$end
$scope module ethernet_encapsulation $end
$var wire 1 ! buffer_empt $end
$var wire 1 " buffer_ready $end
$var wire 1 # clk $end
$var wire 8 $ data_in [7:0] $end
$var wire 1 % data_in_clk $end
$var wire 1 & en_tx $end
$var wire 1 ' gmii_clk_i $end
$var wire 1 ( gmii_clk_o $end
$var wire 8 ) gmii_data_out [7:0] $end
$var wire 1 * gmii_en $end
$var wire 1 + gmii_er $end
$var wire 1 , read_en $end
$var wire 1 - rst $end
$var wire 1 . data_out_en $end
$var reg 1 / buffer_data_valid $end
$var reg 14 0 byte_count [13:0] $end
$var reg 32 1 crc_res [31:0] $end
$var reg 80 2 data_buf [79:0] $end
$var reg 8 3 data_out [7:0] $end
$var reg 1 4 data_recive $end
$var reg 14 5 len_payload [13:0] $end
$var reg 1 6 save_payload_buf $end
$var reg 4 7 state_reg [3:0] $end
$upscope $end
$enddefinitions $end
#0
$dumpvars
b0 7
06
b0 5
x4
b0 3
bx 2
b1111 1
b0 0
0/
0.
z-
z,
z+
z*
bz )
z(
z'
z&
z%
bz $
1#
z"
z!
$end
#1000
0#
#2000
1#
#3000
0#
#4000
1#
#5000
0#
#6000
1#
#7000
0#
#8000
1#
#9000
0#
#10000
b0 2
1#
1-
#11000
0#
#12000
1#
#13000
0#
#14000
1#
#15000
0#
#16000
1#
#17000
0#
#18000
1#
#19000
0#
#20000
1#
#21000
0#
#22000
1#
0-
#23000
0#
#24000
1#
#25000
0#
#26000
1#
#27000
0#
#28000
1#
#29000
0#
#30000
1#
#31000
0#
#32000
1#
#33000
0#
#34000
1#
#35000
0#
#36000
1#
#37000
0#
#38000
1#
#39000
0#
#40000
1#
#41000
0#
#42000
1#
#43000
0#
#44000
1#
#45000
0#
#46000
1#
#47000
0#
#48000
1#
#49000
0#
#50000
1#
#51000
0#
#52000
1#
#53000
0#
#54000
1#
#55000
0#
#56000
1#
#57000
0#
1"
0!
#58000
1,
b11101110 $
16
14
1#
#59000
0#
#60000
b11000001 $
b1 5
b11101110 2
1#
#61000
0#
#62000
b10000001 $
b10 5
b1110111011000001 2
1#
#63000
0#
#64000
b1101010 $
b11 5
b111011101100000110000001 2
1#
#65000
0#
#66000
b10110100 $
b100 5
b11101110110000011000000101101010 2
1#
#67000
0#
#68000
b1111011 $
b101 5
b1110111011000001100000010110101010110100 2
1#
#69000
0#
#70000
b11001000 $
b110 5
b111011101100000110000001011010101011010001111011 2
1#
#71000
0#
#72000
b11000101 $
b111 5
b11101110110000011000000101101010101101000111101111001000 2
1#
#73000
0#
#74000
b1101000 $
b1000 5
b1110111011000001100000010110101010110100011110111100100011000101 2
1#
#75000
0#
#76000
b110111 $
b1001 5
b111011101100000110000001011010101011010001111011110010001100010101101000 2
1#
#77000
0#
#78000
b11010011 $
b1010 5
b11101110110000011000000101101010101101000111101111001000110001010110100000110111 2
1#
#79000
0#
#80000
b111000 $
b1011 5
b11000001100000010110101010110100011110111100100011000101011010000011011111010011 2
1#
#81000
0#
#82000
b1100100 $
b1100 5
b10000001011010101011010001111011110010001100010101101000001101111101001100111000 2
1#
#83000
0#
#84000
b1011001 $
b1101 5
b1101010101101000111101111001000110001010110100000110111110100110011100001100100 2
1#
#85000
0#
#86000
b10001010 $
b1110 5
b10110100011110111100100011000101011010000011011111010011001110000110010001011001 2
1#
#87000
0#
#88000
b11000000 $
b1111 5
b1111011110010001100010101101000001101111101001100111000011001000101100110001010 2
1#
#89000
0#
#90000
0,
b10000 5
b11001000110001010110100000110111110100110011100001100100010110011000101011000000 2
1#
#91000
0#
#92000
1!
0"
1#
#93000
0#
#94000
06
1/
1#
#95000
0#
#96000
1#
#97001
0#
#98001
1#
#99001
0#
#100001
1#
#101001
0#
#102001
1#
#103001
0#
#104001
1#
#105001
0#
#106001
0/
b0 2
b0 5
1#
1-
#107001
0#
#108001
1#
#109001
0#
#110001
1#
#111001
0#
#112001
1#
#113001
0#
#114001
1#
#115001
0#
#116001
1#
#117001
0#
#118001
1#
0-
#119001
0#
#120001
1#
#121001
0#
#122001
1#
#123001
0#
#124001
1#
#125001
0#
#126001
1#
#127001
0#
#128001
1#
#129001
0#
#130001
1#
#131001
0#
#132001
1#
#133001
0#
#134001
1#
#135001
0#
#136001
1#
#137001
0#
#138001
1#
#139001
0#
#140001
1#
#141001
0#
#142001
1#
#143001
0#
#144001
1#
#145001
0#
#146001
1#
#147001
0#
#148001
1#
#149001
0#
#150001
1#
#151001
0#
#152001
1#
#153001
0#
1"
0!
#154001
1,
b11001011 $
16
1#
#155001
0#
#156001
b1011 $
b1 5
b11001011 2
1#
#157001
0#
#158001
b1001001 $
b10 5
b1100101100001011 2
1#
#159001
0#
#160001
b11001110 $
b11 5
b110010110000101101001001 2
1#
#161001
0#
#162001
b10100011 $
b100 5
b11001011000010110100100111001110 2
1#
#163001
0#
#164001
b11011110 $
b101 5
b1100101100001011010010011100111010100011 2
1#
#165001
0#
#166001
b11110100 $
b110 5
b110010110000101101001001110011101010001111011110 2
1#
#167001
0#
#168001
b10000000 $
b111 5
b11001011000010110100100111001110101000111101111011110100 2
1#
#169001
0#
#170001
b1001101 $
b1000 5
b1100101100001011010010011100111010100011110111101111010010000000 2
1#
#171001
0#
#172001
b10110000 $
b1001 5
b110010110000101101001001110011101010001111011110111101001000000001001101 2
1#
#173001
0#
#174001
b10001100 $
b1010 5
b11001011000010110100100111001110101000111101111011110100100000000100110110110000 2
1#
#175001
0#
#176001
b10101001 $
b1011 5
b1011010010011100111010100011110111101111010010000000010011011011000010001100 2
1#
#177001
0#
#178001
b1001101 $
b1100 5
b1001001110011101010001111011110111101001000000001001101101100001000110010101001 2
1#
#179001
0#
#180001
b10110011 $
b1101 5
b11001110101000111101111011110100100000000100110110110000100011001010100101001101 2
1#
#181001
0#
#182001
b1110001 $
b1110 5
b10100011110111101111010010000000010011011011000010001100101010010100110110110011 2
1#
#183001
0#
#184001
b1111011 $
b1111 5
b11011110111101001000000001001101101100001000110010101001010011011011001101110001 2
1#
#185001
0#
#186001
b1000001 $
b10000 5
b11110100100000000100110110110000100011001010100101001101101100110111000101111011 2
1#
#187001
0#
#188001
b11101010 $
b10001 5
b10000000010011011011000010001100101010010100110110110011011100010111101101000001 2
1#
#189001
0#
#190001
b10001010 $
b10010 5
b1001101101100001000110010101001010011011011001101110001011110110100000111101010 2
1#
#191001
0#
#192001
b10011001 $
b10011 5
b10110000100011001010100101001101101100110111000101111011010000011110101010001010 2
1#
#193001
0#
#194001
b1010011 $
b10100 5
b10001100101010010100110110110011011100010111101101000001111010101000101010011001 2
1#
#195001
0#
#196001
b11100 $
b10101 5
b10101001010011011011001101110001011110110100000111101010100010101001100101010011 2
1#
#197001
0#
#198001
b11001000 $
b10110 5
b1001101101100110111000101111011010000011110101010001010100110010101001100011100 2
1#
#199001
0#
#200001
b11001010 $
b10111 5
b10110011011100010111101101000001111010101000101010011001010100110001110011001000 2
1#
#201001
0#
#202001
b111000 $
b11000 5
b1110001011110110100000111101010100010101001100101010011000111001100100011001010 2
1#
#203001
0#
#204001
b10010001 $
b11001 5
b1111011010000011110101010001010100110010101001100011100110010001100101000111000 2
1#
#205001
0#
#206001
b1001110 $
b11010 5
b1000001111010101000101010011001010100110001110011001000110010100011100010010001 2
1#
#207001
0#
#208001
b1110100 $
b11011 5
b11101010100010101001100101010011000111001100100011001010001110001001000101001110 2
1#
#209001
0#
#210001
b10111010 $
b11100 5
b10001010100110010101001100011100110010001100101000111000100100010100111001110100 2
1#
#211001
0#
#212001
b110010 $
b11101 5
b10011001010100110001110011001000110010100011100010010001010011100111010010111010 2
1#
#213001
0#
#214001
b11110100 $
b11110 5
b1010011000111001100100011001010001110001001000101001110011101001011101000110010 2
1#
#215001
0#
#216001
b11101100 $
b11111 5
b11100110010001100101000111000100100010100111001110100101110100011001011110100 2
1#
#217001
0#
#218001
b10001000 $
b100000 5
b11001000110010100011100010010001010011100111010010111010001100101111010011101100 2
1#
#219001
0#
#220001
b11111010 $
b100001 5
b11001010001110001001000101001110011101001011101000110010111101001110110010001000 2
1#
#221001
0#
#222001
b1001001 $
b100010 5
b111000100100010100111001110100101110100011001011110100111011001000100011111010 2
1#
#223001
0#
#224001
b1100001 $
b100011 5
b10010001010011100111010010111010001100101111010011101100100010001111101001001001 2
1#
#225001
0#
#226001
b10010010 $
b100100 5
b1001110011101001011101000110010111101001110110010001000111110100100100101100001 2
1#
#227001
0#
#228001
b1010110 $
b100101 5
b1110100101110100011001011110100111011001000100011111010010010010110000110010010 2
1#
#229001
0#
#230001
b10000111 $
b100110 5
b10111010001100101111010011101100100010001111101001001001011000011001001001010110 2
1#
#231001
0#
#232001
b1101110 $
b100111 5
b110010111101001110110010001000111110100100100101100001100100100101011010000111 2
1#
#233001
0#
#234001
b11110 $
b101000 5
b11110100111011001000100011111010010010010110000110010010010101101000011101101110 2
1#
#235001
0#
#236001
b1101111 $
b101001 5
b11101100100010001111101001001001011000011001001001010110100001110110111000011110 2
1#
#237001
0#
#238001
b10001100 $
b101010 5
b10001000111110100100100101100001100100100101011010000111011011100001111001101111 2
1#
#239001
0#
#240001
b110111 $
b101011 5
b11111010010010010110000110010010010101101000011101101110000111100110111110001100 2
1#
#241001
0#
#242001
b1100011 $
b101100 5
b1001001011000011001001001010110100001110110111000011110011011111000110000110111 2
1#
#243001
0#
#244001
b10111001 $
b101101 5
b1100001100100100101011010000111011011100001111001101111100011000011011101100011 2
1#
#245001
0#
#246001
b11110 $
b101110 5
b10010010010101101000011101101110000111100110111110001100001101110110001110111001 2
1#
#247001
0#
#248001
b110001 $
b101111 5
b1010110100001110110111000011110011011111000110000110111011000111011100100011110 2
1#
#249001
0#
#250001
b1110100 $
b110000 5
b10000111011011100001111001101111100011000011011101100011101110010001111000110001 2
1#
#251001
0#
#252001
b11111001 $
b110001 5
b1101110000111100110111110001100001101110110001110111001000111100011000101110100 2
1#
#253001
0#
#254001
0,
b110010 5
b11110011011111000110000110111011000111011100100011110001100010111010011111001 2
1#
#255001
0#
#256001
1!
0"
1#
#257001
0#
#258001
06
1/
1#
