Framing/framing.v

module ethernet_encapsulation 
#(
    parameter [47:0] destination_mac_addr  = 48'h023528fbdd66,
    parameter [47:0] source_mac_addr       = 48'h072227acdb65
)
(
    // Buffer tx ports
    input [7:0] data_in ,
    input       data_in_clk,read_en,
    input       buffer_ready, buffer_empt,
    output  reg    data_recive,

    // Transmission ports
    output [7:0]    gmii_data_out,
    output          gmii_clk_o, en_tx,
    input           gmii_clk_i,clk,rst,
    output          gmii_er, gmii_en
);

// Dump waveforms with makefile
`ifdef COCOTB_SIM
initial begin
    $dumpfile("sim.vcd");
    $dumpvars(0,ethernet_encapsulation);
end    
`endif

    reg buffer_data_valid= 0;

    reg         [3:0]               state_reg = 0;
    reg        [7:0]               data_out;
    reg                         gmii_o_en = 0;
    reg    [8*10-1:0]         data_buf;
    wire                        update_state;
    reg                        data_out_en;

    localparam  IDLE                = 4'd0,
                PERMABLE            = 4'd1,
                SDF                 = 4'd2,  
                LEN                 = 4'd3,
                PAYLOAD             = 4'd4,  
                FCS                 = 4'd5,
                EXT                 = 4'd6,
                Dest_MAC            = 4'd7,
                Source_Mac          = 4'd8;

    reg  fill_buf = 0;           
    localparam  REC                 = 2'd0,
                Init_rec            = 2'd1;

    integer j;
   
    reg [47:0] mac_addr_des ;
    reg [47:0] mac_addr_src ;
    
    localparam Permable_val = 8'b101010,
               Start_Del_val= 8'b101011;
    localparam min_payload_len = 16'd46;
    localparam      len_addr    = 6,
                    len_len     = 2,
                    len_crc     = 4,
                    len_perm    = 7;
    integer i = 0;

    reg [13:0] len_payload = 0;
    reg [31:0] crc_res;
    
    always @(*) begin
        case (state_reg)
            IDLE        :   begin
                                data_out    =   0;
                                data_out_en =   0;
                            end

            PERMABLE    :   begin
                                data_out_en =   1;
                                data_out    =   Permable_val;
                            end

            SDF         :  begin
                                data_out_en =   1;
                                data_out    =  Start_Del_val;
                            end

            Dest_MAC    :   begin
                                data_out_en =   1;
                                data_out    = destination_mac_addr[(8*(len_addr-i)-1)-:8]; 
                            end

            Source_Mac  :   begin
                                data_out_en =   1;
                                data_out    = source_mac_addr[(8*(len_addr-i)-1)-:8]; 
                            end

            LEN         :   begin
                                data_out_en =   1;
                                data_out = len_payload[((8*(len_len-i)-1)-1)-:8];
                            end

            PAYLOAD     :   begin
                                data_out_en =   1;
                                data_out = len_payload[((8*(len_len-i)-1)-1)-:8];
                            end

            EXT         :   begin
                                data_out    =   1;
                                data_out_en =   0;
                            end

            FCS         :   begin
                                data_out    =   1;
                                data_out = crc_res[(8*(len_crc-i)-1)-:8];
                            end

            default     :   begin
                                 data_out_en =   0;
                            end 
        endcase
    end





    // Ethernet Frame Stages
    always @(posedge clk) begin
        if (rst) begin
            i = 0;
            state_reg = IDLE;
            mac_addr_des = destination_mac_addr;
            mac_addr_src = source_mac_addr;
        end 
        else begin
            if (en_tx) begin
                    case (state_reg)
                        IDLE:       begin
                                        if (buffer_data_valid) begin
                                            state_reg = PERMABLE;
                                        end
                                    end 
                        PERMABLE:   begin
                                        if(i < len_perm-1 ) begin
                                            i  = i +1;
                                        end 
                                        else begin
                                            state_reg = SDF;
                                            i = 0;
                                        end
                                    end
                        SDF:        begin
                                        state_reg   = Dest_MAC;
                                    end
                        Dest_MAC:   begin
                                        if (i < len_addr-1) begin
                                            i = i + 1;
                                        end 
                                        else begin
                                            i= 0;
                                            state_reg = Source_Mac;
                                        end
                                    end
                        Source_Mac: begin
                                        if (i < len_addr-1) begin
                                            i = i + 1;
                                        end 
                                        else begin
                                            i= 0;
                                            state_reg = LEN;
                                        end  
                                    end
                        LEN:        begin
                                        if (i < len_len-1) begin
                                            i = i + 1;
                                        end 
                                        else begin
                                            i= 0;
                                            state_reg = PAYLOAD;
                                        end  
                                    end
                        PAYLOAD:    begin
                                        if (i < len_payload-1) begin
                                            i = i + 1;
                                            state_reg = PAYLOAD;
                                        end 
                                        else begin
                                            i= 0;
                                            if (len_payload <= min_payload_len)
                                                state_reg = EXT;
                                            else
                                                state_reg = FCS;
                                        end  
                                    end

                        EXT:        begin
                                        if (i < min_payload_len-len_payload-1) begin
                                            i = i + 1;
                                        end 
                                        else begin
                                            state_reg = FCS;
                                            i = 0;
                                        end
                                    end

                        FCS:        begin
                                        if (i < len_crc-1) begin
                                            i = i + 1;
                                        end 
                                        else begin
                                            i= 0;
                                            state_reg = IDLE;
                                        end 
                                    end

                        default: state_reg = IDLE;
                    endcase
            end
                else state_reg = IDLE;
        end 
    end

    // Fill the payload buffer
    always @(posedge clk) begin
        case (fill_buf)
        REC    :    
                    begin
                            if (buffer_ready) begin
                                data_recive         = 1;
                                fill_buf            = Init_rec; 
                                buffer_data_valid   = 0;
                                len_payload         = 0; //Problematic
                            end
                    end 
        Init_rec: 
                    begin
                            if(read_en) begin
                                data_buf        =   data_buf <<8;
                                data_buf[7:0]   =   data_in;
                                len_payload     =   len_payload +1;
                            end
                            else
                                if (buffer_empt) begin
                                    buffer_data_valid <= 1;
                                    fill_buf   <=REC;
                                end
                    end
        default: fill_buf   <=REC;
        endcase
    end




endmodule


// Issues
// The fifo clock ? 
// Make Recive stage ascnh
// len_payload calc

Framing/sim.vcd
$date
	Wed Mar 29 11:44:52 2023
$end
$version
	Icarus Verilog
$end
$timescale
	1ps
$end
$scope module ethernet_encapsulation $end
$var wire 1 ! buffer_empt $end
$var wire 1 " buffer_ready $end
$var wire 1 # clk $end
$var wire 8 $ data_in [7:0] $end
$var wire 1 % data_in_clk $end
$var wire 1 & en_tx $end
$var wire 1 ' gmii_clk_i $end
$var wire 1 ( gmii_clk_o $end
$var wire 8 ) gmii_data_out [7:0] $end
$var wire 1 * gmii_en $end
$var wire 1 + gmii_er $end
$var wire 1 , read_en $end
$var wire 1 - rst $end
$var reg 1 . buffer_data_valid $end
$var reg 32 / crc_res [31:0] $end
$var reg 80 0 data_buf [79:0] $end
$var reg 8 1 data_out [7:0] $end
$var reg 1 2 data_out_en $end
$var reg 1 3 data_recive $end
$var reg 1 4 fill_buf $end
$var reg 1 5 gmii_o_en $end
$var reg 14 6 len_payload [13:0] $end
$var reg 48 7 mac_addr_des [47:0] $end
$var reg 48 8 mac_addr_src [47:0] $end
$var reg 4 9 state_reg [3:0] $end
$var integer 32 : i [31:0] $end
$upscope $end
$enddefinitions $end
#0
$dumpvars
b0 :
b0 9
bx 8
bx 7
b0 6
05
04
x3
02
b0 1
bx 0
bx /
0.
z-
z,
z+
z*
bz )
z(
z'
z&
z%
bz $
1#
z"
z!
$end
#1000
0#
#2000
1#
#3000
0#
#4000
1#
#5000
0#
#6000
1#
#7000
0#
#8000
1#
#9000
0#
#10000
b1110010001000100111101011001101101101100101 8
b100011010100101000111110111101110101100110 7
1#
1-
#11000
0#
#12000
1#
#13000
0#
#14000
1#
#15000
0#
#16000
1#
#17000
0#
#18000
1#
#19000
0#
#20000
1#
#21000
0#
#22000
1#
0-
#23000
0#
#24000
1#
#25000
0#
#26000
1#
#27000
0#
#28000
1#
#29000
0#
#30000
1#
#31000
0#
#32000
1#
#33000
0#
#34000
1#
#35000
0#
#36000
1#
#37000
0#
#38000
1#
#39000
0#
#40000
1#
#41000
0#
#42000
1#
#43000
0#
#44000
1#
#45000
0#
#46000
1#
#47000
0#
#48000
1#
#49000
0#
#50000
1#
#51000
0#
#52000
1#
#53000
0#
#54000
1#
#55000
0#
#56000
1#
#57000
0#
1"
0!
#58000
1,
b11100111 $
14
13
1#
#59000
0#
#60000
b11001110 $
b1 6
bx11100111 0
1#
#61000
0#
#62000
b10110010 $
b10 6
bx1110011111001110 0
1#
#63000
0#
#64000
b11001101 $
b11 6
bx111001111100111010110010 0
1#
#65000
0#
#66000
b10000100 $
b100 6
bx11100111110011101011001011001101 0
1#
#67000
0#
#68000
b11101110 $
b101 6
bx1110011111001110101100101100110110000100 0
1#
#69000
0#
#70000
b101000 $
b110 6
bx111001111100111010110010110011011000010011101110 0
1#
#71000
0#
#72000
b11100011 $
b111 6
bx11100111110011101011001011001101100001001110111000101000 0
1#
#73000
0#
#74000
b10101111 $
b1000 6
bx1110011111001110101100101100110110000100111011100010100011100011 0
1#
#75000
0#
#76000
b1101 $
b1001 6
bx111001111100111010110010110011011000010011101110001010001110001110101111 0
1#
#77000
0#
#78000
b11100 $
b1010 6
b11100111110011101011001011001101100001001110111000101000111000111010111100001101 0
1#
#79000
0#
#80000
b100101 $
b1011 6
b11001110101100101100110110000100111011100010100011100011101011110000110100011100 0
1#
#81000
0#
#82000
b10110000 $
b1100 6
b10110010110011011000010011101110001010001110001110101111000011010001110000100101 0
1#
#83000
0#
#84000
b1011001 $
b1101 6
b11001101100001001110111000101000111000111010111100001101000111000010010110110000 0
1#
#85000
0#
#86000
b10111100 $
b1110 6
b10000100111011100010100011100011101011110000110100011100001001011011000001011001 0
1#
#87000
0#
#88000
b111110 $
b1111 6
b11101110001010001110001110101111000011010001110000100101101100000101100110111100 0
1#
#89000
0#
#90000
0,
b10000 6
b101000111000111010111100001101000111000010010110110000010110011011110000111110 0
1#
#91000
0#
#92000
1!
0"
1#
#93000
0#
#94000
04
1.
1#
#95000
0#
#96000
1#
#97001
0#
#98001
1#
#99001
0#
#100001
1#
#101001
0#
#102001
1#
#103001
0#
#104001
1#
#105001
0#
#106001
1#
1-
#107001
0#
#108001
1#
#109001
0#
#110001
1#
#111001
0#
#112001
1#
#113001
0#
#114001
1#
#115001
0#
#116001
1#
#117001
0#
#118001
1#
0-
#119001
0#
#120001
1#
#121001
0#
#122001
1#
#123001
0#
#124001
1#
#125001
0#
#126001
1#
#127001
0#
#128001
1#
#129001
0#
#130001
1#
#131001
0#
#132001
1#
#133001
0#
#134001
1#
#135001
0#
#136001
1#
#137001
0#
#138001
1#
#139001
0#
#140001
1#
#141001
0#
#142001
1#
#143001
0#
#144001
1#
#145001
0#
#146001
1#
#147001
0#
#148001
1#
#149001
0#
#150001
1#
#151001
0#
#152001
1#
#153001
0#
1"
0!
#154001
1,
b11101010 $
b0 6
0.
14
1#
#155001
0#
#156001
b1101101 $
b1 6
b11100011101011110000110100011100001001011011000001011001101111000011111011101010 0
1#
#157001
0#
#158001
b1101011 $
b10 6
b10101111000011010001110000100101101100000101100110111100001111101110101001101101 0
1#
#159001
0#
#160001
b11001 $
b11 6
b1101000111000010010110110000010110011011110000111110111010100110110101101011 0
1#
#161001
0#
#162001
b110000 $
b100 6
b11100001001011011000001011001101111000011111011101010011011010110101100011001 0
1#
#163001
0#
#164001
b101010 $
b101 6
b100101101100000101100110111100001111101110101001101101011010110001100100110000 0
1#
#165001
0#
#166001
b10001 $
b110 6
b10110000010110011011110000111110111010100110110101101011000110010011000000101010 0
1#
#167001
0#
#168001
b1010111 $
b111 6
b1011001101111000011111011101010011011010110101100011001001100000010101000010001 0
1#
#169001
0#
#170001
b11011000 $
b1000 6
b10111100001111101110101001101101011010110001100100110000001010100001000101010111 0
1#
#171001
0#
#172001
b1011100 $
b1001 6
b111110111010100110110101101011000110010011000000101010000100010101011111011000 0
1#
#173001
0#
#174001
b1011101 $
b1010 6
b11101010011011010110101100011001001100000010101000010001010101111101100001011100 0
1#
#175001
0#
#176001
b11 $
b1011 6
b1101101011010110001100100110000001010100001000101010111110110000101110001011101 0
1#
#177001
0#
#178001
b11100 $
b1100 6
b1101011000110010011000000101010000100010101011111011000010111000101110100000011 0
1#
#179001
0#
#180001
b1001111 $
b1101 6
b11001001100000010101000010001010101111101100001011100010111010000001100011100 0
1#
#181001
0#
#182001
b11010110 $
b1110 6
b110000001010100001000101010111110110000101110001011101000000110001110001001111 0
1#
#183001
0#
#184001
b1101 $
b1111 6
b101010000100010101011111011000010111000101110100000011000111000100111111010110 0
1#
#185001
0#
#186001
b10110101 $
b10000 6
b10001010101111101100001011100010111010000001100011100010011111101011000001101 0
1#
#187001
0#
#188001
b11100001 $
b10001 6
b1010111110110000101110001011101000000110001110001001111110101100000110110110101 0
1#
#189001
0#
#190001
b111001 $
b10010 6
b11011000010111000101110100000011000111000100111111010110000011011011010111100001 0
1#
#191001
0#
#192001
b11111010 $
b10011 6
b1011100010111010000001100011100010011111101011000001101101101011110000100111001 0
1#
#193001
0#
#194001
b111010 $
b10100 6
b1011101000000110001110001001111110101100000110110110101111000010011100111111010 0
1#
#195001
0#
#196001
b11011111 $
b10101 6
b11000111000100111111010110000011011011010111100001001110011111101000111010 0
1#
#197001
0#
#198001
b10111111 $
b10110 6
b11100010011111101011000001101101101011110000100111001111110100011101011011111 0
1#
#199001
0#
#200001
b10110000 $
b10111 6
b1001111110101100000110110110101111000010011100111111010001110101101111110111111 0
1#
#201001
0#
#202001
b110100 $
b11000 6
b11010110000011011011010111100001001110011111101000111010110111111011111110110000 0
1#
#203001
0#
#204001
b1101101 $
b11001 6
b1101101101011110000100111001111110100011101011011111101111111011000000110100 0
1#
#205001
0#
#206001
b10000 $
b11010 6
b10110101111000010011100111111010001110101101111110111111101100000011010001101101 0
1#
#207001
0#
#208001
b11010001 $
b11011 6
b11100001001110011111101000111010110111111011111110110000001101000110110100010000 0
1#
#209001
0#
#210001
b1111101 $
b11100 6
b111001111110100011101011011111101111111011000000110100011011010001000011010001 0
1#
#211001
0#
#212001
b10100011 $
b11101 6
b11111010001110101101111110111111101100000011010001101101000100001101000101111101 0
1#
#213001
0#
#214001
b1100 $
b11110 6
b111010110111111011111110110000001101000110110100010000110100010111110110100011 0
1#
#215001
0#
#216001
b101110 $
b11111 6
b11011111101111111011000000110100011011010001000011010001011111011010001100001100 0
1#
#217001
0#
#218001
b1110000 $
b100000 6
b10111111101100000011010001101101000100001101000101111101101000110000110000101110 0
1#
#219001
0#
#220001
b100 $
b100001 6
b10110000001101000110110100010000110100010111110110100011000011000010111001110000 0
1#
#221001
0#
#222001
b1001100 $
b100010 6
b110100011011010001000011010001011111011010001100001100001011100111000000000100 0
1#
#223001
0#
#224001
b11001001 $
b100011 6
b1101101000100001101000101111101101000110000110000101110011100000000010001001100 0
1#
#225001
0#
#226001
b101010 $
b100100 6
b10000110100010111110110100011000011000010111001110000000001000100110011001001 0
1#
#227001
0#
#228001
b10 $
b100101 6
b11010001011111011010001100001100001011100111000000000100010011001100100100101010 0
1#
#229001
0#
#230001
b1100001 $
b100110 6
b1111101101000110000110000101110011100000000010001001100110010010010101000000010 0
1#
#231001
0#
#232001
b10000 $
b100111 6
b10100011000011000010111001110000000001000100110011001001001010100000001001100001 0
1#
#233001
0#
#234001
b110 $
b101000 6
b1100001011100111000000000100010011001100100100101010000000100110000100010000 0
1#
#235001
0#
#236001
b10001010 $
b101001 6
b101110011100000000010001001100110010010010101000000010011000010001000000000110 0
1#
#237001
0#
#238001
b100111 $
b101010 6
b1110000000001000100110011001001001010100000001001100001000100000000011010001010 0
1#
#239001
0#
#240001
b100100 $
b101011 6
b100010011001100100100101010000000100110000100010000000001101000101000100111 0
1#
#241001
0#
#242001
b10001001 $
b101100 6
b1001100110010010010101000000010011000010001000000000110100010100010011100100100 0
1#
#243001
0#
#244001
b10001000 $
b101101 6
b11001001001010100000001001100001000100000000011010001010001001110010010010001001 0
1#
#245001
0#
#246001
b11011110 $
b101110 6
b101010000000100110000100010000000001101000101000100111001001001000100110001000 0
1#
#247001
0#
#248001
b11000011 $
b101111 6
b10011000010001000000000110100010100010011100100100100010011000100011011110 0
1#
#249001
0#
#250001
b10100111 $
b110000 6
b1100001000100000000011010001010001001110010010010001001100010001101111011000011 0
1#
#251001
0#
#252001
b101011 $
b110001 6
b10000000001101000101000100111001001001000100110001000110111101100001110100111 0
1#
#253001
0#
#254001
0,
b110010 6
b110100010100010011100100100100010011000100011011110110000111010011100101011 0
1#
#255001
0#
#256001
1!
0"
1#
#257001
0#
#258001
04
1.
1#
