Framing/framing.v

module ethernet_encapsulation 
#(
    parameter [47:0] destination_mac_addr  = 48'h023528fbdd66,
    parameter [47:0] source_mac_addr       = 48'h072227acdb65
)
(
    // Buffer tx ports
    input [7:0] data_in ,
    input       data_in_clk,read_en,
    input       buffer_ready, buffer_empt,
    output  reg    data_recive,

    // Transmission ports
    output [7:0]    gmii_data_out,
    output          gmii_clk_o, en_tx,
    input           gmii_clk_i,clk,rst,
    output          gmii_er, gmii_en
);

// Dump waveforms with makefile
`ifdef COCOTB_SIM
initial begin
    $dumpfile("sim.vcd");
    $dumpvars(0,ethernet_encapsulation);
end    
`endif

    reg buffer_data_valid= 0;

    reg     [3:0]               state_reg;
    reg     [7:0]               data_out;
    reg                         gmii_o_en = 0;
    reg    [8*10-1:0]         data_buf;
    wire                        update_state;

    localparam  IDLE                = 4'd0,
                PERMABLE            = 4'd1,
                SDF                 = 4'd2,  
                LEN                 = 4'd3,
                PAYLOAD             = 4'd4,  
                FCS                 = 4'd5,
                EXT                 = 4'd6,
                Dest_MAC            = 4'd7,
                Source_Mac          = 4'd8;

    reg  fill_buf = 0;           
    localparam  REC                 = 2'd0,
                Init_rec            = 2'd1;

    integer j;
   
    reg [47:0] mac_addr_des ;
    reg [47:0] mac_addr_src ;
    wire [7:0] addr;
    assign addr = (state_reg[0] == 1)? mac_addr_des[7:0] : mac_addr_src[7:0];
    
    
    
    localparam Permable = 8'b101010,
               Start_Del= 8'b101011;
    localparam min_payload_len = 16'd46;
    
    integer i = 0;

    reg [15:0] len_payload;
    reg [31:0] crc_res;
    
    
    // Ethernet Frame Stages
    always @(posedge clk) begin
        if (rst) begin
            i = 0;
            state_reg = IDLE;
            mac_addr_des = destination_mac_addr;
            mac_addr_src = source_mac_addr;
        end else begin
            if (en_tx) begin
                case (state_reg)
                    IDLE:       begin
                                    if (buffer_data_valid) begin
                                        state_reg = PERMABLE;
                                    end
                                end 
                    PERMABLE:   begin
                                    if(i <= 7) begin
                                        data_out = Permable;
                                        i  = i +1;
                                    end else begin
                                        state_reg = SDF;
                                        i = 0;
                                    end
                                end
                    SDF:         begin
                                    data_out    = Start_Del;
                                    state_reg   = Dest_MAC;
                                end
                    Dest_MAC:   begin
                                    if (i <= 6) begin
                                        data_out = addr;
                                        i = i + 1;
                                        mac_addr_des = mac_addr_des >> 8; 
                                    end else begin
                                        i= 0;
                                        state_reg = Source_Mac;
                                    end
                                end
                    Source_Mac: begin
                                    if (i <= 6) begin
                                        data_out = addr;
                                        i = i + 1;
                                        mac_addr_src = mac_addr_src >> 8; 
                                    end else begin
                                        i= 0;
                                        state_reg = LEN;
                                    end  
                                end
                    LEN:        begin
                                    if (i <= 2) begin
                                        data_out = len_payload[i];
                                        i = i + 1;
                                    end else begin
                                        i= 0;
                                        state_reg = LEN;
                                    end  
                                end
                    PAYLOAD:    begin
                                    if (i <= len_payload) begin
                                        data_out = data_buf[8*(len_payload-i) -:8];
                                        i = i + 1;
                                        state_reg = PAYLOAD;
                                    end else begin
                                        i= 0;
                                        if (len_payload <= min_payload_len) begin
                                            state_reg = EXT;
                                        end else
                                            state_reg = FCS;
                                    end  
                                end

                    EXT:        begin
                                    if (i <= min_payload_len-len_payload) begin
                                        data_out = 0;
                                        i = i + 1;
                                    end else
                                        state_reg = FCS;
                                end

                    FCS:        begin
                                    if (i <= 4) begin
                                        data_out = crc_res[8*(len_payload-i) -:8];
                                        i = i + 1;
                                    end else begin
                                        i= 0;
                                        state_reg = IDLE;
                                    end 
                                end

                    default: state_reg = IDLE;
                endcase
                end
            else begin
            
            end
        end 
    end

    // Fill the payload buffer
    always @(posedge clk) begin
        case (fill_buf)
        REC    :    
                    begin
                            buffer_data_valid <=0;
                            if (buffer_ready) begin
                                data_recive = 1;
                                fill_buf    = Init_rec; 
                            end
                    end 
        Init_rec: 
                    begin
                            if(read_en) begin
                                    data_buf        =   data_buf <<8;
                                    data_buf[7:0]   =   data_in;
                            end
                            else
                                if(!(read_en)) begin
                                    state_reg   <=REC;
                                    if (buffer_empt) begin
                                        buffer_data_valid <= 1;
                                    end
                                end
                    end
        default: state_reg   <=IDLE;
        endcase
    end




endmodule


// Issues
// The fifo clock ? 
// Make Recive stage ascnh
// len_payload calc

Framing/sim.vcd
$date
	Tue Mar 28 13:44:43 2023
$end
$version
	Icarus Verilog
$end
$timescale
	1ps
$end
$scope module ethernet_encapsulation $end
$var wire 1 ! buffer_empt $end
$var wire 1 " buffer_ready $end
$var wire 1 # clk $end
$var wire 8 $ data_in [7:0] $end
$var wire 1 % data_in_clk $end
$var wire 1 & en_tx $end
$var wire 1 ' gmii_clk_i $end
$var wire 1 ( gmii_clk_o $end
$var wire 8 ) gmii_data_out [7:0] $end
$var wire 1 * gmii_en $end
$var wire 1 + gmii_er $end
$var wire 1 , read_en $end
$var wire 1 - rst $end
$var wire 8 . addr [7:0] $end
$var reg 1 / buffer_data_valid $end
$var reg 32 0 crc_res [31:0] $end
$var reg 80 1 data_buf [79:0] $end
$var reg 8 2 data_out [7:0] $end
$var reg 1 3 data_recive $end
$var reg 1 4 fill_buf $end
$var reg 1 5 gmii_o_en $end
$var reg 16 6 len_payload [15:0] $end
$var reg 48 7 mac_addr_des [47:0] $end
$var reg 48 8 mac_addr_src [47:0] $end
$var reg 4 9 state_reg [3:0] $end
$var integer 32 : i [31:0] $end
$upscope $end
$enddefinitions $end
#0
$dumpvars
b0 :
bx 9
bx 8
bx 7
bx 6
05
04
x3
bx 2
bx 1
bx 0
0/
bx .
z-
z,
z+
z*
bz )
z(
z'
z&
z%
bz $
1#
z"
z!
$end
#1000
0#
#2000
1#
#3000
0#
#4000
1#
#5000
0#
#6000
1#
#7000
0#
#8000
1#
#9000
0#
#10000
b1100101 .
b1110010001000100111101011001101101101100101 8
b100011010100101000111110111101110101100110 7
b0 9
1#
1-
#11000
0#
#12000
1#
#13000
0#
#14000
1#
#15000
0#
#16000
1#
#17000
0#
#18000
1#
#19000
0#
#20000
1#
#21000
0#
#22000
1#
0-
#23000
0#
#24000
1#
#25000
0#
#26000
1#
#27000
0#
#28000
1#
#29000
0#
#30000
1#
#31000
0#
#32000
1#
#33000
0#
#34000
1#
#35000
0#
#36000
1#
#37000
0#
#38000
1#
#39000
0#
#40000
1#
#41000
0#
#42000
14
13
1#
1"
1,
b100011 $
#43000
0#
#44000
b1010010 $
bx00100011 1
1#
#45000
0#
#46000
b1011111 $
bx0010001101010010 1
1#
#47000
0#
#48000
b111111 $
bx001000110101001001011111 1
1#
#49000
0#
#50000
b11001 $
bx00100011010100100101111100111111 1
1#
#51000
0#
#52000
b110100 $
bx0010001101010010010111110011111100011001 1
1#
#53000
0#
#54000
b10010110 $
bx001000110101001001011111001111110001100100110100 1
1#
#55000
0#
#56000
b11111001 $
bx00100011010100100101111100111111000110010011010010010110 1
1#
#57000
0#
#58000
b11000011 $
bx0010001101010010010111110011111100011001001101001001011011111001 1
1#
#59000
0#
#60000
bx001000110101001001011111001111110001100100110100100101101111100111000011 1
1#
