Encapsulation/utils.vh
`define min_payload_len                 16'd46
`define len_addr                        13'd6
`define len_len                         13'd2
`define len_crc                         13'd4
`define len_perm                        13'd7
`define len_max_payload                 50

Decapsulation/decapsulation.v
`include "utils.vh"

module ethernet_decapsulation 
#(
    parameter [47:0] destination_mac_addr  = 48'h023528fbdd66,
    parameter [47:0] source_mac_addr       = 48'h072227acdb65
)
(
    // Output Payload
    output  reg     crc_err,adr_err,len_err, buffer_full,
    output data_out_en,

    // Ethernet RX Transmission ports
    input [7:0]     gmii_data_in,
    input           gmii_dv,gmii_er,gmii_en,clk,rst
);

// Dump waveforms with makefile
`ifdef COCOTB_SIM
initial begin
    $dumpfile("sim.vcd");
    $dumpvars(0,ethernet_decapsulation);
end    
`endif

    //  Define Registers
    reg         [3:0]                   state_reg = 0;                               // FSM State register, keep track of frame section 
    reg         [8*10-1:0]              data_buf;                                    // Payload Buffer that holds data
    reg         [13:0]                  byte_count = 0;                              // Track bytes in each state
    reg         [31:0]                 crc_res     = {(`len_crc){1'b1}};             // Initate CRC, update with every processed byte
    reg         [15:0]                 len_payload = 0;                              // Keep track of every Recived Payload Length
    
    wire                               cont_stages;
    reg         [8*`len_addr-1:0]                  source_addr;
    reg         [8*`len_addr-1:0]                  dest_addr;
    reg         [8*`len_len-1:0]                    data_len;                       
    reg         [8*`len_crc-1:0]                    data_crc;  
    reg         [7:0] gmii_buf;

    //  Ethernet Frame Encapsulation Stages
    localparam  IDLE                = 4'd0,
                PERMABLE            = 4'd1,
                SDF                 = 4'd2,  
                LEN                 = 4'd3,
                PAYLOAD             = 4'd4,  
                FCS                 = 4'd5,
                EXT                 = 4'd6,
                Dest_MAC            = 4'd7,
                Source_Mac          = 4'd8,
                Err                 = 4'd9;

    localparam Permable_val = 8'b101010,                            
               Start_Del_val= 8'b101011;                                            // IEEE defined Permable and Delimeter bytes


    assign data_out_en = (state_reg == IDLE)? 1'b1:1'b0;
    // Bufferred Data should not be transmitted while still receiving
    assign cont_stages = (gmii_en && gmii_dv && !(gmii_er))? 1'b1:1'b0 ;

    // Select the right output according to stages
    always @(*) begin
        case (state_reg)            
            IDLE        : data_buf    =   0;

            PERMABLE    : data_buf    =   0;
                            
            SDF         : data_buf    =   0;

            Dest_MAC    : dest_addr[8*(`len_addr-byte_count)+:8]         =    gmii_buf ; 
                         
            Source_Mac  : source_addr[8*(`len_addr-byte_count)+:8]       =    gmii_buf;

            LEN         : data_len[8*(`len_addr-byte_count)-1+:8]          =    gmii_buf;

            PAYLOAD     : data_buf[8*(len_payload-byte_count)-1+:8]        =   gmii_buf;

            EXT         : data_buf    =     0;

            FCS         : data_crc[8*(`len_crc-byte_count)-1+:8]           =    gmii_buf;
        endcase
    end


    // Ethernet Frame Stages
    always @(posedge clk) begin
        if (!rst) begin
            if (gmii_en) begin
                    case (state_reg)
                        IDLE:       begin
                                        if (gmii_en && gmii_dv) begin
                                            state_reg   = PERMABLE;
                                            gmii_buf    = gmii_data_in;
                                            byte_count  = byte_count +1;
                                        end
                                        else if (gmii_er) begin
                                            state_reg =Err;
                                            byte_count  = 0;
                                        end
                                    end 
                        PERMABLE:   begin
                                        if(byte_count < `len_perm-1 ) begin
                                            byte_count  = byte_count +1;
                                        end 
                                        else begin
                                            state_reg = SDF;
                                            byte_count = 0;
                                        end
                                    end
                        SDF:  begin
                                        state_reg   = Dest_MAC;
                                    end
                        Dest_MAC:   begin
                                        gmii_buf  = gmii_data_in;
                                        if (byte_count < `len_addr-1) begin
                                            byte_count = byte_count + 1;
                                        end 
                                        else begin
                                            byte_count= 0;
                                            state_reg = Source_Mac;
                                        end
                                    end
                        Source_Mac: begin
                                        gmii_buf  = gmii_data_in;
                                        if (byte_count < `len_addr-1) begin
                                            byte_count = byte_count + 1;
                                        end 
                                        else begin
                                            byte_count= 0;
                                            state_reg = LEN;
                                        end  
                                    end
                        LEN:        begin
                                        gmii_buf  = gmii_data_in;
                                        if (byte_count < `len_len-1) begin
                                            byte_count = byte_count + 1;
                                        end 
                                        else begin
                                            byte_count= 0;
                                            state_reg = PAYLOAD;
                                        end  
                                    end
                        PAYLOAD:    begin
                                        gmii_buf  = gmii_data_in;
                                        if (byte_count < len_payload-1) begin
                                            byte_count = byte_count + 1;
                                            state_reg = PAYLOAD;
                                        end 
                                        else begin
                                            byte_count= 0;
                                            if (len_payload <= `min_payload_len)
                                                state_reg = EXT;
                                            else
                                                state_reg = FCS;
                                        end  
                                    end

                        EXT:        begin
                                        gmii_buf  = gmii_data_in;
                                        if (byte_count < `min_payload_len-len_payload-1) begin
                                            byte_count = byte_count + 1;
                                        end 
                                        else begin
                                            state_reg = FCS;
                                            byte_count = 0;
                                        end
                                    end

                        FCS:        begin
                                        gmii_buf  = gmii_data_in;
                                        if (byte_count < `len_crc-1) begin
                                            byte_count = byte_count + 1;
                                        end 
                                        else begin
                                            byte_count= 0;
                                            state_reg = IDLE;
                                        end 
                                    end
                        Err:        begin
                            
                                    end

                        default: state_reg = IDLE;
                    endcase
            end
        end 
    end


    //  Global Synchronous Reset
    always @(posedge clk ) begin
        if (rst) begin
            len_payload                     = 0;
            state_reg                       =IDLE;
            data_buf                        = 0;
            crc_res                         = {(`len_crc){1'b1}};
            source_addr                     = 0;
            dest_addr                       = 0;
            data_len                        = 0;
            data_crc                        = 0;
            source_addr                     = 0;
            dest_addr                       = 0;
            data_len                        = 0;
            data_crc                        = 0;
        end
    end

endmodule

Decapsulation/sim.vcd
$date
	Fri Mar 31 12:45:22 2023
$end
$version
	Icarus Verilog
$end
$timescale
	1ps
$end
$scope module ethernet_decapsulation $end
$var wire 1 ! clk $end
$var wire 8 " gmii_data_in [7:0] $end
$var wire 1 # gmii_dv $end
$var wire 1 $ gmii_en $end
$var wire 1 % gmii_er $end
$var wire 1 & rst $end
$var wire 1 ' data_out_en $end
$var wire 1 ( cont_stages $end
$var reg 1 ) adr_err $end
$var reg 1 * buffer_full $end
$var reg 14 + byte_count [13:0] $end
$var reg 1 , crc_err $end
$var reg 32 - crc_res [31:0] $end
$var reg 80 . data_buf [79:0] $end
$var reg 32 / data_crc [31:0] $end
$var reg 16 0 data_len [15:0] $end
$var reg 48 1 dest_addr [47:0] $end
$var reg 8 2 gmii_buf [7:0] $end
$var reg 1 3 len_err $end
$var reg 16 4 len_payload [15:0] $end
$var reg 48 5 source_addr [47:0] $end
$var reg 4 6 state_reg [3:0] $end
$upscope $end
$enddefinitions $end
#0
$dumpvars
b0 6
bx 5
b0 4
x3
bx 2
bx 1
bx 0
bx /
bx .
b1111 -
x,
b0 +
x*
x)
x(
1'
z&
z%
z$
z#
bz "
1!
$end
#5000
0!
#10000
b0 /
b0 0
b0 1
b0 5
b0 .
1!
1&
#15000
0!
#20000
1!
#22000
0&
#25000
0!
#30000
1!
#35000
0!
#40000
1!
#45000
0!
#50000
1!
#55000
0!
#60000
1!
#65000
0!
#70000
1!
#75000
0!
#80000
1!
#85000
0!
#87000
0(
0$
#90000
1!
#95000
0!
#100000
1!
#105000
0!
#110000
1(
b101010 "
0%
1#
1$
1!
#115000
0!
#120000
0'
b1 +
b101010 2
b1 6
1!
#125000
0!
#130000
b10 +
1!
#135000
0!
#140000
b11 +
1!
#145000
0!
#150000
b100 +
1!
#155000
0!
#160000
b101 +
1!
#165000
0!
#170000
b110 +
1!
#175000
0!
#180000
b101011 "
b0 +
b10 6
1!
#185000
0!
#190000
b10 "
b111 6
1!
#195000
0!
#200000
b110101 "
b1 +
b100000000000000000000000000000000000000000 1
1!
#205000
0!
#210000
b101000 "
b10 +
b100011010100000000000000000000000000000000 1
1!
#215000
0!
#220000
b11111011 "
b11 +
b100011010100101000000000000000000000000000 1
1!
#225000
0!
#230000
b11011101 "
b100 +
b100011010100101000111110110000000000000000 1
1!
#235000
0!
#240000
b1100110 "
b101 +
b100011010100101000111110111101110100000000 1
1!
#245000
0!
#250000
b111 "
b1000 6
b0 +
b100011010100101000111110111101110101100110 1
1!
#255000
0!
#260000
b100010 "
b1 +
b1110000000000000000000000000000000000000000 5
1!
#265000
0!
#270000
b100111 "
b10 +
b1110010001000000000000000000000000000000000 5
1!
#275000
0!
#280000
b10101100 "
b11 +
b1110010001000100111000000000000000000000000 5
1!
#285000
0!
#290000
b11011011 "
b100 +
b1110010001000100111101011000000000000000000 5
1!
#295000
0!
#300000
b1100101 "
b101 +
b1110010001000100111101011001101101100000000 5
1!
#305000
0!
#310000
b0 "
b11 6
b0 +
b1110010001000100111101011001101101101100101 5
1!
#315000
0!
#320000
b1100100 "
b1 +
1!
#325000
0!
#330000
b100 6
b0 +
1!
