Encapsulation/utils.vh
`define min_payload_len                 16'd46
`define len_addr                        13'd6
`define len_len                         13'd2
`define len_crc                         13'd4
`define len_perm                        13'd7
`define len_max_payload                 50

crc32_comb.v
module crc32_comb
#(parameter crc_len =32, parameter crc =  32'h04C11DB7, parameter GMII = 1, parameter datalen = 8, parameter refin = 1, parameter refout = 1,parameter byte_len =64)
(
input updatecrc,                                                    
output reg [crc_len-1:0]result,
input clk,rst,                    
input  [datalen-1:0] data
);

reg [crc_len-1:0]   crc_poly        = crc;
reg [crc_len-1:0]   crc_acc         = {(crc_len){1'b1}};            //Initiate acc
reg [11:0]          byte_count =0;                                  //Keep track of bytes
reg [4:0]           bit_n = 0;                                      //Keep track of bites
reg [crc_len-1:0]   nresult  ;                                      //Final CRC Reminder
reg [datalen-1:0] data_buf;                                         //Databuffer stores reflected databyte
reg [crc_len-1:0] crc_acc_n;                                        //Crc Accumulator



generate if (GMII) begin
            always @(*) begin

                if(rst) begin
                    crc_acc     <= {(crc_len){1'b1}};
                    result      <=  0;
                    byte_count  <=  0;
                    crc_acc_n   <= {(crc_len){1'b1}};
                    nresult     <=  0;
                    data_buf    <=  0;
                    bit_n       <=  0;
                end

                else begin
                    result = nresult;
                end
            end

            always @(posedge clk) begin
                if (updatecrc) begin
                    data_buf = reflect_byte(data[datalen-1:0]);
                    crc_acc_n =  {data_buf,{(crc_len-datalen){1'b0}}}^ crc_acc_n;
                    
                    for (bit_n = 0; bit_n <datalen ; bit_n =bit_n +1 ) begin 
                        // Num of itteration = datalen -- For Single CRC Step
                        crc_acc_n = crc_bit_updt(crc_acc_n[crc_len-1:0],crc[crc_len-1:0],crc_acc_n[crc_len-1]);
                    end
                    bit_n       <=  0;
                    byte_count <= byte_count + 1; //  Keep track of bytes processed

                end
                    if(byte_count == byte_len-1) begin
                        nresult      =  ~reflectcrc(crc_acc_n[crc_len-1:0]);
                    end
            end
end endgenerate


function [crc_len-1:0]crc_bit_updt (input [crc_len-1:0]crc_acc, input [crc_len-1:0]crc, input bit);
//      Basic single CRC step
    begin
        if (bit) begin
            crc_bit_updt =   (crc_acc << 1);
            crc_bit_updt =   (crc_bit_updt ^ crc) ;
        end
        else begin
             crc_bit_updt = crc_acc << 1;
        end
    end
endfunction

function [datalen-1:0]reflect_byte (input [datalen-1:0]data);
//      Reflect 8 bits
reg [datalen-1:0]       temp;
reg [4:0]              bit_n;
    begin
       for (bit_n = 0; bit_n <datalen ; bit_n =bit_n +1 ) begin
            temp[bit_n] = data[datalen-1-bit_n];
       end
    reflect_byte = temp;
    end
endfunction

function [crc_len-1:0]reflectcrc (input [crc_len-1:0]crc_acc);
//      Reflect 32 bits
reg [crc_len-1:0]       temp;
reg [5:0]              bit_n;
    begin
       for (bit_n = 0; bit_n <crc_len ; bit_n =bit_n +1 ) begin
            temp[bit_n] = crc_acc[crc_len-1-bit_n];
       end
    reflectcrc = temp;
    end
endfunction

endmodule

Decapsulation/decapsulation.v
`include "utils.vh"

module ethernet_decapsulation 
#(
    parameter [47:0] destination_mac_addr  = 48'h023528fbdd66,
    parameter [47:0] source_mac_addr       = 48'h072227acdb65
)
(
    // Output Payload
    output  reg     ncrc_err,adr_err,len_err, buffer_full,
    output data_out_en,
    // Ethernet RX Transmission ports
    input wire [7:0]     gmii_data_in,
    input           gmii_dv,gmii_er,gmii_en,clk,rst
);

// Dump waveforms with makefile
`ifdef COCOTB_SIM
initial begin
    $dumpfile("sim.vcd");
    $dumpvars(0,ethernet_decapsulation);
end    
`endif

    //  Define Registers
    reg         [3:0]                   state_reg = 0;                               // FSM State register, keep track of frame section 
    reg         [8*10-1:0]              data_buf;                                    // Payload Buffer that holds data
    reg         [13:0]                  byte_count = 0;                              // Track bytes in each state
    wire        [31:0]                 crc_check     ;             // Initate CRC, update with every processed byte
    reg         [15:0]                 len_payload = 0;                              // Keep track of every Recived Payload Length
    
    wire                               cont_stages;
    reg         [8*`len_addr-1:0]                  source_addr;
    reg         [8*`len_addr-1:0]                  dest_addr;
    reg         [8*`len_len-1:0]                    data_len;                       
    reg         [8*`len_crc-1:0]                    data_crc;  
    reg         [7:0] gmii_buf;

    reg updatecrc_reg = 0;
    reg rst_crc_reg   = 1;

    
    //  Ethernet Frame Encapsulation Stages
    localparam  IDLE                = 4'd0,
                PERMABLE            = 4'd1,
                SDF                 = 4'd2,  
                LEN                 = 4'd3,
                PAYLOAD             = 4'd4,  
                FCS                 = 4'd5,
                EXT                 = 4'd6,
                Dest_MAC            = 4'd7,
                Source_Mac          = 4'd8,
                Err                 = 4'd9;

    localparam Permable_val = 8'b101010,                            
               Start_Del_val= 8'b101011;                                            // IEEE defined Permable and Delimeter bytes


    crc32_comb crc_mod(
        .clk(clk),.rst(rst_crc),
        .updatecrc(updatecrc),
        .data(gmii_data_in),
        .result(crc_check)
    );

    assign data_out_en = (state_reg == IDLE)? 1'b1:1'b0;
    // Bufferred Data should not be transmitted while still receiving
    assign cont_stages = (gmii_en && gmii_dv && !(gmii_er))? 1'b1:1'b0 ;

    assign updatecrc = updatecrc_reg;
    assign rst_crc   = rst_crc_reg;

    // Ethernet Frame Stages
    always @(posedge clk) begin
        if (!rst) begin
            if (gmii_en) begin
                    case (state_reg)
                        IDLE:       begin
                                        if (gmii_en && gmii_dv) begin
                                            state_reg   = PERMABLE;
                                            gmii_buf    = gmii_data_in;
                                            byte_count  = byte_count +1;
                                        end
                                        else if (gmii_er) begin
                                            state_reg =Err;
                                            byte_count  = 0;
                                        end
                                    end 
                        PERMABLE:   begin
                                        rst_crc_reg      = 1;
                                        updatecrc_reg    = 0;
                                        if(byte_count < `len_perm-1 ) begin
                                            byte_count  = byte_count +1;
                                        end 
                                        else begin
                                            state_reg = SDF;
                                            byte_count = 0;
                                        end
                                    end
                        SDF:        begin
                                        state_reg   = Dest_MAC;
                                        rst_crc_reg     = 0;
                                        updatecrc_reg   = 1;
                                    end
                        Dest_MAC:   begin
                                        dest_addr[(8*(`len_addr-byte_count)-1)-:8]         =    gmii_data_in ; 
                                        if (byte_count < `len_addr-1) begin
                                            byte_count = byte_count + 1;
                                        end 
                                        else begin
                                            byte_count= 0;
                                            state_reg = Source_Mac;
                                        end
                                    end
                        Source_Mac: begin
                                        source_addr[(8*(`len_addr-byte_count)-1)-:8]       =    gmii_data_in ;
                                        if (byte_count < `len_addr-1) begin
                                            byte_count = byte_count + 1;
                                        end 
                                        else begin
                                            byte_count= 0;
                                            state_reg = LEN;
                                        end  
                                    end
                        LEN:        begin
                                        len_payload[(8*(`len_len-byte_count)-1)-:8]       =    gmii_data_in ;
                                        if (byte_count < `len_len-1) begin
                                            byte_count = byte_count + 1;
                                        end 
                                        else begin
                                            byte_count= 0;
                                            state_reg = PAYLOAD;
                                        end  
                                    end
                        PAYLOAD:    begin
                                        if (byte_count < len_payload-1) begin
                                            byte_count = byte_count + 1;
                                            state_reg = PAYLOAD;
                                        end 
                                        else begin
                                            byte_count= 0;
                                            if (len_payload <= `min_payload_len) begin
                                                state_reg = EXT;
                                                updatecrc_reg   = 1;
                                            end else begin
                                                updatecrc_reg   = 0;
                                                state_reg = FCS;
                                            end
                                        end  
                                    end

                        EXT:        begin
                                        if (byte_count < `min_payload_len-len_payload-1) begin
                                            byte_count = byte_count + 1;
                                        end 
                                        else begin
                                            state_reg = FCS;
                                            byte_count = 0;
                                            updatecrc_reg   = 0;
                                        end
                                    end

                        FCS:        begin
                                        data_crc[(8*(`len_crc-byte_count)-1)-:8]       =    gmii_data_in ;
                                        if (byte_count < `len_crc-1) begin
                                            byte_count = byte_count + 1;
                                        end 
                                        else begin
                                            if (data_crc == crc_check) begin
                                                ncrc_err     = 1;
                                            end else
                                                ncrc_err     = 0;
                                            byte_count= 0;
                                            state_reg = IDLE;
                                        end 
                                    end
                        Err:        begin
                            
                                    end

                        default: state_reg = IDLE;
                    endcase
            end
        end 
    end


    //  Global Synchronous Reset
    always @(posedge clk ) begin
        if (rst) begin
            len_payload                     = 0;
            state_reg                       =IDLE;
            data_buf                        = 0;
            source_addr                     = 0;
            dest_addr                       = 0;
            data_len                        = 0;
            source_addr                     = 0;
            data_len                        = 0;
            data_crc                        = 0;
        end
    end

endmodule

Decapsulation/sim.vcd
$date
	Wed Apr  5 12:57:19 2023
$end
$version
	Icarus Verilog
$end
$timescale
	1ps
$end
$scope module ethernet_decapsulation $end
$var wire 1 ! clk $end
$var wire 8 " gmii_data_in [7:0] $end
$var wire 1 # gmii_dv $end
$var wire 1 $ gmii_en $end
$var wire 1 % gmii_er $end
$var wire 1 & rst $end
$var wire 1 ' rst_crc $end
$var wire 1 ( updatecrc $end
$var wire 1 ) data_out_en $end
$var wire 32 * crc_check [31:0] $end
$var wire 1 + cont_stages $end
$var reg 1 , adr_err $end
$var reg 1 - buffer_full $end
$var reg 14 . byte_count [13:0] $end
$var reg 80 / data_buf [79:0] $end
$var reg 32 0 data_crc [31:0] $end
$var reg 16 1 data_len [15:0] $end
$var reg 48 2 dest_addr [47:0] $end
$var reg 8 3 gmii_buf [7:0] $end
$var reg 1 4 len_err $end
$var reg 16 5 len_payload [15:0] $end
$var reg 1 6 ncrc_err $end
$var reg 1 7 rst_crc_reg $end
$var reg 48 8 source_addr [47:0] $end
$var reg 4 9 state_reg [3:0] $end
$var reg 1 : updatecrc_reg $end
$scope module crc_mod $end
$var wire 1 ! clk $end
$var wire 8 ; data [7:0] $end
$var wire 1 ' rst $end
$var wire 1 ( updatecrc $end
$var reg 5 < bit_n [4:0] $end
$var reg 12 = byte_count [11:0] $end
$var reg 32 > crc_acc [31:0] $end
$var reg 32 ? crc_acc_n [31:0] $end
$var reg 32 @ crc_poly [31:0] $end
$var reg 8 A data_buf [7:0] $end
$var reg 32 B nresult [31:0] $end
$var reg 32 C result [31:0] $end
$scope function crc_bit_updt $end
$var reg 1 D bit $end
$var reg 32 E crc [31:0] $end
$var reg 32 F crc_acc [31:0] $end
$upscope $end
$scope function reflect_byte $end
$var reg 5 G bit_n [4:0] $end
$var reg 8 H data [7:0] $end
$var reg 8 I temp [7:0] $end
$upscope $end
$scope function reflectcrc $end
$var reg 6 J bit_n [5:0] $end
$var reg 32 K crc_acc [31:0] $end
$var reg 32 L temp [31:0] $end
$upscope $end
$scope begin genblk1 $end
$upscope $end
$upscope $end
$upscope $end
$enddefinitions $end
#0
$dumpvars
bx L
bx K
bx J
bx I
bx H
bx G
bx F
bx E
xD
b0 C
b0 B
b0 A
b100110000010001110110110111 @
b11111111111111111111111111111111 ?
b11111111111111111111111111111111 >
b0 =
b0 <
bz ;
0:
b0 9
bx 8
17
x6
b0 5
x4
bx 3
bx 2
bx 1
bx 0
bx /
b0 .
x-
x,
x+
b0 *
1)
0(
1'
z&
z%
z$
z#
bz "
z!
$end
#1
1!
#5001
0!
#10001
b0 0
b0 1
b0 2
b0 8
b0 /
1!
1&
#15001
0!
#20001
1!
#22001
0&
#25001
0!
#30001
1!
#35001
0!
#40001
1!
#45001
0!
#50001
1!
#55001
0!
#60001
1!
#65001
0!
#70001
1!
#75001
0!
#80001
1!
#85001
0!
#87001
0+
0$
#90001
1!
#95001
0!
#100001
1!
#105001
0!
#110001
1+
b101010 "
b101010 ;
0%
1#
1$
1!
#115001
0!
#120001
0)
b1 .
b101010 3
b1 9
1!
#125001
0!
#130001
b10 .
1!
#135001
0!
#140001
b11 .
1!
#145001
0!
#150001
b100 .
1!
#155001
0!
#160001
b101 .
1!
#165001
0!
#170001
b110 .
1!
#175001
0!
#180001
b101011 "
b101011 ;
b0 .
b10 9
1!
#185001
0!
#190001
b10 "
b10 ;
1(
1:
0'
07
b111 9
1!
#195001
0!
#200001
b110101 "
b110101 ;
b1 =
b0 <
b10111111001001111110100100111010 F
b100110000010001110110110111 E
1D
b1111010100011101100111111000011 ?
b1000000 A
b1000000 I
b1000 G
b10 H
b1 .
b100000000000000000000000000000000000000000 2
1!
#205001
0!
#210001
b101000 "
b101000 ;
b10 =
b10 .
b100011010100000000000000000000000000000000 2
1D
b0 <
b11000000100010011110110001110110 F
b10000101110100101100010101011011 ?
b10101100 A
b10101100 I
b1000 G
b110101 H
1!
#215001
0!
#220001
b11111011 "
b11111011 ;
b11 =
1D
b0 <
b11111011111011000011000001001111 F
b11110011000110010111110100101001 ?
b10100 A
b10100 I
b1000 G
b101000 H
b11 .
b100011010100101000000000000000000000000000 2
1!
#225001
0!
#230001
b11011101 "
b11011101 ;
b100 =
b100 .
b100011010100101000111110110000000000000000 2
b0 <
b1011010001010010000001001000010 F
0D
b10110100010100100000010010000100 ?
b11011111 A
b11011111 I
b1000 G
b11111011 H
1!
#235001
0!
#240001
b1100110 "
b1100110 ;
b101 =
1D
b0 <
b10110111010001010001001000000101 F
b1101010010010110011100110111101 ?
b10111011 A
b10111011 I
b1000 G
b11011101 H
b101 .
b100011010100101000111110111101110100000000 2
1!
#245001
0!
#250001
b111 "
b111 ;
b110 =
b1000 9
b0 .
b100011010100101000111110111101110101100110 2
b0 <
b111111000110101001001100110010 F
0D
b1111110001101010010011001100100 ?
b1100110 A
b1100110 I
b1000 G
b1100110 H
1!
#255001
0!
#260001
b100010 "
b100010 ;
b111 =
b0 <
b10110010110101111111111001010 F
0D
b101100101101011111111110010100 ?
b11100000 A
b11100000 I
b1000 G
b111 H
b1 .
b1110000000000000000000000000000000000000000 8
1!
#265001
0!
#270001
b100111 "
b100111 ;
b1000 =
b10 .
b1110010001000000000000000000000000000000000 8
1D
b0 <
b10011101110010011101000101001100 F
b111111010100101011111100101111 ?
b1000100 A
b1000100 I
b1000 G
b100010 H
1!
#275001
0!
#280001
b10101100 "
b10101100 ;
b1001 =
0D
b0 <
b110100001101111101011111000100 F
b1101000011011111010111110001000 ?
b11100100 A
b11100100 I
b1000 G
b100111 H
b11 .
b1110010001000100111000000000000000000000000 8
1!
#285001
0!
#290001
b11011011 "
b11011011 ;
b1010 =
b100 .
b1110010001000100111101011000000000000000000 8
0D
b0 <
b10011011110101101001011101010 F
b100110111101011010010111010100 ?
b110101 A
b110101 I
b1000 G
b10101100 H
1!
#295001
0!
#300001
b1100101 "
b1100101 ;
b1011 =
b0 <
b100110111010000101011111101101 F
0D
b1001101110100001010111111011010 ?
b11011011 A
b11011011 I
b1000 G
b11011011 H
b101 .
b1110010001000100111101011001101101100000000 8
1!
#305001
0!
#310001
b0 "
b0 ;
b1100 =
b11 9
b0 .
b1110010001000100111101011001101101101100101 8
b0 <
b11111001001101001101110001100 F
0D
b111110010011010011011100011000 ?
b10100110 A
b10100110 I
b1000 G
b1100101 H
1!
#315001
0!
#320001
b110010 "
b110010 ;
b1101 =
0D
b0 <
b10100101100010111101010110011010 ?
b1010010110001011110101011001101 F
b0 A
b0 I
b1000 G
b0 H
b1 .
1!
#325001
0!
#330001
b10000 "
b10000 ;
b1110 =
b100 9
b0 .
b110010 5
b0 <
b110110010110101010011000111011 F
0D
b1101100101101010100110001110110 ?
b1001100 A
b1001100 I
b1000 G
b110010 H
1!
#335001
0!
#340001
b110 "
b110 ;
b1111 =
1D
b0 <
b10000111000101100110110111111110 F
b1010111011011100011001001011 ?
b1000 A
b1000 I
b1000 G
b10000 H
b1 .
1!
#345001
0!
#350001
b111 "
b111 ;
b10000 =
b10 .
b0 <
b10110101000101000010001101111011 F
1D
b1101110111010010101101101000001 ?
b1100000 A
b1100000 I
b1000 G
b110 H
1!
#355001
0!
#360001
b1110 "
b1110 ;
b10001 =
0D
b0 <
b1011110011011001000000011110010 F
b10111100110110010000000111100100 ?
b11100000 A
b11100000 I
b1000 G
b111 H
b11 .
1!
#365001
0!
#370001
b10000 "
b10000 ;
b10010 =
b100 .
b0 <
b11011010101000110111100100100101 F
1D
b10110001100001111110111111111101 ?
b1110000 A
b1110000 I
b1000 G
b1110 H
1!
#375001
0!
#380001
b10011 =
1D
b0 <
b10001110011011001100111011100011 F
b11000000110001000000001110001 ?
b1000 A
b1000 I
b1000 G
b10000 H
b101 .
1!
#385001
0!
#390001
b11 "
b11 ;
b10100 =
b110 .
b0 <
b101010010010001101010100111000 F
0D
b1010100100100011010101001110000 ?
b1000 G
1!
#395001
0!
#400001
b10000 "
b10000 ;
b10101 =
b0 <
b1010011110110011001111010100001 F
0D
b10100111101100110011110101000010 ?
b11000000 A
b11000000 I
b1000 G
b11 H
b111 .
1!
#405001
0!
#410001
b1100 "
b1100 ;
b10110 =
b1000 .
b0 <
b10111111010011100101101000000010 F
1D
b1111010010111011010100110110011 ?
b1000 A
b1000 I
b1000 G
b10000 H
1!
#415001
0!
#420001
b1000 "
b1000 ;
b10111 =
b0 <
b10100001001100100000010000001011 F
1D
b1000110101001010001010110100001 ?
b110000 A
b110000 I
b1000 G
b1100 H
b1001 .
1!
#425001
0!
#430001
b1001 "
b1001 ;
b11000 =
b1010 .
b0 <
b11100001111000101010110100000001 F
1D
b11000111000001000100011110110101 ?
b10000 A
b10000 I
b1000 G
b1000 H
1!
#435001
0!
#440001
b1011 "
b1011 ;
b11001 =
b0 <
b110001010010111010011100000001 F
0D
b1100010100101110100111000000010 ?
b10010000 A
b10010000 I
b1000 G
b1001 H
b1011 .
1!
#445001
0!
#450001
b101 "
b101 ;
b11010 =
b1100 .
b0 <
b10001111110010101101000001000 F
0D
b100011111100101011010000010000 ?
b11010000 A
b11010000 I
b1000 G
b1011 H
1!
#455001
0!
#460001
b1011 "
b1011 ;
b11011 =
b0 <
b11001001000111010110010111000000 F
1D
b10010110111110111101011000110111 ?
b10100000 A
b10100000 I
b1000 G
b101 H
b1101 .
1!
#465001
0!
#470001
b1001 "
b1001 ;
b11100 =
b1110 .
b0 <
b11101000100010111000101110111001 F
1D
b11010101110101100000101011000101 ?
b11010000 A
b11010000 I
b1000 G
b1011 H
1!
#475001
0!
#480001
b1100 "
b1100 ;
b11101 =
b0 <
b1111010101001001110111100001110 F
0D
b11110101010010011101111000011100 ?
b10010000 A
b10010000 I
b1000 G
b1001 H
b1111 .
1!
#485001
0!
#490001
b1111 "
b1111 ;
b11110 =
b10000 .
b0 <
b1110010001111001111111001 F
0D
b11100100011110011111110010 ?
b110000 A
b110000 I
b1000 G
b1100 H
1!
#495001
0!
#500001
b11111 =
b0 <
b1010100011100001010011101000 F
0D
b10101000111000010100111010000 ?
b11110000 A
b11110000 I
b1000 G
b1111 H
b10001 .
1!
#505001
0!
#510001
b1011 "
b1011 ;
b100000 =
b10010 .
b0 <
b1100111001000101100111010001001 F
0D
b11001110010001011001110100010010 ?
b1000 G
1!
#515001
0!
#520001
b1110 "
b1110 ;
b100001 =
0D
b0 <
b11010100000010011010010111101 F
b110101000000100110100101111010 ?
b11010000 A
b11010000 I
b1000 G
b1011 H
b10011 .
1!
#525001
0!
#530001
b110 "
b110 ;
b100010 =
b10100 .
0D
b0 <
b10000100101010011000010001110 F
b100001001010100110000100011100 ?
b1110000 A
b1110000 I
b1000 G
b1110 H
1!
#535001
0!
#540001
b1 "
b1 ;
b100011 =
0D
b0 <
b1101000100110011100011100000 F
b11010001001100111000111000000 ?
b1100000 A
b1100000 I
b1000 G
b110 H
b10101 .
1!
#545001
0!
#550001
b1111 "
b1111 ;
b100100 =
b10110 .
b0 <
b10110011100110001011010100100 F
0D
b101100111001100010110101001000 ?
b10000000 A
b10000000 I
b1000 G
b1 H
1!
#555001
0!
#560001
b1011 "
b1011 ;
b100101 =
b0 <
b11100011001111011100001010011101 F
1D
b11000010101110101001100010001101 ?
b11110000 A
b11110000 I
b1000 G
b1111 H
b10111 .
1!
#565001
0!
#570001
b1110 "
b1110 ;
b100110 =
b11000 .
b0 <
b1111111100001011011011010001111 F
0D
b11111111000010110110110100011110 ?
b11010000 A
b11010000 I
b1000 G
b1011 H
1!
#575001
0!
#580001
b111 "
b111 ;
b100111 =
b0 <
b10101111011101111010111101110010 F
1D
b1011010001011100100001101010011 ?
b1110000 A
b1110000 I
b1000 G
b1110 H
b11001 .
1!
#585001
0!
#590001
b101 "
b101 ;
b101000 =
b11010 .
0D
b0 <
b1011110011110111000010001010100 F
b10111100111101110000100010101000 ?
b11100000 A
b11100000 I
b1000 G
b111 H
1!
#595001
0!
#600001
b1010 "
b1010 ;
b101001 =
0D
b0 <
b1000111000010101111010000001010 F
b10001110000101011110100000010100 ?
b10100000 A
b10100000 I
b1000 G
b101 H
b11011 .
1!
#605001
0!
#610001
b111 "
b111 ;
b101010 =
b11100 .
b0 <
b10011110000111100111000100101010 F
1D
b111000111111011111111111100011 ?
b1010000 A
b1010000 I
b1000 G
b1010 H
1!
#615001
0!
#620001
b100 "
b100 ;
b101011 =
1D
b0 <
b11100111010101101010110001110011 F
b11001010011011000100010101010001 ?
b11100000 A
b11100000 I
b1000 G
b111 H
b11101 .
1!
#625001
0!
#630001
b1110 "
b1110 ;
b101100 =
b11110 .
1D
b0 <
b11000001010100111101111000001100 F
b10000110011001101010000110101111 ?
b100000 A
b100000 I
b1000 G
b100 H
1!
#635001
0!
#640001
b100 "
b100 ;
b101101 =
1D
b0 <
b11111000101011110000000100000110 F
b11110101100111110001111110111011 ?
b1110000 A
b1110000 I
b1000 G
b1110 H
b11111 .
1!
#645001
0!
#650001
b1001 "
b1001 ;
b101110 =
b100000 .
0D
b0 <
b1001100101000001100110111000001 F
b10011001010000011001101110000010 ?
b100000 A
b100000 I
b1000 G
b100 H
1!
#655001
0!
#660001
b100 "
b100 ;
b101111 =
1D
b0 <
b10110011110010011011011111011100 F
b1100011010100100111001000001111 ?
b10010000 A
b10010000 I
b1000 G
b1001 H
b100001 .
1!
#665001
0!
#670001
b1101 "
b1101 ;
b110000 =
b100010 .
b0 <
b110101110110111010110011010111 F
0D
b1101011101101110101100110101110 ?
b100000 A
b100000 I
b1000 G
b100 H
1!
#675001
0!
#680001
b101 "
b101 ;
b110001 =
b0 <
b1000110110001001001011101000100 F
0D
b10001101100010010010111010001000 ?
b10110000 A
b10110000 I
b1000 G
b1101 H
b100011 .
1!
#685001
0!
#690001
b1000 "
b1000 ;
b110010 =
b100100 .
1D
b0 <
b10010010000000001101001011000010 F
b100000110000001011100000110011 ?
b10100000 A
b10100000 I
b1000 G
b101 H
1!
#695001
0!
#700001
b100 "
b100 ;
b110011 =
b0 <
b1010010001010010111101001000 F
0D
b10100100010100101111010010000 ?
b10000 A
b10000 I
b1000 G
b1000 H
b100101 .
1!
#705001
0!
#710001
b10 "
b10 ;
b110100 =
b100110 .
0D
b0 <
b100110101101000100010110100110 F
b1001101011010001000101101001100 ?
b100000 A
b100000 I
b1000 G
b100 H
1!
#715001
0!
#720001
b11 "
b11 ;
b110101 =
1D
b0 <
b10101110110000111110101110110010 F
b1011001010001101100101011010011 ?
b1000000 A
b1000000 I
b1000 G
b10 H
b100111 .
1!
#725001
0!
#730001
b1110 "
b1110 ;
b110110 =
b101000 .
1D
b0 <
b10100010111011111000001010010011 F
b1000001000111100001100010010001 ?
b11000000 A
b11000000 I
b1000 G
b11 H
1!
#735001
0!
#740001
b10000 "
b10000 ;
b110111 =
b0 <
b11100101000101010111111001001000 F
1D
b11001110111010111110000100100111 ?
b1110000 A
b1110000 I
b1000 G
b1110 H
b101001 .
1!
#745001
0!
#750001
b1110 "
b1110 ;
b111000 =
b101010 .
1D
b0 <
b11010100000101100111001111001110 F
b10101100111011011111101000101011 ?
b1000 A
b1000 I
b1000 G
b10000 H
1!
#755001
0!
#760001
b100 "
b100 ;
b111001 =
1D
b0 <
b11100110110101100111001100011101 F
b11001001011011011111101110001101 ?
b1110000 A
b1110000 I
b1000 G
b1110 H
b101011 .
1!
#765001
0!
#770001
b1101 "
b1101 ;
b111010 =
b101100 .
0D
b0 <
b1000101010011011010110110111011 F
b10001010100110110101101101110110 ?
b100000 A
b100000 I
b1000 G
b100 H
1!
#775001
0!
#780001
b1000 "
b1000 ;
b111011 =
0D
b0 <
b110000011100011110011010100011 F
b1100000111000111100110101000110 ?
b10110000 A
b10110000 I
b1000 G
b1101 H
b101101 .
1!
#785001
0!
#790001
b100 "
b100 ;
b111100 =
b101110 .
1D
b0 <
b10000011110111000010001100101000 F
b11011110010101101111100111 ?
b10000 A
b10000 I
b1000 G
b1000 H
1!
#795001
0!
#800001
b10000 "
b10000 ;
b111101 =
b0 <
b11110100011111010011010101000111 F
1D
b11101100001110110111011100111001 ?
b100000 A
b100000 I
b1000 G
b100 H
b101111 .
1!
#805001
0!
#810001
b1011 "
b1011 ;
b111110 =
b110000 .
1D
b0 <
b11110100100011011011101000001001 F
b11101101110110100110100110100101 ?
b1000 A
b1000 I
b1000 G
b10000 H
1!
#815001
0!
#820001
b101 "
b101 ;
b111111 =
b0 <
b10011101101010111010100111111010 F
1D
b111111100101100100111001000011 ?
b11010000 A
b11010000 I
b1000 G
b1011 H
b110001 .
1!
#825001
0!
#830001
b111011 "
b111011 ;
b1000000 =
b111011010111001100011100101110 *
b111011010111001100011100101110 C
b101 9
0(
0:
b0 .
b111011010111001100011100101110 B
b11000100101000110011100011010001 L
b100000 J
b10001011000111001100010100100011 K
1D
b0 <
b11000111111011101110110001001010 F
b10001011000111001100010100100011 ?
b10100000 A
b10100000 I
b1000 G
b101 H
1!
#835001
0!
#840001
b1011100 "
b1011100 ;
b1 .
b111011000000000000000000000000 0
1!
#845001
0!
#850001
b11000111 "
b11000111 ;
b10 .
b111011010111000000000000000000 0
1!
#855001
0!
#860001
b101110 "
b101110 ;
b11 .
b111011010111001100011100000000 0
1!
#865001
0!
#870001
1)
b0 9
b0 .
16
b111011010111001100011100101110 0
1!
#875001
0!
#880001
0)
b1 .
b101110 3
b1 9
1!
#885001
0!
#890001
b0 A
b0 B
b11111111111111111111111111111111 ?
b0 =
b0 *
b0 C
b10 .
1'
17
1!
#895001
0!
#900001
b11 .
1!
#905001
0!
#910001
b100 .
1!
#915001
0!
#920001
b101 .
1!
#925001
0!
#930001
b110 .
1!
#935001
0!
#940001
b0 .
b10 9
1!
#945001
0!
#950001
1(
1:
0'
07
b111 9
1!
#955001
0!
#960001
b1 =
1D
b0 <
b11011100101111001110010010011100 F
b10111101101110001101010010001111 ?
b1110100 A
b1110100 I
b1000 G
b101110 H
b1 .
b1011100011010100101000111110111101110101100110 2
1!
#965001
0!
#970001
b10 =
b10 .
b1011100010111000101000111110111101110101100110 2
0D
b0 <
b1100011110010111111011111001011 F
b11000111100101111110111110010110 ?
b1000 G
1!
#975001
0!
#980001
b11 =
b0 <
b10010001101010011001000000001000 F
1D
b100111100100100011110110100111 ?
b1000 G
b11 .
b1011100010111000101110111110111101110101100110 2
1!
#985001
0!
#990001
b100 =
b100 .
b1011100010111000101110001011101101110101100110 2
b0 <
b1110011111101001001010101101111 F
0D
b11100111111010010010101011011110 ?
b1000 G
1!
#995001
0!
#1000001
b101 =
b0 <
b11100010110110101110111101111000 F
1D
b11000001011101001100001101000111 ?
b1000 G
b101 .
b1011100010111000101110001011100010111001100110 2
1!
#1005001
0!
#1010001
b110 =
b1000 9
b0 .
b1011100010111000101110001011100010111000101110 2
1D
b0 <
b11101101011111001101111001010001 F
b11011110001110001010000100010101 ?
b1000 G
1!
#1015001
0!
#1020001
b111 =
0D
b0 <
b1110011000000100100101011101100 F
b11100110000001001001010111011000 ?
b1000 G
b1 .
b1011100010001000100111101011001101101101100101 8
1!
#1025001
0!
#1030001
b1000 =
b10 .
b1011100010111000100111101011001101101101100101 8
b0 <
b10100000001010110110001111000 F
0D
b101000000010101101100011110000 ?
b1000 G
1!
#1035001
0!
#1040001
b1001 =
1D
b0 <
b10100001110000010110111011101010 F
b1000111010000111100000001100011 ?
b1000 G
b11 .
b1011100010111000101110101011001101101101100101 8
1!
#1045001
0!
#1050001
b1010 =
b100 .
b1011100010111000101110001011101101101101100101 8
b0 <
b11001111001110000001101011111111 F
1D
b10011010101100010010100001001001 ?
b1000 G
1!
#1055001
0!
#1060001
b1011 =
1D
b0 <
b10100110011001110110100101100010 F
b1001000000011111100111101110011 ?
b1000 G
b101 .
b1011100010111000101110001011100010111001100101 8
1!
#1065001
0!
#1070001
b1100 =
b11 9
b0 .
b1011100010111000101110001011100010111000101110 8
b0 <
b1110111011110001100001011111010 F
0D
b11101110111100011000010111110100 ?
b1000 G
1!
#1075001
0!
#1080001
b1101 =
b0 <
b1111101100010010000110010100100 F
0D
b11111011000100100001100101001000 ?
b1000 G
b1 .
b10111000110010 5
1!
#1085001
0!
#1090001
b1110 =
b100 9
b0 .
b10111000101110 5
b0 <
b10100011110011011000010001110010 F
1D
b1000011010110100001010101010011 ?
b1000 G
1!
#1095001
0!
#1100001
b1111 =
b0 <
b11001010010100001011100110010001 F
1D
b10010000011000000110111010010101 ?
b1000 G
b1 .
1!
#1105001
0!
#1110001
b10000 =
b10 .
1D
b0 <
b11011001000000010110110000001001 F
b10110110110000111100010110100101 ?
b1000 G
1!
#1115001
0!
#1120001
b10001 =
1D
b0 <
b11001001100001100000100110100000 F
b10010111110011010000111011110111 ?
b1000 G
b11 .
1!
#1125001
0!
#1130001
b10010 =
b100 .
0D
b0 <
b10111100100111101111010000 F
b101111001001111011110100000 ?
b1000 G
1!
#1135001
0!
#1140001
b10011 =
0D
b0 <
b10000010101000000101000 F
b100000101010000001010000 ?
b1000 G
b101 .
1!
#1145001
0!
#1150001
b10100 =
b110 .
1D
b0 <
b10111010111010001001001101000110 F
b1110001000100000011101100111011 ?
b1000 G
1!
#1155001
0!
#1160001
b10101 =
b0 <
b10000001100111111010011011101110 F
1D
b111111111100101000001101011 ?
b1000 G
b111 .
1!
#1165001
0!
#1170001
b10110 =
b1000 .
b0 <
b1001110100111010100000011111 F
0D
b10011101001110101000000111110 ?
b1000 G
1!
#1175001
0!
#1180001
b10111 =
0D
b0 <
b1010110110010101010001001001 F
b10101101100101010100010010010 ?
b1000 G
b1001 .
1!
#1185001
0!
