Encapsulation/utils.vh
`define min_payload_len                 16'd46
`define len_addr                        13'd6
`define len_len                         13'd2
`define len_crc                         13'd4
`define len_perm                        13'd7
`define len_max_payload                 50

crc32_comb.v
module crc32_comb
#(parameter crc_len =32, parameter crc =  32'h04C11DB7, parameter GMII = 1, parameter datalen = 8, parameter refin = 1, parameter refout = 1,parameter byte_len =64)
(
input updatecrc,                                                    
output reg [crc_len-1:0]result,
input clk,rst,                    
input  [datalen-1:0] data
);

reg [crc_len-1:0]   crc_poly        = crc;
reg [crc_len-1:0]   crc_acc         = {(crc_len){1'b1}};            //Initiate acc
reg [11:0]          byte_count =0;                                  //Keep track of bytes
reg [4:0]           bit_n = 0;                                      //Keep track of bites
reg [crc_len-1:0]   nresult  ;                                      //Final CRC Reminder
reg [datalen-1:0] data_buf;                                         //Databuffer stores reflected databyte
reg [crc_len-1:0] crc_acc_n;                                        //Crc Accumulator



generate if (GMII) begin
            always @(*) begin

                if(rst) begin
                    crc_acc     <= {(crc_len){1'b1}};
                    result      <=  0;
                    byte_count  <=  0;
                    crc_acc_n   <= {(crc_len){1'b1}};
                    nresult     <=  0;
                    data_buf    <=  0;
                    bit_n       <=  0;
                end

                else begin
                    result = nresult;
                end
            end

            always @(posedge clk) begin
                if (updatecrc) begin
                    data_buf = reflect_byte(data[datalen-1:0]);
                    crc_acc_n =  {data_buf,{(crc_len-datalen){1'b0}}}^ crc_acc_n;
                    
                    for (bit_n = 0; bit_n <datalen ; bit_n =bit_n +1 ) begin 
                        // Num of itteration = datalen -- For Single CRC Step
                        crc_acc_n = crc_bit_updt(crc_acc_n[crc_len-1:0],crc[crc_len-1:0],crc_acc_n[crc_len-1]);
                    end
                    bit_n       <=  0;
                    byte_count <= byte_count + 1; //  Keep track of bytes processed

                end
                    if(byte_count == byte_len-1) begin
                        nresult      =  ~reflectcrc(crc_acc_n[crc_len-1:0]);
                    end
            end
end endgenerate


function [crc_len-1:0]crc_bit_updt (input [crc_len-1:0]crc_acc, input [crc_len-1:0]crc, input bit);
//      Basic single CRC step
    begin
        if (bit) begin
            crc_bit_updt =   (crc_acc << 1);
            crc_bit_updt =   (crc_bit_updt ^ crc) ;
        end
        else begin
             crc_bit_updt = crc_acc << 1;
        end
    end
endfunction

function [datalen-1:0]reflect_byte (input [datalen-1:0]data);
//      Reflect 8 bits
reg [datalen-1:0]       temp;
reg [4:0]              bit_n;
    begin
       for (bit_n = 0; bit_n <datalen ; bit_n =bit_n +1 ) begin
            temp[bit_n] = data[datalen-1-bit_n];
       end
    reflect_byte = temp;
    end
endfunction

function [crc_len-1:0]reflectcrc (input [crc_len-1:0]crc_acc);
//      Reflect 32 bits
reg [crc_len-1:0]       temp;
reg [5:0]              bit_n;
    begin
       for (bit_n = 0; bit_n <crc_len ; bit_n =bit_n +1 ) begin
            temp[bit_n] = crc_acc[crc_len-1-bit_n];
       end
    reflectcrc = temp;
    end
endfunction

endmodule

Decapsulation/decapsulation.v
`include "utils.vh"

module ethernet_decapsulation 
#(
    parameter [47:0] destination_mac_addr  = 48'h023528fbdd66,
    parameter [47:0] source_mac_addr       = 48'h072227acdb65
)
(
    // Output Payload
    output  reg     ncrc_err,adr_err,len_err, buffer_full,
    output data_out_en,
    // Ethernet RX Transmission ports
    input wire [7:0]     gmii_data_in,
    input           gmii_dv,gmii_er,gmii_en,clk,rst
);

// Dump waveforms with makefile
`ifdef COCOTB_SIM
initial begin
    $dumpfile("sim.vcd");
    $dumpvars(0,ethernet_decapsulation);
end    
`endif

    //  Define Registers
    reg         [3:0]                   state_reg = 0;                               // FSM State register, keep track of frame section 
    reg         [8*10-1:0]              data_buf;                                    // Payload Buffer that holds data
    reg         [13:0]                  byte_count = 0;                              // Track bytes in each state
    wire        [31:0]                 crc_check     ;             // Initate CRC, update with every processed byte
    reg         [15:0]                 len_payload = 0;                              // Keep track of every Recived Payload Length
    
    wire                               cont_stages;
    reg         [8*`len_addr-1:0]                  source_addr;
    reg         [8*`len_addr-1:0]                  dest_addr;
    reg         [8*`len_len-1:0]                    data_len;                       
    reg         [8*`len_crc-1:0]                    data_crc;  
    reg         [7:0] gmii_buf;

    reg updatecrc_reg = 0;
    reg rst_crc_reg   = 1;

    
    //  Ethernet Frame Encapsulation Stages
    localparam  IDLE                = 4'd0,
                PERMABLE            = 4'd1,
                SDF                 = 4'd2,  
                LEN                 = 4'd3,
                PAYLOAD             = 4'd4,  
                FCS                 = 4'd5,
                EXT                 = 4'd6,
                Dest_MAC            = 4'd7,
                Source_Mac          = 4'd8,
                Err                 = 4'd9;

    localparam Permable_val = 8'b101010,                            
               Start_Del_val= 8'b101011;                                            // IEEE defined Permable and Delimeter bytes


    crc32_comb crc_mod(
        .clk(clk),.rst(rst_crc),
        .updatecrc(updatecrc),
        .data(gmii_data_in),
        .result(crc_check)
    );

    assign data_out_en = (state_reg == IDLE)? 1'b1:1'b0;
    // Bufferred Data should not be transmitted while still receiving
    assign cont_stages = (gmii_en && gmii_dv && !(gmii_er))? 1'b1:1'b0 ;

    assign updatecrc = updatecrc_reg;
    assign rst_crc   = rst_crc_reg;

    // Ethernet Frame Stages
    always @(posedge clk) begin
        if (!rst) begin
            if (gmii_en) begin
                    case (state_reg)
                        IDLE:       begin
                                        if (gmii_en && gmii_dv) begin
                                            state_reg   = PERMABLE;
                                            gmii_buf    = gmii_data_in;
                                            byte_count  = byte_count +1;
                                        end
                                        else if (gmii_er) begin
                                            state_reg =Err;
                                            byte_count  = 0;
                                        end
                                    end 
                        PERMABLE:   begin
                                        rst_crc_reg      = 1;
                                        updatecrc_reg    = 0;
                                        if(byte_count < `len_perm-1 ) begin
                                            byte_count  = byte_count +1;
                                        end 
                                        else begin
                                            state_reg = SDF;
                                            byte_count = 0;
                                        end
                                    end
                        SDF:        begin
                                        state_reg   = Dest_MAC;
                                        rst_crc_reg     = 0;
                                        updatecrc_reg   = 1;
                                    end
                        Dest_MAC:   begin
                                        dest_addr[(8*(`len_addr-byte_count)-1)-:8]         =    gmii_data_in ; 
                                        if (byte_count < `len_addr-1) begin
                                            byte_count = byte_count + 1;
                                        end 
                                        else begin
                                            byte_count= 0;
                                            state_reg = Source_Mac;
                                        end
                                    end
                        Source_Mac: begin
                                        source_addr[(8*(`len_addr-byte_count)-1)-:8]       =    gmii_data_in ;
                                        if (byte_count < `len_addr-1) begin
                                            byte_count = byte_count + 1;
                                        end 
                                        else begin
                                            byte_count= 0;
                                            state_reg = LEN;
                                        end  
                                    end
                        LEN:        begin
                                        len_payload[(8*(`len_len-byte_count)-1)-:8]       =    gmii_data_in ;
                                        if (byte_count < `len_len-1) begin
                                            byte_count = byte_count + 1;
                                        end 
                                        else begin
                                            byte_count= 0;
                                            state_reg = PAYLOAD;
                                        end  
                                    end
                        PAYLOAD:    begin
                                        if (byte_count < len_payload-1) begin
                                            byte_count = byte_count + 1;
                                            state_reg = PAYLOAD;
                                        end 
                                        else begin
                                            byte_count= 0;
                                            if (len_payload <= `min_payload_len) begin
                                                state_reg = EXT;
                                                updatecrc_reg   = 1;
                                            end else begin
                                                updatecrc_reg   = 0;
                                                state_reg = FCS;
                                            end
                                        end  
                                    end

                        EXT:        begin
                                        if (byte_count < `min_payload_len-len_payload-1) begin
                                            byte_count = byte_count + 1;
                                        end 
                                        else begin
                                            state_reg = FCS;
                                            byte_count = 0;
                                            updatecrc_reg   = 0;
                                        end
                                    end

                        FCS:        begin
                                        data_crc[(8*(`len_crc-byte_count)-1)-:8]       =    gmii_data_in ;
                                        if (byte_count < `len_crc-1) begin
                                            byte_count = byte_count + 1;
                                        end 
                                        else begin
                                            if (data_crc == crc_check) begin
                                                ncrc_err     = 1;
                                            end else
                                                ncrc_err     = 0;
                                            byte_count= 0;
                                            state_reg = IDLE;
                                        end 
                                    end
                        Err:        begin
                            
                                    end

                        default: state_reg = IDLE;
                    endcase
            end
        end 
    end


    //  Global Synchronous Reset
    always @(posedge clk ) begin
        if (rst) begin
            len_payload                     = 0;
            state_reg                       =IDLE;
            data_buf                        = 0;
            source_addr                     = 0;
            dest_addr                       = 0;
            data_len                        = 0;
            source_addr                     = 0;
            data_len                        = 0;
            data_crc                        = 0;
        end
    end

endmodule

Decapsulation/sim.vcd
$date
	Wed Apr  5 15:04:43 2023
$end
$version
	Icarus Verilog
$end
$timescale
	1ps
$end
$scope module ethernet_decapsulation $end
$var wire 1 ! clk $end
$var wire 8 " gmii_data_in [7:0] $end
$var wire 1 # gmii_dv $end
$var wire 1 $ gmii_en $end
$var wire 1 % gmii_er $end
$var wire 1 & rst $end
$var wire 1 ' rst_crc $end
$var wire 1 ( updatecrc $end
$var wire 1 ) data_out_en $end
$var wire 32 * crc_check [31:0] $end
$var wire 1 + cont_stages $end
$var reg 1 , adr_err $end
$var reg 1 - buffer_full $end
$var reg 14 . byte_count [13:0] $end
$var reg 80 / data_buf [79:0] $end
$var reg 32 0 data_crc [31:0] $end
$var reg 16 1 data_len [15:0] $end
$var reg 48 2 dest_addr [47:0] $end
$var reg 8 3 gmii_buf [7:0] $end
$var reg 1 4 len_err $end
$var reg 16 5 len_payload [15:0] $end
$var reg 1 6 ncrc_err $end
$var reg 1 7 rst_crc_reg $end
$var reg 48 8 source_addr [47:0] $end
$var reg 4 9 state_reg [3:0] $end
$var reg 1 : updatecrc_reg $end
$scope module crc_mod $end
$var wire 1 ! clk $end
$var wire 8 ; data [7:0] $end
$var wire 1 ' rst $end
$var wire 1 ( updatecrc $end
$var reg 5 < bit_n [4:0] $end
$var reg 12 = byte_count [11:0] $end
$var reg 32 > crc_acc [31:0] $end
$var reg 32 ? crc_acc_n [31:0] $end
$var reg 32 @ crc_poly [31:0] $end
$var reg 8 A data_buf [7:0] $end
$var reg 32 B nresult [31:0] $end
$var reg 32 C result [31:0] $end
$scope function crc_bit_updt $end
$var reg 1 D bit $end
$var reg 32 E crc [31:0] $end
$var reg 32 F crc_acc [31:0] $end
$upscope $end
$scope function reflect_byte $end
$var reg 5 G bit_n [4:0] $end
$var reg 8 H data [7:0] $end
$var reg 8 I temp [7:0] $end
$upscope $end
$scope function reflectcrc $end
$var reg 6 J bit_n [5:0] $end
$var reg 32 K crc_acc [31:0] $end
$var reg 32 L temp [31:0] $end
$upscope $end
$scope begin genblk1 $end
$upscope $end
$upscope $end
$upscope $end
$enddefinitions $end
#0
$dumpvars
bx L
bx K
bx J
bx I
bx H
bx G
bx F
bx E
xD
b0 C
b0 B
b0 A
b100110000010001110110110111 @
b11111111111111111111111111111111 ?
b11111111111111111111111111111111 >
b0 =
b0 <
bz ;
0:
b0 9
bx 8
17
x6
b0 5
x4
bx 3
bx 2
bx 1
bx 0
bx /
b0 .
x-
x,
x+
b0 *
1)
0(
1'
z&
z%
z$
z#
bz "
z!
$end
#1
1!
#5001
0!
#10001
b0 0
b0 1
b0 2
b0 8
b0 /
1!
1&
#15001
0!
#20001
1!
#22001
0&
#25001
0!
#30001
1!
#35001
0!
#40001
1!
#45001
0!
#50001
1!
#55001
0!
#60001
1!
#65001
0!
#70001
1!
#75001
0!
#80001
1!
#85001
0!
#87001
0+
0$
#90001
1!
#95001
0!
#100001
1!
#105001
0!
#110001
1+
b101010 "
b101010 ;
0%
1#
1$
1!
#115001
0!
#120001
0)
b1 .
b101010 3
b1 9
1!
#125001
0!
#130001
b10 .
1!
#135001
0!
#140001
b11 .
1!
#145001
0!
#150001
b100 .
1!
#155001
0!
#160001
b101 .
1!
#165001
0!
#170001
b110 .
1!
#175001
0!
#180001
b101011 "
b101011 ;
b0 .
b10 9
1!
#185001
0!
#190001
b10 "
b10 ;
1(
1:
0'
07
b111 9
1!
#195001
0!
#200001
b110101 "
b110101 ;
b1 =
b0 <
b10111111001001111110100100111010 F
b100110000010001110110110111 E
1D
b1111010100011101100111111000011 ?
b1000000 A
b1000000 I
b1000 G
b10 H
b1 .
b100000000000000000000000000000000000000000 2
1!
#205001
0!
#210001
b101000 "
b101000 ;
b10 =
b10 .
b100011010100000000000000000000000000000000 2
1D
b0 <
b11000000100010011110110001110110 F
b10000101110100101100010101011011 ?
b10101100 A
b10101100 I
b1000 G
b110101 H
1!
#215001
0!
#220001
b11111011 "
b11111011 ;
b11 =
1D
b0 <
b11111011111011000011000001001111 F
b11110011000110010111110100101001 ?
b10100 A
b10100 I
b1000 G
b101000 H
b11 .
b100011010100101000000000000000000000000000 2
1!
#225001
0!
#230001
b11011101 "
b11011101 ;
b100 =
b100 .
b100011010100101000111110110000000000000000 2
b0 <
b1011010001010010000001001000010 F
0D
b10110100010100100000010010000100 ?
b11011111 A
b11011111 I
b1000 G
b11111011 H
1!
#235001
0!
#240001
b1100110 "
b1100110 ;
b101 =
1D
b0 <
b10110111010001010001001000000101 F
b1101010010010110011100110111101 ?
b10111011 A
b10111011 I
b1000 G
b11011101 H
b101 .
b100011010100101000111110111101110100000000 2
1!
#245001
0!
#250001
b111 "
b111 ;
b110 =
b1000 9
b0 .
b100011010100101000111110111101110101100110 2
b0 <
b111111000110101001001100110010 F
0D
b1111110001101010010011001100100 ?
b1100110 A
b1100110 I
b1000 G
b1100110 H
1!
#255001
0!
#260001
b100010 "
b100010 ;
b111 =
b0 <
b10110010110101111111111001010 F
0D
b101100101101011111111110010100 ?
b11100000 A
b11100000 I
b1000 G
b111 H
b1 .
b1110000000000000000000000000000000000000000 8
1!
#265001
0!
#270001
b100111 "
b100111 ;
b1000 =
b10 .
b1110010001000000000000000000000000000000000 8
1D
b0 <
b10011101110010011101000101001100 F
b111111010100101011111100101111 ?
b1000100 A
b1000100 I
b1000 G
b100010 H
1!
#275001
0!
#280001
b10101100 "
b10101100 ;
b1001 =
0D
b0 <
b110100001101111101011111000100 F
b1101000011011111010111110001000 ?
b11100100 A
b11100100 I
b1000 G
b100111 H
b11 .
b1110010001000100111000000000000000000000000 8
1!
#285001
0!
#290001
b11011011 "
b11011011 ;
b1010 =
b100 .
b1110010001000100111101011000000000000000000 8
0D
b0 <
b10011011110101101001011101010 F
b100110111101011010010111010100 ?
b110101 A
b110101 I
b1000 G
b10101100 H
1!
#295001
0!
#300001
b1100101 "
b1100101 ;
b1011 =
b0 <
b100110111010000101011111101101 F
0D
b1001101110100001010111111011010 ?
b11011011 A
b11011011 I
b1000 G
b11011011 H
b101 .
b1110010001000100111101011001101101100000000 8
1!
#305001
0!
#310001
b0 "
b0 ;
b1100 =
b11 9
b0 .
b1110010001000100111101011001101101101100101 8
b0 <
b11111001001101001101110001100 F
0D
b111110010011010011011100011000 ?
b10100110 A
b10100110 I
b1000 G
b1100101 H
1!
#315001
0!
#320001
b110010 "
b110010 ;
b1101 =
0D
b0 <
b10100101100010111101010110011010 ?
b1010010110001011110101011001101 F
b0 A
b0 I
b1000 G
b0 H
b1 .
1!
#325001
0!
#330001
b11 "
b11 ;
b1110 =
b100 9
b0 .
b110010 5
b0 <
b110110010110101010011000111011 F
0D
b1101100101101010100110001110110 ?
b1001100 A
b1001100 I
b1000 G
b110010 H
1!
#335001
0!
#340001
b10000 "
b10000 ;
b1111 =
b0 <
b111000101101111101110110110101 F
0D
b1110001011011111011101101101010 ?
b11000000 A
b11000000 I
b1000 G
b11 H
b1 .
1!
#345001
0!
#350001
b1000 "
b1000 ;
b10000 =
b10 .
0D
b0 <
b1010110111000110100001111110100 F
b10101101110001101000011111101000 ?
b1000 A
b1000 I
b1000 G
b10000 H
1!
#355001
0!
#360001
b1001 "
b1001 ;
b10001 =
b0 <
b10100111010110101111111100001101 F
1D
b1001010011101001110001110101101 ?
b10000 A
b10000 I
b1000 G
b1000 H
b11 .
1!
#365001
0!
#370001
b10010 =
b100 .
1D
b0 <
b10100111000110011001011011000100 F
b1001010111100100011000000111111 ?
b10010000 A
b10010000 I
b1000 G
b1001 H
1!
#375001
0!
#380001
b1110 "
b1110 ;
b10011 =
1D
b0 <
b11100100011100000101111111000100 F
b11001100001000011010001000111111 ?
b1000 G
b101 .
1!
#385001
0!
#390001
b1 "
b1 ;
b10100 =
b110 .
0D
b0 <
b1010100110010000001010010001101 F
b10101001100100000010100100011010 ?
b1110000 A
b1110000 I
b1000 G
b1110 H
1!
#395001
0!
#400001
b101 "
b101 ;
b10101 =
1D
b0 <
b10010111000000010010000010101100 F
b101010110000110101110011101111 ?
b10000000 A
b10000000 I
b1000 G
b1 H
b111 .
1!
#405001
0!
#410001
b100 "
b100 ;
b10110 =
b1000 .
0D
b0 <
b1000010111011010110110010011100 F
b10000101110110101101100100111000 ?
b10100000 A
b10100000 I
b1000 G
b101 H
1!
#415001
0!
#420001
b1101 "
b1101 ;
b10111 =
b0 <
b10011100011110010000110001101001 F
1D
b111100001100110000010101100101 ?
b100000 A
b100000 I
b1000 G
b100 H
b1001 .
1!
#425001
0!
#430001
b11 "
b11 ;
b11000 =
b1010 .
0D
b0 <
b110111100000101000111101000101 F
b1101111000001010001111010001010 ?
b10110000 A
b10110000 I
b1000 G
b1101 H
1!
#435001
0!
#440001
b1101 "
b1101 ;
b11001 =
b0 <
b11100100010111111011111000000010 F
1D
b11001100011111100110000110110011 ?
b11000000 A
b11000000 I
b1000 G
b11 H
b1011 .
1!
#445001
0!
#450001
b110 "
b110 ;
b11010 =
b1100 .
b0 <
b11010111100011000001010000011010 F
1D
b10101011110110010011010110000011 ?
b10110000 A
b10110000 I
b1000 G
b1101 H
1!
#455001
0!
#460001
b10000 "
b10000 ;
b11011 =
0D
b0 <
b1010111111110100110110001111100 F
b10101111111101001101100011111000 ?
b1100000 A
b1100000 I
b1000 G
b110 H
b1101 .
1!
#465001
0!
#470001
b101 "
b101 ;
b11100 =
b1110 .
b0 <
b10001111101110001111000111011110 F
1D
b11011101100001111111000001011 ?
b1000 A
b1000 I
b1000 G
b10000 H
1!
#475001
0!
#480001
b1011 "
b1011 ;
b11101 =
1D
b0 <
b10010001001001010010100001010100 F
b100110100010110100110100011111 ?
b10100000 A
b10100000 I
b1000 G
b101 H
b1111 .
1!
#485001
0!
#490001
b1111 "
b1111 ;
b11110 =
b10000 .
1D
b0 <
b10001110010110010101100100000110 F
b11000011100111010111110111011 ?
b11010000 A
b11010000 I
b1000 G
b1011 H
1!
#495001
0!
#500001
b1100 "
b1100 ;
b11111 =
1D
b0 <
b11001010011001111011011010111011 F
b10010000000011100111000011000001 ?
b11110000 A
b11110000 I
b1000 G
b1111 H
b10001 .
1!
#505001
0!
#510001
b1111 "
b1111 ;
b100000 =
b10010 .
0D
b0 <
b1111111101011111100101110000111 F
b11111111010111111001011100001110 ?
b110000 A
b110000 I
b1000 G
b1100 H
1!
#515001
0!
#520001
b1000 "
b1000 ;
b100001 =
1D
b0 <
b10110001100011001101011100000101 F
b1100111110110001011001110111101 ?
b11110000 A
b11110000 I
b1000 G
b1111 H
b10011 .
1!
#525001
0!
#530001
b1 "
b1 ;
b100010 =
b10100 .
b0 <
b10011001000000111100001110001 F
0D
b100110010000001111000011100010 ?
b10000 A
b10000 I
b1000 G
b1000 H
1!
#535001
0!
#540001
b11 "
b11 ;
b100011 =
b0 <
b1010101101011001111110011011110 F
0D
b10101011010110011111100110111100 ?
b10000000 A
b10000000 I
b1000 G
b1 H
b10101 .
1!
#545001
0!
#550001
b100 "
b100 ;
b100100 =
b10110 .
0D
b0 <
b1101111000010111101100011111011 F
b11011110000101111011000111110110 ?
b11000000 A
b11000000 I
b1000 G
b11 H
1!
#555001
0!
#560001
b11 "
b11 ;
b100101 =
b0 <
b11010011001000110101101101011010 F
1D
b10100010100001111010101100000011 ?
b100000 A
b100000 I
b1000 G
b100 H
b10111 .
1!
#565001
0!
#570001
b1001 "
b1001 ;
b100110 =
b11000 .
b0 <
b10010011001001101111000110100111 F
1D
b100010100011001111111011111001 ?
b11000000 A
b11000000 I
b1000 G
b11 H
1!
#575001
0!
#580001
b1110 "
b1110 ;
b100111 =
0D
b0 <
b11100001000010010011110001000 F
b111000010000100100111100010000 ?
b10010000 A
b10010000 I
b1000 G
b1001 H
b11001 .
1!
#585001
0!
#590001
b110 "
b110 ;
b101000 =
b11010 .
1D
b0 <
b10101010000000000100100000111100 F
b1010000110000011000110111001111 ?
b1110000 A
b1110000 I
b1000 G
b1110 H
1!
#595001
0!
#600001
b111 "
b111 ;
b101001 =
b0 <
b1010110111111101000101001000 F
0D
b10101101111111010001010010000 ?
b1100000 A
b1100000 I
b1000 G
b110 H
b11011 .
1!
#605001
0!
#610001
b1001 "
b1001 ;
b101010 =
b11100 .
b0 <
b10000111011111000001100110001 F
0D
b100001110111110000011001100010 ?
b11100000 A
b11100000 I
b1000 G
b111 H
1!
#615001
0!
#620001
b1010 "
b1010 ;
b101011 =
b0 <
b10110001000111000111011110111111 F
1D
b1100110111110011111001011001001 ?
b10010000 A
b10010000 I
b1000 G
b1001 H
b11101 .
1!
#625001
0!
#630001
b10 "
b10 ;
b101100 =
b11110 .
b0 <
b11011101000110111010010010001 F
0D
b110111010001101110100100100010 ?
b1010000 A
b1010000 I
b1000 G
b1010 H
1!
#635001
0!
#640001
b10000 "
b10000 ;
b101101 =
0D
b0 <
b1011100000011010011011111110001 F
b10111000000110100110111111100010 ?
b1000000 A
b1000000 I
b1000 G
b10 H
b11111 .
1!
#645001
0!
#650001
b1000 "
b1000 ;
b101110 =
b100000 .
b0 <
b1010011101010001011011110111111 F
0D
b10100111010100010110111101111110 ?
b1000 A
b1000 I
b1000 G
b10000 H
1!
#655001
0!
#660001
b110 "
b110 ;
b101111 =
b0 <
b11111011011010111101111101100110 F
1D
b11110010000101101010001101111011 ?
b10000 A
b10000 I
b1000 G
b1000 H
b100001 .
1!
#665001
0!
#670001
b11 "
b11 ;
b110000 =
b100010 .
0D
b0 <
b11101000111100011110111111000 F
b111010001111000111101111110000 ?
b1100000 A
b1100000 I
b1000 G
b110 H
1!
#675001
0!
#680001
b1001 "
b1001 ;
b110001 =
b0 <
b11001111010001000110001100110100 F
1D
b10011010010010011101101111011111 ?
b11000000 A
b11000000 I
b1000 G
b11 H
b100011 .
1!
#685001
0!
#690001
b1000 "
b1000 ;
b110010 =
b100100 .
b0 <
b110011001010001000010011101011 F
0D
b1100110010100010000100111010110 ?
b10010000 A
b10010000 I
b1000 G
b1001 H
1!
#695001
0!
#700001
b10000 "
b10000 ;
b110011 =
1D
b0 <
b11010111111111010100110111110001 F
b10101011001110111000011001010101 ?
b10000 A
b10000 I
b1000 G
b1000 H
b100101 .
1!
#705001
0!
#710001
b1011 "
b1011 ;
b110100 =
b100110 .
1D
b0 <
b11100001100101011001110000110000 F
b11000111111010100010010111010111 ?
b1000 A
b1000 I
b1000 G
b10000 H
1!
#715001
0!
#720001
b111 "
b111 ;
b110101 =
b0 <
b11011110010110010010000011100001 F
1D
b10111000011100110101110001110101 ?
b11010000 A
b11010000 I
b1000 G
b1011 H
b100111 .
1!
#725001
0!
#730001
b110 "
b110 ;
b110110 =
b101000 .
b0 <
b10010100100000010001011100000100 F
1D
b101101110000110011001110111111 ?
b11100000 A
b11100000 I
b1000 G
b111 H
1!
#735001
0!
#740001
b1011 "
b1011 ;
b110111 =
b0 <
b1100011001111000010010011010010 F
0D
b11000110011110000100100110100100 ?
b1100000 A
b1100000 I
b1000 G
b110 H
b101001 .
1!
#745001
0!
#750001
b1010 "
b1010 ;
b111000 =
b101010 .
0D
b0 <
b10111011011110001100101100001 F
b101110110111100011001011000010 ?
b11010000 A
b11010000 I
b1000 G
b1011 H
1!
#755001
0!
#760001
b10 "
b10 ;
b111001 =
1D
b0 <
b10000011011001001011000100101101 F
b10000010000111111111101101 ?
b1010000 A
b1010000 I
b1000 G
b1010 H
b101011 .
1!
#765001
0!
#770001
b101 "
b101 ;
b111010 =
b101100 .
b0 <
b10011000110111010101110111010111 F
1D
b110101011110111010011000011001 ?
b1000000 A
b1000000 I
b1000 G
b10 H
1!
#775001
0!
#780001
b1100 "
b1100 ;
b111011 =
1D
b0 <
b10100110110111111010101000100001 F
b1001001011111100100100111110101 ?
b10100000 A
b10100000 I
b1000 G
b101 H
b101101 .
1!
#785001
0!
#790001
b10 "
b10 ;
b111100 =
b101110 .
b0 <
b1011110000110100000110001110100 F
0D
b10111100001101000001100011101000 ?
b110000 A
b110000 I
b1000 G
b1100 H
1!
#795001
0!
#800001
b101 "
b101 ;
b111101 =
b0 <
b11000110001101101100100111101101 F
1D
b10001000101011001000111001101101 ?
b1000000 A
b1000000 I
b1000 G
b10 H
b101111 .
1!
#805001
0!
#810001
b111110 =
b110000 .
b0 <
b1001010100101001101100101100 F
0D
b10010101001010011011001011000 ?
b10100000 A
b10100000 I
b1000 G
b101 H
1!
#815001
0!
#820001
b1101 "
b1101 ;
b111111 =
b0 <
b1000110001010111011100001000 F
0D
b10001100010101110111000010000 ?
b1000 G
b110001 .
1!
#825001
0!
#830001
b1100010 "
b1100010 ;
b1000000 =
b1100010001001011111111100000001 *
b1100010001001011111111100000001 C
b101 9
0(
0:
b0 .
b1100010001001011111111100000001 B
b10011101110110100000000011111110 L
b100000 J
b1111111000000000101101110111001 K
b0 <
b10111101111000001010001100000111 F
1D
b1111111000000000101101110111001 ?
b10110000 A
b10110000 I
b1000 G
b1101 H
1!
#835001
0!
#840001
b100101 "
b100101 ;
b1 .
b1100010000000000000000000000000 0
1!
#845001
0!
#850001
b11111111 "
b11111111 ;
b10 .
b1100010001001010000000000000000 0
1!
#855001
0!
#860001
b1 "
b1 ;
b11 .
b1100010001001011111111100000000 0
1!
#865001
0!
#870001
1)
b0 9
b0 .
16
b1100010001001011111111100000001 0
1!
#875001
0!
#880001
0)
b1 .
b1 3
b1 9
1!
#885001
0!
#890001
b0 A
b0 B
b11111111111111111111111111111111 ?
b0 =
b0 *
b0 C
b10 .
1'
17
1!
#895001
0!
#900001
b11 .
1!
#905001
0!
#910001
b100 .
1!
#915001
0!
#920001
b101 .
1!
#925001
0!
#930001
b110 .
1!
#935001
0!
#940001
b0 .
b10 9
1!
#945001
0!
#950001
1(
1:
0'
07
b111 9
1!
#955001
0!
#960001
b1 =
b0 <
b10011100000100010111110101101 F
0D
b100111000001000101111101011010 ?
b10000000 A
b10000000 I
b1000 G
b1 H
b1 .
b10011010100101000111110111101110101100110 2
1!
#965001
0!
#970001
b10 =
b10 .
b10000000100101000111110111101110101100110 2
b0 <
b11110111111110110010000011011110 F
1D
b11101011001101110101110000001011 ?
b1000 G
1!
#975001
0!
#980001
b11 =
b0 <
b1011000010110010000001101111011 F
0D
b10110000101100100000011011110110 ?
b1000 G
b11 .
b10000000100000001111110111101110101100110 2
1!
#985001
0!
#990001
b100 =
b100 .
b10000000100000001000000011101110101100110 2
0D
b0 <
b110011000110100100110111001000 F
b1100110001101001001101110010000 ?
b1000 G
1!
#995001
0!
#1000001
b101 =
b0 <
b11110111101110101111001100111110 F
1D
b11101011101101001111101111001011 ?
b1000 G
b101 .
b10000000100000001000000010000000101100110 2
1!
#1005001
0!
#1010001
b110 =
b1000 9
b0 .
b10000000100000001000000010000000100000001 2
b0 <
b11001100010101110001101111011 F
0D
b110011000101011100011011110110 ?
b1000 G
1!
#1015001
0!
#1020001
b111 =
b0 <
b11010000101111010010000000001000 F
1D
b10100101101110110101110110100111 ?
b1000 G
b1 .
b10010001000100111101011001101101101100101 8
1!
#1025001
0!
#1030001
b1000 =
b10 .
b10000000100100111101011001101101101100101 8
b0 <
b10011000001111010011001110011110 F
1D
b110100101110110111101010001011 ?
b1000 G
1!
#1035001
0!
#1040001
b1001 =
0D
b0 <
b1010101000000011100001010001 F
b10101010000000111000010100010 ?
b1000 G
b11 .
b10000000100000001101011001101101101100101 8
1!
#1045001
0!
#1050001
b1010 =
b100 .
b10000000100000001000000011101101101100101 8
b0 <
b10111011001101001111011110100001 F
1D
b1110010101010001111001011110101 ?
b1000 G
1!
#1055001
0!
#1060001
b1011 =
1D
b0 <
b10010110000001001001011101101000 F
b101000110010000011001101100111 ?
b1000 G
b101 .
b10000000100000001000000010000000101100101 8
1!
#1065001
0!
#1070001
b1100 =
b11 9
b0 .
b10000000100000001000000010000000100000001 8
0D
b0 <
b1111100010100110111001011011 F
b11111000101001101110010110110 ?
b1000 G
1!
#1075001
0!
#1080001
b1101 =
b0 <
b10000110101001111001011011001010 F
1D
b1001100011100011000000100011 ?
b1000 G
b1 .
b100110010 5
1!
#1085001
0!
#1090001
b1110 =
b100 9
b0 .
b100000001 5
1D
b0 <
b11100000100110100001011100101011 F
b11000101111101010011001111100001 ?
b1000 G
1!
#1095001
0!
#1100001
b1111 =
b0 <
b1101011001110000111110100001110 F
0D
b11010110011100001111101000011100 ?
b1000 G
b1 .
1!
#1105001
0!
#1110001
b10000 =
b10 .
1D
b0 <
b10001011000101010111001110000001 F
b10010111010111111101010110101 ?
b1000 G
1!
#1115001
0!
#1120001
b10001 =
0D
b0 <
b1100011101100101101101011111000 F
b11000111011001011011010111110000 ?
b1000 G
b11 .
1!
#1125001
0!
#1130001
b10010 =
b100 .
0D
b0 <
b100111101110100110100000111001 F
b1001111011101001101000001110010 ?
b1000 G
1!
#1135001
0!
#1140001
b10011 =
b0 <
b1000100010101010111110010010 F
0D
b10001000101010101111100100100 ?
b1000 G
b101 .
1!
#1145001
0!
#1150001
b10100 =
b110 .
b0 <
b10011000001000010000111111001111 F
1D
b110100100000110000001000101001 ?
b1000 G
1!
#1155001
0!
#1160001
b10101 =
0D
b0 <
b10110100111000110100101010001 F
b101101001110001101001010100010 ?
b1000 G
b111 .
1!
#1165001
0!
#1170001
b10110 =
b1000 .
b0 <
b11111110011110001011011110110101 F
1D
b11111000001100000111001011011101 ?
b1000 G
1!
#1175001
0!
#1180001
b10111 =
b0 <
b11111001000001111001100001110100 F
1D
b11110110110011100010110101011111 ?
b1000 G
b1001 .
1!
#1185001
0!
