Encapsulation/utils.vh
`define min_payload_len                 16'd46
`define len_addr                        13'd6
`define len_len                         13'd2
`define len_crc                         13'd4
`define len_perm                        13'd7
`define len_max_payload                 50

Decapsulation/decapsulation.v
`include "utils.vh"

module ethernet_decapsulation 
#(
    parameter [47:0] destination_mac_addr  = 48'h023528fbdd66,
    parameter [47:0] source_mac_addr       = 48'h072227acdb65
)
(
    // Output Payload
    output  reg     crc_err,adr_err,len_err, buffer_full,
    output data_out_en,
    input test_in,
    // Ethernet RX Transmission ports
    input [7:0]     gmii_data_in,
    input           gmii_dv,gmii_er,gmii_en,clk,rst
);

// Dump waveforms with makefile
`ifdef COCOTB_SIM
initial begin
    $dumpfile("sim.vcd");
    $dumpvars(0,ethernet_decapsulation);
end    
`endif

    //  Define Registers
    reg         [3:0]                   state_reg = 0;                               // FSM State register, keep track of frame section 
    reg         [8*10-1:0]              data_buf;                                    // Payload Buffer that holds data
    reg         [13:0]                  byte_count = 0;                              // Track bytes in each state
    reg         [31:0]                 crc_res     = {(`len_crc){1'b1}};             // Initate CRC, update with every processed byte
    reg         [15:0]                 len_payload = 0;                              // Keep track of every Recived Payload Length
    
    wire                               cont_stages;
    reg         [8*`len_addr-1:0]                  source_addr;
    reg         [8*`len_addr-1:0]                  dest_addr;
    reg         [8*`len_len-1:0]                    data_len;                       
    reg         [8*`len_crc-1:0]                    data_crc;  
    reg         [7:0] gmii_buf;

    //  Ethernet Frame Encapsulation Stages
    localparam  IDLE                = 4'd0,
                PERMABLE            = 4'd1,
                SDF                 = 4'd2,  
                LEN                 = 4'd3,
                PAYLOAD             = 4'd4,  
                FCS                 = 4'd5,
                EXT                 = 4'd6,
                Dest_MAC            = 4'd7,
                Source_Mac          = 4'd8,
                Err                 = 4'd9;

    localparam Permable_val = 8'b101010,                            
               Start_Del_val= 8'b101011;                                            // IEEE defined Permable and Delimeter bytes


    assign data_out_en = (state_reg == IDLE)? 1'b1:1'b0;
    // Bufferred Data should not be transmitted while still receiving
    assign cont_stages = (gmii_en && gmii_dv && !(gmii_er))? 1'b1:1'b0 ;

    // Select the right output according to stages

    // Ethernet Frame Stages
    always @(posedge clk) begin
        if (!rst) begin
            if (gmii_en) begin
                    case (state_reg)
                        IDLE:       begin
                                        if (gmii_en && gmii_dv) begin
                                            state_reg   = PERMABLE;
                                            gmii_buf    = gmii_data_in;
                                            byte_count  = byte_count +1;
                                        end
                                        else if (gmii_er) begin
                                            state_reg =Err;
                                            byte_count  = 0;
                                        end
                                    end 
                        PERMABLE:   begin
                                        if(byte_count < `len_perm-1 ) begin
                                            byte_count  = byte_count +1;
                                        end 
                                        else begin
                                            state_reg = SDF;
                                            byte_count = 0;
                                        end
                                    end
                        SDF:  begin
                                        state_reg   = Dest_MAC;
                                    end
                        Dest_MAC:   begin
                                        dest_addr[(8*(`len_addr-byte_count)-1)-:8]         =    gmii_data_in ; 
                                        if (byte_count < `len_addr-1) begin
                                            byte_count = byte_count + 1;
                                        end 
                                        else begin
                                            byte_count= 0;
                                            state_reg = Source_Mac;
                                        end
                                    end
                        Source_Mac: begin
                                        source_addr[(8*(`len_addr-byte_count)-1)-:8]       =    gmii_data_in ;
                                        if (byte_count < `len_addr-1) begin
                                            byte_count = byte_count + 1;
                                        end 
                                        else begin
                                            byte_count= 0;
                                            state_reg = LEN;
                                        end  
                                    end
                        LEN:        begin
                                        if (byte_count < `len_len-1) begin
                                            byte_count = byte_count + 1;
                                        end 
                                        else begin
                                            byte_count= 0;
                                            state_reg = PAYLOAD;
                                        end  
                                    end
                        PAYLOAD:    begin
                                        if (byte_count < len_payload-1) begin
                                            byte_count = byte_count + 1;
                                            state_reg = PAYLOAD;
                                        end 
                                        else begin
                                            byte_count= 0;
                                            if (len_payload <= `min_payload_len)
                                                state_reg = EXT;
                                            else
                                                state_reg = FCS;
                                        end  
                                    end

                        EXT:        begin
                                        if (byte_count < `min_payload_len-len_payload-1) begin
                                            byte_count = byte_count + 1;
                                        end 
                                        else begin
                                            state_reg = FCS;
                                            byte_count = 0;
                                        end
                                    end

                        FCS:        begin
                                        if (byte_count < `len_crc-1) begin
                                            byte_count = byte_count + 1;
                                        end 
                                        else begin
                                            byte_count= 0;
                                            state_reg = IDLE;
                                        end 
                                    end
                        Err:        begin
                            
                                    end

                        default: state_reg = IDLE;
                    endcase
            end
        end 
    end


    //  Global Synchronous Reset
    always @(posedge clk ) begin
        if (rst) begin
            len_payload                     = 0;
            state_reg                       =IDLE;
            data_buf                        = 0;
            crc_res                         = {(`len_crc){1'b1}};
            source_addr                     = 0;
            dest_addr                       = 0;
            data_len                        = 0;
            data_crc                        = 0;
            source_addr                     = 0;
            data_len                        = 0;
            data_crc                        = 0;
        end
    end

    reg [3:0] Test = 0;

    always @(posedge clk ) begin
        if (test_in) begin
            Test = Test + 1;
        end
    end

endmodule

Decapsulation/sim.vcd
$date
	Fri Mar 31 14:58:44 2023
$end
$version
	Icarus Verilog
$end
$timescale
	1ps
$end
$scope module ethernet_decapsulation $end
$var wire 1 ! clk $end
$var wire 8 " gmii_data_in [7:0] $end
$var wire 1 # gmii_dv $end
$var wire 1 $ gmii_en $end
$var wire 1 % gmii_er $end
$var wire 1 & rst $end
$var wire 1 ' test_in $end
$var wire 1 ( data_out_en $end
$var wire 1 ) cont_stages $end
$var reg 4 * Test [3:0] $end
$var reg 1 + adr_err $end
$var reg 1 , buffer_full $end
$var reg 14 - byte_count [13:0] $end
$var reg 1 . crc_err $end
$var reg 32 / crc_res [31:0] $end
$var reg 80 0 data_buf [79:0] $end
$var reg 32 1 data_crc [31:0] $end
$var reg 16 2 data_len [15:0] $end
$var reg 48 3 dest_addr [47:0] $end
$var reg 8 4 gmii_buf [7:0] $end
$var reg 1 5 len_err $end
$var reg 16 6 len_payload [15:0] $end
$var reg 48 7 source_addr [47:0] $end
$var reg 4 8 state_reg [3:0] $end
$upscope $end
$enddefinitions $end
#0
$dumpvars
b0 8
bx 7
b0 6
x5
bx 4
bx 3
bx 2
bx 1
bx 0
b1111 /
x.
b0 -
x,
x+
b0 *
x)
1(
z'
z&
z%
z$
z#
bz "
1!
$end
#5000
0!
#10000
b0 1
b0 2
b0 3
b0 7
b0 0
1!
1&
#15000
0!
#20000
1!
#22000
0&
#25000
0!
#30000
1!
#35000
0!
#40000
1!
#45000
0!
#50000
1!
#55000
0!
#60000
1!
#65000
0!
#70000
1!
#75000
0!
#80000
1!
#85000
0!
#87000
0)
0$
#90000
1!
#95000
0!
#100000
1!
#105000
0!
#110000
1)
b101010 "
0%
1#
1$
1!
#115000
0!
#120000
0(
b1 -
b101010 4
b1 8
1!
#125000
0!
#130000
b10 -
1!
#135000
0!
#140000
b11 -
1!
#145000
0!
#150000
b100 -
1!
#155000
0!
#160000
b101 -
1!
#165000
0!
#170000
b110 -
1!
#175000
0!
#180000
b101011 "
b0 -
b10 8
1!
#185000
0!
#190000
b10 "
b111 8
1!
#195000
0!
#200000
b110101 "
b1 -
b100000000000000000000000000000000000000000 3
1!
#205000
0!
#210000
b101000 "
b10 -
b100011010100000000000000000000000000000000 3
1!
#215000
0!
#220000
b11111011 "
b11 -
b100011010100101000000000000000000000000000 3
1!
#225000
0!
#230000
b11011101 "
b100 -
b100011010100101000111110110000000000000000 3
1!
#235000
0!
#240000
b1100110 "
b101 -
b100011010100101000111110111101110100000000 3
1!
#245000
0!
#250000
b111 "
b1000 8
b0 -
b100011010100101000111110111101110101100110 3
1!
#255000
0!
#260000
b100010 "
b1 -
b1110000000000000000000000000000000000000000 7
1!
#265000
0!
#270000
b100111 "
b10 -
b1110010001000000000000000000000000000000000 7
1!
#275000
0!
#280000
b10101100 "
b11 -
b1110010001000100111000000000000000000000000 7
1!
#285000
0!
#290000
b11011011 "
b100 -
b1110010001000100111101011000000000000000000 7
1!
#295000
0!
#300000
b1100101 "
b101 -
b1110010001000100111101011001101101100000000 7
1!
#305000
0!
#310000
b0 "
b11 8
b0 -
b1110010001000100111101011001101101101100101 7
1!
#315000
0!
#320000
b1100100 "
b1 -
1!
#325000
0!
#330000
b100 8
b0 -
1!
#331001
0!
#332001
b1 -
1!
#333001
0!
#334001
b10 -
1!
#335001
0!
#336001
b11 -
1!
#337001
0!
#338001
b100 -
1!
#339001
0!
#340001
1(
b0 3
b0 7
b0 8
1!
1&
#341001
0!
#342001
1!
#343001
0!
#344001
1!
#345001
0!
#346001
1!
#347001
0!
#348001
1!
#349001
0!
#350001
1!
#351001
0!
#352001
0(
b101 -
b1100100 4
b1 8
1!
0&
#353001
0!
#354001
b110 -
1!
#355001
0!
#356001
b0 -
b10 8
1!
#357001
0!
#358001
b111 8
1!
#359001
0!
#360001
b1 -
b11001000000000000000000000000000000000000000000 3
1!
#361001
0!
#362001
b10 -
b11001000110010000000000000000000000000000000000 3
1!
#363001
0!
#364001
b11 -
b11001000110010001100100000000000000000000000000 3
1!
#365001
0!
#366001
b100 -
b11001000110010001100100011001000000000000000000 3
1!
#367001
0!
#368001
b101 -
b11001000110010001100100011001000110010000000000 3
1!
#369001
0!
#370001
b1000 8
b0 -
b11001000110010001100100011001000110010001100100 3
1!
