cocotb_Test/action/crc32_comb.v
module crc32_comb
#(parameter crc_len =32, parameter crc =  32'h04C11DB7, parameter GMII = 1, parameter datalen = 8, parameter refin = 1, parameter refout = 1,parameter byte_len =9)
(
input updatecrc,                                                    
output reg [crc_len-1:0]result,
input clk,rst,strt,
input  [datalen-1:0] data
);

reg [crc_len-1:0]   crc_poly        = crc;
reg [crc_len-1:0]   crc_acc         = {(crc_len){1'b1}};  //Initiate acc
reg [11:0]          byte_count =0;                                  //Keep track of bytes
reg [4:0]           bit_n = 0;                                      //Keep track of bites
reg [crc_len-1:0]   nresult  ;
reg [datalen-1:0] data_buf;
reg [crc_len-1:0] crc_acc_n;


`ifdef COCOTB_SIM
initial begin
    $dumpfile("sim.vcd");
    $dumpvars(0,crc32_comb);
end    
`endif


generate if (GMII) begin
        
            always @(*) begin

                if(rst) begin
                    crc_acc     <= {(crc_len){1'b1}};
                    result      <=  0;
                    byte_count  <=  0;
                    crc_acc_n   <= {(crc_len){1'b1}};
                    nresult     <=  0;
                    data_buf    <=  0;
                    bit_n       <=  0;
                end

                else begin
                    result = nresult;
                end
            end

            always @(posedge clk) begin
                if (updatecrc) begin
                    $display("\n Recived Message \t   %h, \t %b \t %d",data,data,data_buf);

                    data_buf = reflect_byte(data[datalen-1:0]);
                    $display("\n Reversed Message \t  %h, \t %b \t %d",data_buf,data_buf,data_buf);


                    crc_acc_n =  {data_buf,{(crc_len-datalen){1'b0}}}^ crc_acc_n;
                    $display("1|| \t CRC \t %h, \t %b", crc_acc_n ,crc_acc_n );
                    
                    for (bit_n = 0; bit_n <datalen ; bit_n =bit_n +1 ) begin // loop count = datalen-crc+1 d = 8, crc = 4 , loop = 7
                        crc_acc_n = crc_bit_updt(crc_acc_n[crc_len-1:0],crc[crc_len-1:0],crc_acc_n[crc_len-1]);
                    $display("2_ %d|| \t CRC %h, \t %b", bit_n,crc_acc_n ,crc_acc_n );
                    end
                    bit_n       <=  0;
                    byte_count <= byte_count + 1;
                    $display("3 Byte Count incremented \t %d", byte_count);
                end
                    if(byte_count == byte_len-1) begin
                        nresult      =  ~reflectcrc(crc_acc_n[crc_len-1:0]);
                    end
            end
end endgenerate


function [crc_len-1:0]crc_bit_updt (input [crc_len-1:0]crc_acc, input [crc_len-1:0]crc, input bit);
    begin
       
        if (bit) begin
            crc_bit_updt =   (crc_acc << 1);
            crc_bit_updt =   (crc_bit_updt ^ crc) ;
        end
        else begin
             crc_bit_updt = crc_acc << 1;
        end
    end
endfunction

function [datalen-1:0]reflect_byte (input [datalen-1:0]data);
reg [datalen-1:0]       temp;
reg [4:0]              bit_n;
    begin
       for (bit_n = 0; bit_n <datalen ; bit_n =bit_n +1 ) begin
            temp[bit_n] = data[datalen-1-bit_n];
       end
    reflect_byte = temp;
    end
endfunction

function [crc_len-1:0]reflectcrc (input [crc_len-1:0]crc_acc);
reg [crc_len-1:0]       temp;
reg [5:0]              bit_n;
    begin
       for (bit_n = 0; bit_n <crc_len ; bit_n =bit_n +1 ) begin
            temp[bit_n] = crc_acc[crc_len-1-bit_n];
       end
    reflectcrc = temp;
    end
endfunction

endmodule

cocotb_Test/CRC_32_Simple/sim.vcd
$date
	Wed Mar 29 13:03:53 2023
$end
$version
	Icarus Verilog
$end
$timescale
	1ps
$end
$scope module crc32_comb $end
$var wire 1 ! clk $end
$var wire 8 " data [7:0] $end
$var wire 1 # rst $end
$var wire 1 $ strt $end
$var wire 1 % updatecrc $end
$var reg 5 & bit_n [4:0] $end
$var reg 12 ' byte_count [11:0] $end
$var reg 32 ( crc_acc [31:0] $end
$var reg 32 ) crc_acc_n [31:0] $end
$var reg 32 * crc_poly [31:0] $end
$var reg 8 + data_buf [7:0] $end
$var reg 32 , nresult [31:0] $end
$var reg 32 - result [31:0] $end
$scope function crc_bit_updt $end
$var reg 1 . bit $end
$var reg 32 / crc [31:0] $end
$var reg 32 0 crc_acc [31:0] $end
$upscope $end
$scope function reflect_byte $end
$var reg 5 1 bit_n [4:0] $end
$var reg 8 2 data [7:0] $end
$var reg 8 3 temp [7:0] $end
$upscope $end
$scope function reflectcrc $end
$var reg 6 4 bit_n [5:0] $end
$var reg 32 5 crc_acc [31:0] $end
$var reg 32 6 temp [31:0] $end
$upscope $end
$scope begin genblk1 $end
$upscope $end
$upscope $end
$enddefinitions $end
#0
$dumpvars
bx 6
bx 5
bx 4
bx 3
bx 2
bx 1
bx 0
bx /
x.
b0 -
b0 ,
b0 +
b100110000010001110110110111 *
b11111111111111111111111111111111 )
b11111111111111111111111111111111 (
b0 '
b0 &
z%
1$
1#
bz "
1!
$end
#1000
0!
#2000
1!
#3000
0!
#4000
1!
#5000
0!
#6000
1!
#7000
0!
#8000
1!
#9000
0!
#10000
1!
0#
#11000
0!
#12000
1!
#13000
0!
#14000
1!
#15000
0!
#16000
1!
#17000
0!
#18000
1!
#19000
0!
#20000
1!
b110001 "
#21000
0!
#22000
b1 '
b0 &
b1001000001000110001000011111 0
b100110000010001110110110111 /
0.
b10010000010001100010000111110 )
b10001100 +
b10001100 3
b1000 1
b110001 2
1!
1%
#23000
0!
#24000
1!
b110010 "
0%
#25000
0!
#26000
b10 '
1.
b0 &
b10100100000011100001010001011101 0
b1001100110111010011010100001101 )
b1001100 +
b1001100 3
b1000 1
b110010 2
1!
1%
#27000
0!
#28000
1!
b110011 "
0%
#29000
0!
#30000
b11 '
0.
b0 &
b1011010000111001111011011110111 0
b10110100001110011110110111101110 )
b11001100 +
b11001100 3
b1000 1
b110011 2
1!
1%
#31000
0!
#32000
1!
b110100 "
0%
#33000
0!
#34000
b100 '
b0 &
b11101011111000001110000010011 0
0.
b111010111110000011100000100110 )
b101100 +
b101100 3
b1000 1
b110100 2
1!
1%
#35000
0!
#36000
1!
b110101 "
0%
#37000
0!
#38000
b101 '
b0 &
b1100011110100011010100000010110 0
0.
b11000111101000110101000000101100 )
b10101100 +
b10101100 3
b1000 1
b110101 2
1!
1%
#39000
0!
#40000
1!
b110110 "
0%
#41000
0!
#42000
b110 '
b0 &
b10111110111110101101011001101100 0
1.
b1111001001101001011000101101111 )
b1101100 +
b1101100 3
b1000 1
b110110 2
1!
1%
#43000
0!
#44000
1!
b110111 "
0%
#45000
0!
#46000
b111 '
1.
b0 &
b10000001010101000001000100100001 0
b110011010010011111111110101 )
b11101100 +
b11101100 3
b1000 1
b110111 2
1!
1%
#47000
0!
#48000
1!
b111000 "
0%
#49000
0!
#50000
b1000 '
b0 &
b101010100100111110001010011 0
0.
b1010101001001111100010100110 )
b11100 +
b11100 3
b1000 1
b111000 2
1!
1%
#51000
0!
#52000
b10011010111000001101101010101111 -
b10011010111000001101101010101111 ,
b1100101000111110010010101010000 6
b100000 4
b1010101001001111100010100110 5
1!
b111001 "
0%
#53000
0!
#54000
b1001 '
b11001011111101000011100100100110 -
b11001011111101000011100100100110 ,
b110100000010111100011011011001 6
b100000 4
b10011011011000111101000000101100 5
b0 &
b1001101101100011110100000010110 0
0.
b10011011011000111101000000101100 )
b10011100 +
b10011100 3
b1000 1
b111001 2
1!
1%
#55000
0!
#56000
1!
0%
